Workbook
Name EOLSearch: 'Search List'!$C$2:$C$4
Name SearchType: #REF!
Name SearchType: 'Search List'!$A$2:$A$4

Sheet Disclaimer
A1: The National Renewable Energy Laboratory (NREL) is operated for the U.S. Department of Energy (DOE) by Alliance for Sustainable Energy, LLC ("Alliance"). NAATBatt International (NAATBatt) is the trade association for the advanced battery industry in North America.
A3: Access to or use of any data or software made available on this server ("Data") shall impose the following obligations on the user, and use of the Data constitutes user's agreement to these terms. The user is granted the right, without any fee or cost, to use or copy the Data, provided that this entire notice appears in all copies of the Data. Further, the user agrees to credit DOE/NREL/ALLIANCE/NAATBatt in any publication that results from the use of the Data. The names DOE/NREL/ALLIANCE/NAATBatt, however, may not be used in any advertising or publicity to endorse or promote any products or commercial entities unless specific written permission is obtained from DOE/NREL/ ALLIANCE/NAATBatt. The user also understands that DOE/NREL/ALLIANCE/NAATBatt are not obligated to provide the user with any support, consulting, training or assistance of any kind with regard to the use of the Data or to provide the user with any updates, revisions or new versions thereof. DOE, NREL,ALLIANCE, and NAATBatt do not guarantee or endorse any results generated by use of the Data, and user is entirely responsible for the results and any reliance on the results or the Data in general.
A5: USER AGREES TO INDEMNIFY DOE/NREL/ALLIANCE/NAATBATT AND THEIR RESPECTIVE SUBSIDIARIES, AFFILIATES, OFFICERS, AGENTS, AND EMPLOYEES AGAINST ANY CLAIM OR DEMAND, INCLUDING REASONABLE ATTORNEYS' FEES, RELATED TO USER'S USE OF THE DATA. THE DATA ARE PROVIDED BY DOE/NREL/ALLIANCE/NAATBATT "AS IS," AND ANY EXPRESS OR IMPLIED WARRANTIES, INCLUDING BUT NOT LIMITED TO THE IMPLIED WARRANTIES OF MERCHANTABILITY AND FITNESS FOR A PARTICULAR PURPOSE ARE DISCLAIMED. DOE/NREL/ALLIANCE/NAATBATTASSUME NO LEGAL LIABILITY OR RESPONSIBILITY FOR THE ACCURACY, COMPLETENESS, OR USEFULNESS OF THE DATA, OR REPRESENT THAT ITS USE WOULD NOT INFRINGE PRIVATELY OWNED RIGHTS. IN NO EVENT SHALL DOE/NREL/ALLIANCE/NAATBATT BE LIABLE FOR ANY SPECIAL, INDIRECT OR CONSEQUENTIAL DAMAGES OR ANY DAMAGES WHATSOEVER, INCLUDING BUT NOT LIMITED TO CLAIMS ASSOCIATED WITH THE LOSS OF DATA OR PROFITS, THAT MAY RESULT FROM AN ACTION IN CONTRACT, NEGLIGENCE OR OTHER TORTIOUS CLAIM THAT ARISES OUT OF OR IN CONNECTION WITH THE ACCESS, USE OR PERFORMANCE OF THE DATA.
A7: Contributers: Vicky Putsche, Erik Witter, Shriram Santhanagopalan, Maggie Mann, Sara Dunn, Beth Monk, Michael Khalfin and Ahmad A. Pesaran National Renewable Energy Laboratory Version 3 December 7, 2022 NAATBatt International funded this project under two Technical Services Agreements (TSA-21-17854, TSA-21-21593, and TSA-25-33176) with NREL

Sheet User Agreement 
B3: To access and use the Database, you are required to provide certain information and/or answer certain questions and need to accept the terms of the End User License Agreement

Sheet SummaryTable
A1: Current as of: | E1: March 27, 2026
A3: Supply Chain Segment | B3: US | D3: Canada | F3: Other | H3: Total | L3: Canada
B4: Companies | C4: Facilities | D4: Companies | E4: Facilities | F4: Companies | G4: Facilities | H4: Companies | I4: Facilities | L4: US
A5: Raw Material Manufacturing | B5: {=IFERROR(ROWS(_xlfn.UNIQUE(_xlfn._xlws.FILTER('Raw Materials'!$D$2:$D$104,'Raw Materials'!$M$2:$M$104=B3))),0)} -> 42 | C5: {=IFERROR(ROWS(_xlfn.UNIQUE(_xlfn._xlws.FILTER('Raw Materials'!$F$2:$F$104,'Raw Materials'!$M$2:$M$104=B3))),0)} -> 46 | D5: {=IFERROR(ROWS(_xlfn.UNIQUE(_xlfn._xlws.FILTER('Raw Materials'!$D$2:$D$104,'Raw Materials'!$M$2:$M$104=D3))),0)} -> 28 | E5: {=IFERROR(ROWS(_xlfn.UNIQUE(_xlfn._xlws.FILTER('Raw Materials'!$F$2:$F$104,'Raw Materials'!$M$2:$M$104=D3))),0)} -> 41 | F5: {=IFERROR(ROWS(_xlfn.UNIQUE(_xlfn._xlws.FILTER('Raw Materials'!$D$2:$D$104,ISNUMBER(MATCH('Raw Materials'!$M$2:$M$104,$L$3:$L$4,0))=FALSE))),0)} -> 3 | G5: {=IFERROR(ROWS(_xlfn.UNIQUE(_xlfn._xlws.FILTER('Raw Materials'!$F$2:$F$104,ISNUMBER(MATCH('Raw Materials'!$M$2:$M$104,$L$3:$L$4,0))=FALSE))),0)} -> 4 | H5: =IFERROR(ROWS(_xlfn.UNIQUE('Raw Materials'!$D$2:$D$104)),0) -> 73 | I5: =IFERROR(ROWS(_xlfn.UNIQUE('Raw Materials'!$F$2:$F$104)),0) -> 91
A6: Battery Grade Materials Manufacturing | B6: {=IFERROR(ROWS(_xlfn.UNIQUE(_xlfn._xlws.FILTER('Battery Grade Materials'!$D$2:$D$158,'Battery Grade Materials'!$M$2:$M$158=B$3))),0)} -> 84 | C6: {=IFERROR(ROWS(_xlfn.UNIQUE(_xlfn._xlws.FILTER('Battery Grade Materials'!$F$2:$F$158,'Battery Grade Materials'!$M$2:$M$158=B$3))),0)} -> 104 | D6: {=IFERROR(ROWS(_xlfn.UNIQUE(_xlfn._xlws.FILTER('Battery Grade Materials'!$D$2:$D$158,'Battery Grade Materials'!$M$2:$M$158=D$3))),0)} -> 24 | E6: {=IFERROR(ROWS(_xlfn.UNIQUE(_xlfn._xlws.FILTER('Battery Grade Materials'!$F$2:$F$158,'Battery Grade Materials'!$M$2:$M$158=D$3))),0)} -> 27 | F6: {=IFERROR(ROWS(_xlfn.UNIQUE(_xlfn._xlws.FILTER('Battery Grade Materials'!$D$2:$D$158,ISNUMBER(MATCH('Battery Grade Materials'!$M$2:$M$158,$L$3:$L$4,0))=FALSE))),0)} -> 3 | G6: {=IFERROR(ROWS(_xlfn.UNIQUE(_xlfn._xlws.FILTER('Battery Grade Materials'!$F$2:$F$158,ISNUMBER(MATCH('Battery Grade Materials'!$M$2:$M$158,$L$3:$L$4,0))=FALSE))),0)} -> 3 | H6: =IFERROR(ROWS(_xlfn.UNIQUE('Battery Grade Materials'!$D$2:$D$158)),0) -> 111 | I6: =IFERROR(ROWS(_xlfn.UNIQUE('Battery Grade Materials'!$F$2:$F$158)),0) -> 133
A7: Other Battery Components and Materials Manufacturing | B7: {=IFERROR(ROWS(_xlfn.UNIQUE(_xlfn._xlws.FILTER('Other Battery Components & Mat.'!$D$2:$D$106,'Other Battery Components & Mat.'!$M$2:$M$106=B$3))),0)} -> 76 | C7: {=IFERROR(ROWS(_xlfn.UNIQUE(_xlfn._xlws.FILTER('Other Battery Components & Mat.'!$F$2:$F$106,'Other Battery Components & Mat.'!$M$2:$M$106=B$3))),0)} -> 93 | D7: {=IFERROR(ROWS(_xlfn.UNIQUE(_xlfn._xlws.FILTER('Other Battery Components & Mat.'!$D$2:$D$106,'Other Battery Components & Mat.'!$M$2:$M$106=D$3))),0)} -> 6 | E7: {=IFERROR(ROWS(_xlfn.UNIQUE(_xlfn._xlws.FILTER('Other Battery Components & Mat.'!$F$2:$F$106,'Other Battery Components & Mat.'!$M$2:$M$106=D$3))),0)} -> 6 | F7: {=IFERROR(ROWS(_xlfn.UNIQUE(_xlfn._xlws.FILTER('Other Battery Components & Mat.'!$D$2:$D$106,ISNUMBER(MATCH('Other Battery Components & Mat.'!$M$2:$M$106,$L$3:$L$4,0))=FALSE))),0)} -> 1 | G7: {=IFERROR(ROWS(_xlfn.UNIQUE(_xlfn._xlws.FILTER('Other Battery Components & Mat.'!$F$2:$F$106,ISNUMBER(MATCH('Other Battery Components & Mat.'!$M$2:$M$106,$L$3:$L$4,0))=FALSE))),0)} -> 1 | H7: =IFERROR(ROWS(_xlfn.UNIQUE('Battery Grade Materials'!$D$2:$D$95)),0) -> 69 | I7: =IFERROR(ROWS(_xlfn.UNIQUE('Other Battery Components & Mat.'!$F$2:$F$106)),0) -> 99
A8: Electrode and Cells Manufacturing | B8: {=IFERROR(ROWS(_xlfn.UNIQUE(_xlfn._xlws.FILTER('Electrode & Cell Manufacturing'!$D$2:$D$119,'Electrode & Cell Manufacturing'!$M$2:$M$119=B$3))),0)} -> 80 | C8: {=IFERROR(ROWS(_xlfn.UNIQUE(_xlfn._xlws.FILTER('Electrode & Cell Manufacturing'!$F$2:$F$119,'Electrode & Cell Manufacturing'!$M$2:$M$119=B$3))),0)} -> 98 | D8: {=IFERROR(ROWS(_xlfn.UNIQUE(_xlfn._xlws.FILTER('Electrode & Cell Manufacturing'!$D$2:$D$119,'Electrode & Cell Manufacturing'!$M$2:$M$119=D$3))),0)} -> 12 | E8: {=IFERROR(ROWS(_xlfn.UNIQUE(_xlfn._xlws.FILTER('Electrode & Cell Manufacturing'!$F$2:$F$119,'Electrode & Cell Manufacturing'!$M$2:$M$119=D$3))),0)} -> 12 | F8: {=IFERROR(ROWS(_xlfn.UNIQUE(_xlfn._xlws.FILTER('Electrode & Cell Manufacturing'!$D$2:$D$119,ISNUMBER(MATCH('Electrode & Cell Manufacturing'!$M$2:$M$119,$L$3:$L$4,0))=FALSE))),0)} -> 3 | G8: {=IFERROR(ROWS(_xlfn.UNIQUE(_xlfn._xlws.FILTER('Electrode & Cell Manufacturing'!$F$2:$F$119,ISNUMBER(MATCH('Electrode & Cell Manufacturing'!$M$2:$M$119,$L$3:$L$4,0))=FALSE))),0)} -> 3 | H8: =IFERROR(ROWS(_xlfn.UNIQUE('Electrode & Cell Manufacturing'!$D$2:$D$119)),0) -> 89 | I8: =IFERROR(ROWS(_xlfn.UNIQUE('Electrode & Cell Manufacturing'!$F$2:$F$119)),0) -> 113
A9: Modules and Packs Manufacturing | B9: {=IFERROR(ROWS(_xlfn.UNIQUE(_xlfn._xlws.FILTER('Module-Pack Manufacturing'!$D$2:$D$268,'Module-Pack Manufacturing'!$M$2:$M$268=B$3))),0)} -> 183 | C9: {=IFERROR(ROWS(_xlfn.UNIQUE(_xlfn._xlws.FILTER('Module-Pack Manufacturing'!$F$2:$F$268,'Module-Pack Manufacturing'!$M$2:$M$268=B$3))),0)} -> 209 | D9: {=IFERROR(ROWS(_xlfn.UNIQUE(_xlfn._xlws.FILTER('Module-Pack Manufacturing'!$D$2:$D$268,'Module-Pack Manufacturing'!$M$2:$M$268=D$3))),0)} -> 20 | E9: {=IFERROR(ROWS(_xlfn.UNIQUE(_xlfn._xlws.FILTER('Module-Pack Manufacturing'!$F$2:$F$268,'Module-Pack Manufacturing'!$M$2:$M$268=D$3))),0)} -> 23 | F9: {=IFERROR(ROWS(_xlfn.UNIQUE(_xlfn._xlws.FILTER('Module-Pack Manufacturing'!$D$2:$D$268,ISNUMBER(MATCH('Module-Pack Manufacturing'!$M$2:$M$268,$L$3:$L$4,0))=FALSE))),0)} -> 10 | G9: {=IFERROR(ROWS(_xlfn.UNIQUE(_xlfn._xlws.FILTER('Module-Pack Manufacturing'!$F$2:$F$268,ISNUMBER(MATCH('Module-Pack Manufacturing'!$M$2:$M$268,$L$3:$L$4,0))=FALSE))),0)} -> 11 | H9: =IFERROR(ROWS(_xlfn.UNIQUE('Module-Pack Manufacturing'!$D$2:$D$268)),0) -> 202 | I9: =IFERROR(ROWS(_xlfn.UNIQUE('Module-Pack Manufacturing'!$F$2:$F$268)),0) -> 242
A10: Recycling/Repurposing | B10: {=IFERROR(ROWS(_xlfn.UNIQUE(_xlfn._xlws.FILTER('Recycling-Repurposing'!$D$2:$D$133,'Recycling-Repurposing'!$O$2:$O$133=B$3))),0)} -> 85 | C10: {=IFERROR(ROWS(_xlfn.UNIQUE(_xlfn._xlws.FILTER('Recycling-Repurposing'!$F$2:$F$133,'Recycling-Repurposing'!$O$2:$O$133=B$3))),0)} -> 113 | D10: {=IFERROR(ROWS(_xlfn.UNIQUE(_xlfn._xlws.FILTER('Recycling-Repurposing'!$D$2:$D$133,'Recycling-Repurposing'!$O$2:$O$133=D$3))),0)} -> 9 | E10: {=IFERROR(ROWS(_xlfn.UNIQUE(_xlfn._xlws.FILTER('Recycling-Repurposing'!$F$2:$F$133,'Recycling-Repurposing'!$O$2:$O$133=D$3))),0)} -> 11 | F10: {=IFERROR(ROWS(_xlfn.UNIQUE(_xlfn._xlws.FILTER('Recycling-Repurposing'!$D$2:$D$133,ISNUMBER(MATCH('Recycling-Repurposing'!$O$2:$O$133,$L$3:$L$4,0))=FALSE))),0)} -> 0 | G10: {=IFERROR(ROWS(_xlfn.UNIQUE(_xlfn._xlws.FILTER('Recycling-Repurposing'!$F$2:$F$133,ISNUMBER(MATCH('Recycling-Repurposing'!$O$2:$O$133,$L$3:$L$4,0))=FALSE))),0)} -> 0 | H10: =IFERROR(ROWS(_xlfn.UNIQUE('Recycling-Repurposing'!$D$2:$D$133)),0) -> 90 | I10: =IFERROR(ROWS(_xlfn.UNIQUE('Recycling-Repurposing'!$F$2:$F$133)),0) -> 123
A11: Equipment Manufacturing | B11: {=IFERROR(ROWS(_xlfn.UNIQUE(_xlfn._xlws.FILTER(Equipment!$D$5:$D$144,Equipment!$M$5:$M$144=B$3))),0)} -> 99 | C11: {=IFERROR(ROWS(_xlfn.UNIQUE(_xlfn._xlws.FILTER(Equipment!$F$5:$F$144,Equipment!$M$5:$M$144=B$3))),0)} -> 103 | D11: {=IFERROR(ROWS(_xlfn.UNIQUE(_xlfn._xlws.FILTER(Equipment!$D$5:$D$144,Equipment!$M$5:$M$144=D$3))),0)} -> 3 | E11: {=IFERROR(ROWS(_xlfn.UNIQUE(_xlfn._xlws.FILTER(Equipment!$F$5:$F$144,Equipment!$M$5:$M$144=D$3))),0)} -> 3 | F11: {=IFERROR(ROWS(_xlfn.UNIQUE(_xlfn._xlws.FILTER(Equipment!$D$2:$D$145,ISNUMBER(MATCH(Equipment!$M$2:$M$145,$L$3:$L$4,0))=FALSE))),0)} -> 0 | G11: {=IFERROR(ROWS(_xlfn.UNIQUE(_xlfn._xlws.FILTER(Equipment!$F$2:$F$145,ISNUMBER(MATCH(Equipment!$M$2:$M$145,$L$3:$L$4,0))=FALSE))),0)} -> 0 | H11: =IFERROR(ROWS(_xlfn.UNIQUE(Equipment!$D$5:$D$144)),0) -> 102 | I11: =IFERROR(ROWS(_xlfn.UNIQUE(Equipment!$F$5:$F$144)),0) -> 106
A12: R&D | B12: {=IFERROR(ROWS(_xlfn.UNIQUE(_xlfn._xlws.FILTER('R&D'!$D$2:$D$144,'R&D'!$M$2:$M$144=B$3))),0)} -> 117 | C12: {=IFERROR(ROWS(_xlfn.UNIQUE(_xlfn._xlws.FILTER('R&D'!$F$2:$F$144,'R&D'!$M$2:$M$144=B$3))),0)} -> 126 | D12: {=IFERROR(ROWS(_xlfn.UNIQUE(_xlfn._xlws.FILTER('R&D'!$D$2:$D$144,'R&D'!$M$2:$M$144=D$3))),0)} -> 13 | E12: {=IFERROR(ROWS(_xlfn.UNIQUE(_xlfn._xlws.FILTER('R&D'!$F$2:$F$144,'R&D'!$M$2:$M$144=D$3))),0)} -> 13 | F12: {=IFERROR(ROWS(_xlfn.UNIQUE(_xlfn._xlws.FILTER('R&D'!$D$2:$D$144,ISNUMBER(MATCH('R&D'!$M$2:$M$144,$L$3:$L$4,0))=FALSE))),0)} -> 0 | G12: {=IFERROR(ROWS(_xlfn.UNIQUE(_xlfn._xlws.FILTER('R&D'!$F$2:$F$144,ISNUMBER(MATCH('R&D'!$M$2:$M$144,$L$3:$L$4,0))=FALSE))),0)} -> 0 | H12: =IFERROR(ROWS(_xlfn.UNIQUE('R&D'!$D$2:$D$144)),0) -> 129 | I12: =IFERROR(ROWS(_xlfn.UNIQUE('R&D'!$F$2:$F$144)),0) -> 139
A13: Service and Repair | B13: {=IFERROR(ROWS(_xlfn.UNIQUE(_xlfn._xlws.FILTER('Services & Consulting'!$D$2:$D$149,'Services & Consulting'!$L$2:$L$149=B$3))),0)} -> 128 | C13: {=IFERROR(ROWS(_xlfn.UNIQUE(_xlfn._xlws.FILTER('Services & Consulting'!$I$2:$I$149,'Services & Consulting'!$L$2:$L$149=B$3))),0)} -> 128 | D13: {=IFERROR(ROWS(_xlfn.UNIQUE(_xlfn._xlws.FILTER('Services & Consulting'!$D$2:$D$149,'Services & Consulting'!$L$2:$L$149=D$3))),0)} -> 9 | E13: {=IFERROR(ROWS(_xlfn.UNIQUE(_xlfn._xlws.FILTER('Services & Consulting'!$I$2:$I$149,'Services & Consulting'!$L$2:$L$149=D$3))),0)} -> 9 | F13: {=IFERROR(ROWS(_xlfn.UNIQUE(_xlfn._xlws.FILTER('Services & Consulting'!$D$2:$D$149,ISNUMBER(MATCH('Services & Consulting'!$L$2:$L$149,$L$3:$L$4,0))=FALSE))),0)} -> 0 | G13: {=IFERROR(ROWS(_xlfn.UNIQUE(_xlfn._xlws.FILTER('Services & Consulting'!$F$2:$F$149,ISNUMBER(MATCH('Services & Consulting'!$L$2:$L$149,$L$3:$L$4,0))=FALSE))),0)} -> 0 | H13: =IFERROR(ROWS(_xlfn.UNIQUE('Services & Consulting'!$D$2:$D$149)),0) -> 135 | I13: =IFERROR(ROWS(_xlfn.UNIQUE('Services & Consulting'!$I$2:I$149)),0) -> 136
A14: Modeling | B14: {=IFERROR(ROWS(_xlfn.UNIQUE(_xlfn._xlws.FILTER('Modeling & Software'!$D$2:$D$37,'Modeling & Software'!$L$2:$L$37=B$3))),0)} -> 34 | C14: {=IFERROR(ROWS(_xlfn.UNIQUE(_xlfn._xlws.FILTER('Modeling & Software'!$I$2:$I$37,'Modeling & Software'!$L$2:$L$37=B$3))),0)} -> 34 | D14: {=IFERROR(ROWS(_xlfn.UNIQUE(_xlfn._xlws.FILTER('Modeling & Software'!$D$2:$D$37,'Modeling & Software'!$L$2:$L$37=D$3))),0)} -> 2 | E14: {=IFERROR(ROWS(_xlfn.UNIQUE(_xlfn._xlws.FILTER('Modeling & Software'!$F$2:$F$37,'Modeling & Software'!$L$2:$L$37=D$3))),0)} -> 1 | F14: {=IFERROR(ROWS(_xlfn.UNIQUE(_xlfn._xlws.FILTER('Modeling & Software'!$D$2:$D$37,ISNUMBER(MATCH('Modeling & Software'!$L$2:$L$37,$L$3:$L$4,0))=FALSE))),0)} -> 0 | G14: {=IFERROR(ROWS(_xlfn.UNIQUE(_xlfn._xlws.FILTER('Modeling & Software'!$F$2:$F$37,ISNUMBER(MATCH('Modeling & Software'!$L$2:$L$37,$L$3:$L$4,0))=FALSE))),0)} -> 0 | H14: =IFERROR(ROWS(_xlfn.UNIQUE('Modeling & Software'!$D$2:$D$37)),0) -> 35 | I14: =IFERROR(ROWS(_xlfn.UNIQUE('Modeling & Software'!$I$2:$I$37)),0) -> 36
A15: Professional Services | B15: {=IFERROR(ROWS(_xlfn.UNIQUE(_xlfn._xlws.FILTER('Professional Services (NB)'!$D$2:$D$39,'Professional Services (NB)'!$L$2:$L$39=B$3))),0)} -> 35 | C15: {=IFERROR(ROWS(_xlfn.UNIQUE(_xlfn._xlws.FILTER('Professional Services (NB)'!$I$2:$I$39,'Professional Services (NB)'!$L$2:$L$39=B$3))),0)} -> 35 | D15: {=IFERROR(ROWS(_xlfn.UNIQUE(_xlfn._xlws.FILTER('Professional Services (NB)'!$D$2:$D$39,'Professional Services (NB)'!$L$2:$L$39=D$3))),0)} -> 2 | E15: {=IFERROR(ROWS(_xlfn.UNIQUE(_xlfn._xlws.FILTER('Professional Services (NB)'!$I$2:$I$39,'Professional Services (NB)'!$L$2:$L$39=D$3))),0)} -> 2 | F15: {=IFERROR(ROWS(_xlfn.UNIQUE(_xlfn._xlws.FILTER('Professional Services (NB)'!$D$2:$D$39,ISNUMBER(MATCH('Professional Services (NB)'!$L$2:$L$39,$L$3:$L$4,0))=FALSE))),0)} -> 1 | G15: {=IFERROR(ROWS(_xlfn.UNIQUE(_xlfn._xlws.FILTER('Professional Services (NB)'!$F$2:$F$39,ISNUMBER(MATCH('Professional Services (NB)'!$L$2:$L$39,$L$3:$L$4,0))=FALSE))),0)} -> 1 | H15: =IFERROR(ROWS(_xlfn.UNIQUE('Professional Services (NB)'!$D$2:$D$39)),0) -> 38 | I15: =IFERROR(ROWS(_xlfn.UNIQUE('Professional Services (NB)'!$I$2:$I$39)),0) -> 38
A16: Distributors | B16: {=IFERROR(ROWS(_xlfn.UNIQUE(_xlfn._xlws.FILTER(Distributors!$D$2:$D$22,Distributors!$L$2:$L$22=B$3))),0)} -> 8 | C16: {=IFERROR(ROWS(_xlfn.UNIQUE(_xlfn._xlws.FILTER(Distributors!$I$2:$I$22,Distributors!$L$2:$L$22=B$3))),0)} -> 8 | D16: {=IFERROR(ROWS(_xlfn.UNIQUE(_xlfn._xlws.FILTER(Distributors!$D$2:$D$22,Distributors!$L$2:$L$22=D$3))),0)} -> 1 | E16: {=IFERROR(ROWS(_xlfn.UNIQUE(_xlfn._xlws.FILTER(Distributors!$I$2:$I$22,Distributors!$L$2:$L$22=D$3))),0)} -> 1 | F16: {=IFERROR(ROWS(_xlfn.UNIQUE(_xlfn._xlws.FILTER(Distributors!$D$2:$D$22,ISNUMBER(MATCH(Distributors!$L$2:$L$22,$L$3:$L$4,0))=FALSE))),0)} -> 0 | G16: {=IFERROR(ROWS(_xlfn.UNIQUE(_xlfn._xlws.FILTER(Distributors!$F$2:$F$22,ISNUMBER(MATCH(Distributors!$L$2:$L$22,$L$3:$L$4,0))=FALSE))),0)} -> 0 | H16: =IFERROR(ROWS(_xlfn.UNIQUE(Distributors!$D$2:$D$22)),0) -> 9 | I16: =IFERROR(ROWS(_xlfn.UNIQUE(Distributors!$I$2:$I$22)),0) -> 9
A17: Totals | B17: =SUM(B5:B16) -> 971 | C17: =SUM(C5:C16) -> 1097 | D17: =SUM(D5:D16) -> 129 | E17: =SUM(E5:E16) -> 149 | F17: =SUM(F5:F16) -> 21 | G17: =SUM(G5:G16) -> 23 | H17: =SUM(H5:H16) -> 1082 | I17: =SUM(I5:I16) -> 1265

Sheet Glossary
A1: Term | B1: Definition | C1: Source
A2: 4R's | B2: Repair, Remanufacture, Refurbish and/or Repurpose | C2: Battery Pack Design book
A3: Active material | B3: The constituents of a cell that participate in electrochemical charge and/or discharge reactions. This does not inclue separators, current collectors, catalysts or supports | C3: SAE J1715 - Battery Terminology (2021-08)
A4: Anode | B4: The negative battery electrode at which oxidation (a loss of electrons) take place during discharge. | C4: SAE J1715 - Battery Terminology (2021-08)
A5: Battery (RESS Battery) | B5: A general term that inclusively refers to electrochemical cells, modules, packs, and endergy storage systems. | C5: SAE J1715 - Battery Terminology (2021-08)
A6: Battery collection | B6: Gathering of batteries for the purpose of shipment to a treatment facility where treatment facility may include any end of life treatment facility such as a recycler or licensed disposal site; it can also include other processes such as evaluation, remanufacture, and/or repurpose | C6: SAE J2974 - Technical Information Report on Automotive Battery Recycling
A7: Battery grade materials | B7: Materials for batteries that are made at facilities after initial concentration at extraction points
A8: Battery management system (BMS) | B8: An electronic system that monitors, manage,s and may communicate information about performance, safety, and supervisory control ofa battery through battery state estimations and/or fault detections and predictions | C8: SAE J1715 - Battery Terminology (2021-08)
A9: Battery module | B9: Multiple electrochemical cells connected in series or parallel. Batttery modules may or may not include snesors such as voltage and temperature sensors, safety components, and a cooling structure that each module can be controlled and managed independently. | C9: SAE J1715 - Battery Terminology (2021-08)
A10: Battery pack | B10: A battery assembly that consists of one or more modules. A pack may include sensors, interlocks, contactors, battery management controller, safety devices, thermal management, and structural components | C10: SAE J1715 - Battery Terminology (2021-08)
A11: Black mass | B11: The material in an LIB that is released after shredding and screening
A12: BMS | B12: Battery Management System: The BMS is the control system within the battery pack that consists of one or more electronic controllers, which manages the charging and discharging, monitors the temperature and voltage, communicates with the vehicle system, balances the cells, and manages the safety functionality of the battery pack. | C12: Battery Pack Design book
A13: Cathode | B13: The positive battery electrode at which reduction (a gain of electrons) takes place during discharge | C13: SAE J1715 - Battery Terminology (2021-08)
A14: Cell | B14: A basic electrochemical functional unit that at minimum consists of a positive electrode, a negative electrode electrode, and an electrolyte. | C14: SAE J1715 - Battery Terminology (2021-08)
A15: Connector | B15: Conductor of electricity used for carrying current between components in an electric circuit. For example, a connector electrically joins two cells, or a terminal of the battery to an exterior circuit and also to auxiliary devices. | C15: SAE J1715 - Battery Terminology (2021-08)
A16: Collection and Sorting of Feedstock | B16: Recycling processes are enhanced by segregating the feed (spent batteries) into separate fractions based on chemistry. This can greatly reduce the cost of recycling, unwanted emissions, and safety concerns. Presently hand sorting of portable batteries by chemistries is common prior to shipment to recyclers. | C16: SAE J2974 - Technical Information Report on Automotive Battery Recycling
A17: Collection, Disassembly and/or Storage | B17: Facilities that collect vehicles or other products containing batteries and they take the product apart and get the battery and safely store it.
A18: Collection, Sorting Storage, and/or Discharging | B18: Facilities that collect batteries, sort them by battery type or chemistry, safely store them and/or discharge them
A19: Direct recycling | B19: Direct recycling is a hybrid of the processing methods drawing most heavily from physical separation as the goal is to return the feed to the initial application with a minimum of processing. Byproducts are process dependent, and generally dust and particulate emissions may be a concern. Capital cost is expected to be low compared to other processes, and permitting is process specific. This type of process has been applied to the polypropylene cases of lead acid batteries and the metallic cases from Zn/C and alkaline batteries. This type of process has been demonstrated with Ni-MH and Li-ion cells. | C19: SAE J2974 - Technical Information Report on Automotive Battery Recycling
A20: Electrode | B20: The conducting body that contains active materials and through which current enters or leaves a cell. | C20: SAE J1715 - Battery Terminology (2021-08)
A21: Electrolyte | B21: The medium, which can be liquid or solid, that provides ion transport between the positive and negative electrodes of a cell.. Electrolytes may also participate directly in the charge and/or discharge reactions. | C21: SAE J1715 - Battery Terminology (2021-08)
A22: End of Life (EOL) | B22: When a battery fails to meet specified capacity, power, or function in specified use conditions | C22: SAE J1715 - Battery Terminology (2021-08)
A23: Hydrometallurgy | B23: or Hydrometallurgical Processing: Hydrometallurgical processing uses aqueous chemicals, acids, bases or other solvents to leach the material. This is usually followed by species (chemical compound) separation and purification processes. The materials are then precipitated as hydroxides/salts or electrorefined for reuse as metal. Byproducts include: leach residue, waste water that requires further treatment, and sludges from waste water treatment. Hydroxide and salts are often reprocessed in pyrometallurgical facilities to produce metals. Capital cost is typically less than pyrometallurgy depending on target metals recovered, and permitting is reagent specific. This type of process has been applied to lead acid, NiCd, NiMH, and Li-ion. | C23: SAE J2974 - Technical Information Report on Automotive Battery Recycling
A24: Lithium ion battery (LIB) | B24: A rechargeable battery that uses lithium ions as the primary ionic conductor in the electrolyte. | C24: SAE J1715 - Battery Terminology (2021-08)
A25: Module | B25: or Battery module or battery monoblock: Refers to the multiple connections of electrochemical or electrostatic cells. Battery modules amy or may not include sensors such as voltage and temperature sensors, safety components and a cooling structure so that each module can be controlled and managed independently | C25: SAE J2974 - Technical Information Report on Automotive Battery Recycling
A26: Pack | B26: or Battery pack: A battery pack may consist of only one module or multiple modules. The pack includes sensors, interlocks, contactors, battery management controller, safety devices, thermal management, and structural components | C26: SAE J2974 - Technical Information Report on Automotive Battery Recycling
A27: Physical Separation | B27: Physical separation procesess separate target materials based on physical properties, such as size, density, color, conductivity, magnetic susceptibility, and surface chemistry. This process usually involves size reduction, followed by separation and upgrading | C27: SAE J2974 - Technical Information Report on Automotive Battery Recycling
A28: Prismatic cell | B28: Cell with a metallic container with faces that are rectangular. | C28: SAE J1715 - Battery Terminology (2021-08)
A29: Pyrometallurgy | B29: or Pyrometallurgical Processing: Pyrometallurgical processing involves a thermal or high-temperature process in which metals are reduced back to a base metallic state. The oxidation potential of the metals typically determine which metals report to the melt and which report to the slag, this outcome can be somewhat controlled through the atmosphere present in the smelter. Any remaining organic components are burned for energy recovery. Waste and byproducts can include: drosses, slags, soot, and other emissions, as well as high-quality heat. These facilities benefit greatly from economies of scale. Capital cost and permitting burden are high. This type of process has been applied to lead acid, NiCd, NiMH, and Li-ion. | C29: SAE J2974 - Technical Information Report on Automotive Battery Recycling
A30: Rack
A31: Rebuilt | B31: Includes factory rebuilt and remanufactured, and refers to a component (such as a battery) that has been dismantled and reconstructed, as necessary. Its internal and external parts have been cleaned and made rust- and corrosion-free; all impaired, defective, or substantially worn parts have been restored to a sound condition or replaced with new; it has rebuilt (in accordance with the provisions of this paragraph) or unimpaired used parts; all missing parts have been replaced with new, rebuilt, or unimpaired used parts; and such rewinding or machining and other operations have been performed as necessary to put the industry product in sound working condition according to OEM specifications and parameters. | C31: SAE J2974 - Technical Information Report on Automotive Battery Recycling
A32: Recycling | B32: Transformation of end of life products (RESS, batteries, or scrap) into usable products
A33: Refining | B33: Converting a metallic component into another component that is of higher purity using heat, chemicals or other methods
A34: Second life battery | B34: This describes the act of taking a battery system from the end of service life, characterizing the components, and reconfiguring some or all of the components of the battery system for a new application. This may also require new, rebuilt, or unimpaired used parts to be incorporated into the system. Second use requires many of the same commitments as the remanufacture or rebuilding of automotive parts. The difference is the battery may go into a related, but nonautomotive, application. These should be subject to appropriate consensus standards, such as UL 1974 Evaluation for Repurposing Batteries. | C34: SAE J2974 - Technical Information Report on Automotive Battery Recycling
A35: Separator | B35: A cell component placed between the negative and positive electrodes, which electrically isolates or separates the electrodes while allowing ionic conduction to occur. | C35: SAE J1715 - Battery Terminology (2021-08)
A36: Shredding and screening | B36: Physical processing of lithium-ion batteries to produce black mass
A37: Solid electrolyte cell | B37: Cell with an ionically conducting solid as electrolyte. | C37: SAE J1715 - Battery Terminology (2021-08)
A38: Sorted EOL battery | B38: An end of life battery that has been sorted by overall type (e.g., lead-acid vs. lithium-ion) and/or lithium-ion chemistry (e.g., Lithium iron phosphate, Nickel manganese cobalt)
A39: Spodumene | B39: a translucent, typically grayish-white aluminosilicate mineral which is an important source of lithium.
A40: Universal Waste Handler | B40: A facility that processes hazardous waste under universal waste regulations which are: Streamlined hazardous waste management regulation put out by the US at the federal (EPA) and local (state) level, with the goal of promoting the collection and recycling of these materials by easing the regulator burden on the collection and transport, and encouraging the development of programs to reduce the quantity going to municipal solid waste facilities of certain common hazardous wastes. | C40: SAE J2974 - Technical Information Report on Automotive Battery Recycling

Sheet General Search
A1: Directions: | B1: 1. Select the Search Type (Company, Product, State) in the yellow box next to Search Type. 2. Enter the full or partial name of a the selected Search Type in the 2nd yellow box and hit Enter
D3: No. of Records: | G3: =IF(B7<>"",COUNTA(D7:D64004),0) -> 2
A5: Search | D5: Results
A6: Select Search Type (dropdown list): | B6: Company | C6: ID | D6: Status* | E6: NAATBatt Member? | F6: Company | G6: Facility Name | H6: Facility City | I6: Facility State or Province | J6: Facility Country | K6: Product or Service Type | L6: Product or Service | M6: Production Capacity | N6: Units
A7: =IF(B6<>"",B6,"") -> Company | B7: Copper | C7: {=IF($B$6="Company",IF($B$7<>"",_xlfn._xlws.FILTER(Append2[ID],ISNUMBER(SEARCH($B$7,Append2[Company])),"No result"),""),IF($B$6="Product",IF($B$7<>"",_xlfn._xlws.FILTER(Append2[ID],ISNUMBER(SEARCH($B$7,Append2[Product])),"No result"),""), IF($B$6="State",IF($B$7<>"",_xlfn._xlws.FILTER(Append2[ID],ISNUMBER(SEARCH($B$7,Append2[Facility State or Province])),"No result"),""))))} -> 1058 | D7: {=IF($B$6="Company", IF($B$7<>"",_xlfn._xlws.FILTER(Append2[Status],ISNUMBER(SEARCH($B$7,Append2[Company])),"No result"),""),IF($B$6="Product", IF($B$7<>"",_xlfn._xlws.FILTER(Append2[Status],ISNUMBER(SEARCH($B$7,Append2[Product])),"No result"),""), IF($B$6="State", IF($B$7<>"",_xlfn._xlws.FILTER(Append2[Status],ISNUMBER(SEARCH($B$7,Append2[Facility State or Province])),"No result"),""))))} -> Under construction | E7: {=IF($B$6="Company", IF($B$7<>"",_xlfn._xlws.FILTER(Append2[NAATBatt Member],ISNUMBER(SEARCH($B$7,Append2[Company])),"No result"),""),IF($B$6="Product", IF($B$7<>"",_xlfn._xlws.FILTER(Append2[NAATBatt Member],ISNUMBER(SEARCH($B$7,Append2[Product])),"No result"),""), IF($B$6="State", IF($B$7<>"",_xlfn._xlws.FILTER(Append2[NAATBatt Member],ISNUMBER(SEARCH($B$7,Append2[Facility State or Province])),"No result"),""))))} -> No | F7: {=IF($B$6="Company", IF($B$7<>"",_xlfn._xlws.FILTER(Append2[Company],ISNUMBER(SEARCH($B$7,Append2[Company])),"No result"),""),IF($B$6="Product", IF($B$7<>"",_xlfn._xlws.FILTER(Append2[Company],ISNUMBER(SEARCH($B$7,Append2[Product])),"No result"),""),IF($B$6="State", IF($B$7<>"",_xlfn._xlws.FILTER(Append2[Company],ISNUMBER(SEARCH($B$7,Append2[Facility State or Province])),"No result"),""))))} -> NewRange Copper Nickel JV | G7: {=IF($B$6="Company",IF(IF($B$7<>"",_xlfn._xlws.FILTER(Append2[Facility Name],ISNUMBER(SEARCH($B$7,Append2[Company])),"No result"),"")=0,"",IF($B$7<>"",_xlfn._xlws.FILTER(Append2[Facility Name],ISNUMBER(SEARCH($B$7,Append2[Company])),"No result"),"")),IF($B$6="Product",IF(IF($B$7<>"",_xlfn._xlws.FILTER(Append2[Facility Name],ISNUMBER(SEARCH($B$7,Append2[Product])),"No result"),"")=0,"",IF($B$7<>"",_xlfn._xlws.FILTER(Append2[Facility Name],ISNUMBER(SEARCH($B$7,Append2[Product])),"No result"),"")),IF($B$6="State",IF(IF($B$7<>"",_xlfn._xlws.FILTER(Append2[Facility Name],ISNUMBER(SEARCH($B$7,Append2[Facility State or Province])),"No result"),"")=0,"",IF($B$7<>"",_xlfn._xlws.FILTER(Append2[Facility Name],ISNUMBER(SEARCH($B$7,Append2[Facility State or Province])),"No result"),"")))))} -> NewRange Copper Nickel Project | H7: {=IF($B$6="Company",IF($B$7<>"",_xlfn._xlws.FILTER(Append2[Facility City],ISNUMBER(SEARCH($B$7,Append2[Company])),"No result"),""),IF($B$6="Product",IF($B$7<>"",_xlfn._xlws.FILTER(Append2[Facility City],ISNUMBER(SEARCH($B$7,Append2[Product])),"No result"),""),IF($B$6="State",IF($B$7<>"",_xlfn._xlws.FILTER(Append2[Facility City],ISNUMBER(SEARCH($B$7,Append2[Facility State or Province])),"No result"),""))))} -> Hoyt Lakes | I7: {=IF($B$6="Company",IF($B$7<>"",_xlfn._xlws.FILTER(Append2[Facility State or Province],ISNUMBER(SEARCH($B$7,Append2[Company])),"No result"),""),IF($B$6="Product",IF($B$7<>"",_xlfn._xlws.FILTER(Append2[Facility State or Province],ISNUMBER(SEARCH($B$7,Append2[Product])),"No result"),""),IF($B$6="State",IF($B$7<>"",_xlfn._xlws.FILTER(Append2[Facility State or Province],ISNUMBER(SEARCH($B$7,Append2[Facility State or Province])),"No result"),""))))} -> MN | J7: {=IF($B$6="Company",IF($B$7<>"",_xlfn._xlws.FILTER(Append2[Facility Country],ISNUMBER(SEARCH($B$7,Append2[Company])),"No result"),""),IF($B$6="Product",IF($B$7<>"",_xlfn._xlws.FILTER(Append2[Facility Country],ISNUMBER(SEARCH($B$7,Append2[Product])),"No result"),""),IF($B$6="State",IF($B$7<>"",_xlfn._xlws.FILTER(Append2[Facility Country],ISNUMBER(SEARCH($B$7,Append2[Facility State or Province])),"No result"),""))))} -> US | K7: {=IF($B$6="Company",IF($B$7<>"",_xlfn._xlws.FILTER(Append2[Product/Facility Type],ISNUMBER(SEARCH($B$7,Append2[Company])),"No result"),""),IF($B$6="Product",IF($B$7<>"",_xlfn._xlws.FILTER(Append2[Product/Facility Type],ISNUMBER(SEARCH($B$7,Append2[Product/Facility Type])),"No result"),""),IF($B$6="State",IF($B$7<>"",_xlfn._xlws.FILTER(Append2[Product/Facility Type],ISNUMBER(SEARCH($B$7,Append2[Facility State or Province])),"No result"),""))))} -> Cathode raw materials | L7: {=IF($B$6="Company",IF($B$7<>"",_xlfn._xlws.FILTER(Append2[Product],ISNUMBER(SEARCH($B$7,Append2[Company])),"No result"),""),IF($B$6="Product",IF($B$7<>"",_xlfn._xlws.FILTER(Append2[Product],ISNUMBER(SEARCH($B$7,Append2[Product])),"No result"),""),IF($B$6="State",IF($B$7<>"",_xlfn._xlws.FILTER(Append2[Product],ISNUMBER(SEARCH($B$7,Append2[Facility State or Province])),"No result"),""))))} -> Nickel concentrates | M7: {=IF($B$6="Company",IF($B$7<>"",_xlfn._xlws.FILTER(Append2[Production Capacity],ISNUMBER(SEARCH($B$7,Append2[Company])),"No result"),""),IF($B$6="Product",IF($B$7<>"",_xlfn._xlws.FILTER(Append2[Production Capacity],ISNUMBER(SEARCH($B$7,Append2[Product])),"No result"),""),IF($B$6="State",IF($B$7<>"",_xlfn._xlws.FILTER(Append2[Production Capacity],ISNUMBER(SEARCH($B$7,Append2[Facility State or Province])),"No result"),""))))} -> 0 | N7: {=IF($B$6="Company",IF($B$7<>"",_xlfn._xlws.FILTER(Append2[Production Units],ISNUMBER(SEARCH($B$7,Append2[Company])),"No result"),""),IF($B$6="Product",IF($B$7<>"",_xlfn._xlws.FILTER(Append2[Production Units],ISNUMBER(SEARCH($B$7,Append2[Product])),"No result"),""),IF($B$6="State",IF($B$7<>"",_xlfn._xlws.FILTER(Append2[Production Units],ISNUMBER(SEARCH($B$7,Append2[Facility State or Province])),"No result"),""))))} -> 0
A8: Note: | B8: If a company is in the Recycling/ Repurposing sector (e.g. Second Use), use the Recycling_Repurposing Search sheet instead | C8: 2037 | D8: Commercial | E8: No | F8: Boleo Copper Project | G8: Boleo Copper/ Cobalt Mine | H8: Santa Rosalia | I8: Baja California Sur | J8: Mexico | K8: Cathode Battery Grade Materials | L8: Cobalt oxide | M8: 1700 | N8: MT
B10: *Status
B11: C - Commercial
B12: P - Planned
B13: PC-SU - Pre-commercial/ startup
B14: UC - Under construction

Sheet Recycling_Repurpoing  Search
A1: Directions: | B1: 1. Select the Search Type (Company, Facility Type, State) in the green box next to Search Type. 2. Enter the full or partial name of a the selected Search Type in the 2nd green box and hit Enter
D3: No. of Records: | G3: =IF(B6<>"",COUNTA(D6:D64002),0) -> 4
A4: Search | D4: Results
A5: Select Search Type (dropdown list): | B5: Company | C5: ID | D5: Status* | E5: NAATBatt Member? | F5: Company | G5: Facility Name | H5: Facility City | I5: Facility State or Province | J5: Facility Country | K5: Facility Type | L5: Feedstock | M5: Product | N5: Production Capacity | O5: Units
A6: =IF(B5<>"",B5,"") -> Company | B6: recycler | C6: {=IF($B$5="Company",IF($B$6<>"",_xlfn._xlws.FILTER(EOL_Tbl[ID],ISNUMBER(SEARCH($B$6,EOL_Tbl[Company])),"No result"),""),IF($B$5="Facility Type",IF($B$6<>"",_xlfn._xlws.FILTER(EOL_Tbl[ID],ISNUMBER(SEARCH($B$6,EOL_Tbl[Product/Facility Type])),"No result"),""),IF($B$5="State",IF($B$6<>"",_xlfn._xlws.FILTER(EOL_Tbl[ID],ISNUMBER(SEARCH($B$6,EOL_Tbl[Facility State or Province])),"No result"),""))))} -> 6023 | D6: {=IF($B$5="Company",IF($B$6<>"",_xlfn._xlws.FILTER(EOL_Tbl[Status],ISNUMBER(SEARCH($B$6,EOL_Tbl[Company])),"No result"),""),IF($B$5="Facility Type",IF($B$6<>"",_xlfn._xlws.FILTER(EOL_Tbl[Status],ISNUMBER(SEARCH($B$6,EOL_Tbl[Product/Facility Type])),"No result"),""),IF($B$5="State",IF($B$6<>"",_xlfn._xlws.FILTER(EOL_Tbl[Status],ISNUMBER(SEARCH($B$6,EOL_Tbl[Facility State or Province])),"No result"),""))))} -> Commercial | E6: {=IF($B$5="Company",IF($B$6<>"",_xlfn._xlws.FILTER(EOL_Tbl[NAATBatt Member],ISNUMBER(SEARCH($B$6,EOL_Tbl[Company])),"No result"),""),IF($B$5="Facility Type",IF($B$6<>"",_xlfn._xlws.FILTER(EOL_Tbl[NAATBatt Member],ISNUMBER(SEARCH($B$6,EOL_Tbl[Product/Facility Type])),"No result"),""),IF($B$5="State",IF($B$6<>"",_xlfn._xlws.FILTER(EOL_Tbl[NAATBatt Member],ISNUMBER(SEARCH($B$6,EOL_Tbl[Facility State or Province])),"No result"),""))))} -> No | F6: {=IF($B$5="Company",IF($B$6<>"",_xlfn._xlws.FILTER(EOL_Tbl[Company],ISNUMBER(SEARCH($B$6,EOL_Tbl[Company])),"No result"),""),IF($B$5="Facility Type",IF($B$6<>"",_xlfn._xlws.FILTER(EOL_Tbl[Company],ISNUMBER(SEARCH($B$6,EOL_Tbl[Product/Facility Type])),"No result"),""),IF($B$5="State",IF($B$6<>"",_xlfn._xlws.FILTER(EOL_Tbl[Company],ISNUMBER(SEARCH($B$6,EOL_Tbl[Facility State or Province])),"No result"),""))))} -> Battery Recyclers of America | G6: {=IF($B$5="Company",IF($B$6<>"",_xlfn._xlws.FILTER(EOL_Tbl[Facility Name],ISNUMBER(SEARCH($B$6,EOL_Tbl[Company])),"No result"),""),IF($B$5="Facility Type",IF($B$6<>"",_xlfn._xlws.FILTER(EOL_Tbl[Facility Name],ISNUMBER(SEARCH($B$6,EOL_Tbl[Product/Facility Type])),"No result"),""),IF($B$5="State",IF($B$6<>"",_xlfn._xlws.FILTER(EOL_Tbl[Facility Name],ISNUMBER(SEARCH($B$6,EOL_Tbl[Facility State or Province])),"No result"),""))))} -> Battery Recyclers of America | H6: {=IF($B$5="Company",IF($B$6<>"",_xlfn._xlws.FILTER(EOL_Tbl[Facility City],ISNUMBER(SEARCH($B$6,EOL_Tbl[Company])),"No result"),""),IF($B$5="Facility Type",IF($B$6<>"",_xlfn._xlws.FILTER(EOL_Tbl[Facility City],ISNUMBER(SEARCH($B$6,EOL_Tbl[Product/Facility Type])),"No result"),""),IF($B$5="State",IF($B$6<>"",_xlfn._xlws.FILTER(EOL_Tbl[Facility City],ISNUMBER(SEARCH($B$6,EOL_Tbl[Facility State or Province])),"No result"),""))))} -> Dallas | I6: {=IF($B$5="Company",IF($B$6<>"",_xlfn._xlws.FILTER(EOL_Tbl[Facility State or Province],ISNUMBER(SEARCH($B$6,EOL_Tbl[Company])),"No result"),""),IF($B$5="Facility Type",IF($B$6<>"",_xlfn._xlws.FILTER(EOL_Tbl[Facility State or Province],ISNUMBER(SEARCH($B$6,EOL_Tbl[Product/Facility Type])),"No result"),""),IF($B$5="State",IF($B$6<>"",_xlfn._xlws.FILTER(EOL_Tbl[Facility State or Province],ISNUMBER(SEARCH($B$6,EOL_Tbl[Facility State or Province])),"No result"),""))))} -> TX | J6: {=IF($B$5="Company",IF($B$6<>"",_xlfn._xlws.FILTER(EOL_Tbl[Facility Country],ISNUMBER(SEARCH($B$6,EOL_Tbl[Company])),"No result"),""),IF($B$5="Facility Type",IF($B$6<>"",_xlfn._xlws.FILTER(EOL_Tbl[Facility Country],ISNUMBER(SEARCH($B$6,EOL_Tbl[Product/Facility Type])),"No result"),""),IF($B$5="State",IF($B$6<>"",_xlfn._xlws.FILTER(EOL_Tbl[Facility Country],ISNUMBER(SEARCH($B$6,EOL_Tbl[Facility State or Province])),"No result"),""))))} -> US | K6: {=IF($B$5="Company",IF($B$6<>"",_xlfn._xlws.FILTER(EOL_Tbl[Product/Facility Type],ISNUMBER(SEARCH($B$6,EOL_Tbl[Company])),"No result"),""),IF($B$5="Facility Type",IF($B$6<>"",_xlfn._xlws.FILTER(EOL_Tbl[Product/Facility Type],ISNUMBER(SEARCH($B$6,EOL_Tbl[Product/Facility Type])),"No result"),""),IF($B$5="State",IF($B$6<>"",_xlfn._xlws.FILTER(EOL_Tbl[Product/Facility Type],ISNUMBER(SEARCH($B$6,EOL_Tbl[Facility State or Province])),"No result"),""))))} -> Collection, Disassembling and/ or Storage (Universal Waste Handlers) | L6: {=IF($B$5="Company",IF($B$6<>"",_xlfn._xlws.FILTER(EOL_Tbl[Feedstock],ISNUMBER(SEARCH($B$6,EOL_Tbl[Company])),"No result"),""),IF($B$5="Facility Type",IF($B$6<>"",_xlfn._xlws.FILTER(EOL_Tbl[Feedstock],ISNUMBER(SEARCH($B$6,EOL_Tbl[Product/Facility Type])),"No result"),""),IF($B$5="State",IF($B$6<>"",_xlfn._xlws.FILTER(EOL_Tbl[Feedstock],ISNUMBER(SEARCH($B$6,EOL_Tbl[Facility State or Province])),"No result"),""))))} -> End-of-life Battery | M6: {=IF($B$5="Company",IF($B$6<>"",_xlfn._xlws.FILTER(EOL_Tbl[Product],ISNUMBER(SEARCH($B$6,EOL_Tbl[Company])),"No result"),""),IF($B$5="Facility Type",IF($B$6<>"",_xlfn._xlws.FILTER(EOL_Tbl[Product],ISNUMBER(SEARCH($B$6,EOL_Tbl[Product/Facility Type])),"No result"),""),IF($B$5="State",IF($B$6<>"",_xlfn._xlws.FILTER(EOL_Tbl[Product],ISNUMBER(SEARCH($B$6,EOL_Tbl[Facility State or Province])),"No result"),""))))} -> Sorted End-of-life Battery | N6: {=IF($B$5="Company",IF($B$6<>"",_xlfn._xlws.FILTER(EOL_Tbl[Capacity],ISNUMBER(SEARCH($B$6,EOL_Tbl[Company])),"No result"),""),IF($B$5="Facility Type",IF($B$6<>"",_xlfn._xlws.FILTER(EOL_Tbl[Capacity],ISNUMBER(SEARCH($B$6,EOL_Tbl[Product/Facility Type])),"No result"),""),IF($B$5="State",IF($B$6<>"",_xlfn._xlws.FILTER(EOL_Tbl[Capacity],ISNUMBER(SEARCH($B$6,EOL_Tbl[Facility State or Province])),"No result"),""))))} -> 0 | O6: {=IF($B$5="Company",IF($B$6<>"",_xlfn._xlws.FILTER(EOL_Tbl[Capacity Units],ISNUMBER(SEARCH($B$6,EOL_Tbl[Company])),"No result"),""),IF($B$5="Facility Type",IF($B$6<>"",_xlfn._xlws.FILTER(EOL_Tbl[Capacity Units],ISNUMBER(SEARCH($B$6,EOL_Tbl[Product/Facility Type])),"No result"),""),IF($B$5="State",IF($B$6<>"",_xlfn._xlws.FILTER(EOL_Tbl[Capacity Units],ISNUMBER(SEARCH($B$6,EOL_Tbl[Facility State or Province])),"No result"),""))))} -> 0
A7: Note: | C7: 6025 | D7: Commercial | E7: No | F7: Blue Star Recyclers | G7: Denver | H7: Denver | I7: CO | J7: US | K7: Collection, Disassembling and/ or Storage (Universal Waste Handlers) | L7: Consumer Electronics | M7: Sorted End-of-life Battery | N7: 10500 | O7: tons electronic waste/yr
C8: 6067 | D8: Commercial | E8: Yes | F8: Interco - A Metaltronics Recycler | G8: Interco | H8: Madison | I8: IL | J8: US | K8: Shredding/ Black mass production | L8: End-of-life Battery | M8: Black Mass | N8: 24000 | O8: MT/yr
B9: *Status | C9: 6125 | D9: Pre-commercial/ startup | E9: Yes | F9: United Battery Recyclers Int | G9: United Battery Recyclers Int | H9: Fenton | I9: MI | J9: US | K9: Shredding/ Black mass production | L9: End-of-life Battery | M9: Black Mass
B10: C - Commercial
B11: P - Planned
B12: PC-SU - Pre-commercial/ startup
B13: UC - Under construction

Sheet Append2
A1: ID | B1: Status | C1: Supply Chain Segment | D1: Company | E1: NAATBatt Member | F1: Facility Name | G1: Product/Facility Type | H1: Product | I1: Company Website | J1: Facility Address | K1: Facility City | L1: Facility State or Province | M1: Facility Country | N1: Facility Zip | O1: Facility Phone | P1: Latitude | Q1: Longitude | R1: Facility Workforce | S1: Production Capacity | T1: Production Units | U1: HQ Company | V1: HQ Company Website | W1: HQ City | X1: HQ State or Province | Y1: HQ Country | Z1: QC | AA1: QC Date | AB1: Sources | AC1: Brief Company Profile | AD1: Summary Word Count | AE1: Notes | AF1: Contact | AG1: Contact email | AH1: Contact Phone | AI1: Long Description | AJ1: Sources2 | AK1: Contact Email2 | AL1: Column1 | AM1: Supply Chain Segment | AN1: Long description3
A2: 1001 | B2: Pre-commercial/ startup | C2: Upstream | D2: Aether | E2: Yes | F2: Aether | G2: Cathode raw materials | H2: Lithium | I2: https://www.aetherbio.com/ | J2: 1455 Adams Dr | K2: Menlo Park | L2: CA | M2: US | N2: 94025 | O2: 415-316-3591 | P2: 37.478008 | Q2: -122.14252 | R2: 40 | U2: Aether | V2: https://www.aetherbio.com/ | W2: Aether | X2: CA | Y2: US | Z2: VP | AA2: 45339 | AC2: Aether engineers enzymes to make novel products. It recently developed a cheaper, faster and more sustainable direct lithium extraction technology using robotics, machine learning, and synthetic biology. | AD2: 27
A3: 1002 | B3: Pre-commercial/ startup | C3: Upstream | D3: Alaska Energy Metals Corp | E3: No | F3: Nikolai Project | G3: Mining & metals | H3: Nickel, copper, cobalt, chromium, iron, platinum, palladium, gold | I3: https://alaskaenergymetals.com/ | K3: Delta Junction | L3: AK | M3: US | O3: 907-677-7479 | P3: 63.5236 | Q3: -145.8222 | U3: Alaska Energy Metals Corp | V3: https://alaskaenergymetals.com/ | W3: Vancouver | X3: BC | Y3: US | Z3: MK | AA3: 45872 | AB3: https://www.morningstar.com/news/accesswire/1052272msn/alaska-energy-metals-enters-memorandum-of-understanding-with-american-electric-vehicle-manufacturer-lucid-and-other-mining-and-processing-companies | AC3: Alaska Energy Metals is a mineral exploration company focused on developing its large-scale Nikolai Project in Alaska to become a domestic source of strategic and critical metals for North America. | AD3: 30 | AE3: The company is actively exploring the site to define the resources they will focus on. They also have an office in Anchorage, AK.
A4: 1003 | B4: Commercial | C4: Upstream | D4: Albemarle Corporation | E4: Yes | F4: Albemarle Corporation, Silver Peak NV | G4: Cathode raw materials | H4: Lithium carbonate - crude | I4: https://www.albemarle.com/ | J4: HWY 265 | K4: Silver Peak | L4: NV | M4: US | N4: 89047 | O4: 775-937-2222 | P4: 37.740208 | Q4: -117.79232 | R4: 75 | S4: 5000 | T4: MT contained Li/yr | U4: Albermarle | V4: https://www.albermarle.com/ | W4: Charlotte | X4: NC | Y4: US | Z4: VP MK | AB4: Capacity from BNEF: Interactive Datasets / Metals/ Mine Assets Map/ Lithium; albermarle.com; Questionnaire; https://www.leg.state.nv.us/App/InterimCommittee/REL/Document/16038#:~:text=We%20have%2065%20employees%20and,is%20about%20%2494%2C000%20a%20year.&text=We%20thank%20you%20for%20the%20opportunity%20to%20speak%20to%20you%20today.&text=Global%20specialty%20chemicals%20company%20with,lithium%2C%20bromine%20and%20refining%20catalysts; https://www.mining.com/albemarle-to-double-lithium-production-in-nevada/ | AC4: Albemarle is a chemical company that provides lithium carbonate and lithium hydroxide as cathode precursors, lithium bis-(oxalato)borate for liquid electrolytes, and lithium sulfide as a solid electrolyte. | AD4: 27 | AE4: Expects to double production; Expansion possible after completing federal permitting in Feb 2026
A5: 1004 | B5: Commercial | C5: Upstream | D5: Albemarle Corporation | E5: Yes | F5: Albemarle - Kings Mountain, NC | G5: Cathode raw materials | H5: Lithium hydroxide - crude | I5: https://www.albemarle.com/ | J5: 348 Holiday Inn Drive | K5: Kings Mountain | L5: NC | M5: US | N5: 28086 | O5: 704-739-2501 | P5: 35.220466 | Q5: -81.341653 | R5: 170 | S5: 5500 | T5: MT contained Li/yr | U5: Albermarle | V5: https://www.albemarle.com/ | W5: Charlotte | X5: NC | Y5: US | Z5: VP | AA5: 44417 | AB5: albermarle.com; BNEF: US Supply Chain Security; Questionnaire; https://www.shelbystar.com/story/news/2022/03/25/kings-mountain-corporation-restart-lithium-mining/7130284001/ | AC5: Albemarle is a chemical company that provides lithium carbonate and lithium hydroxide as cathode precursors, lithium bis-(oxalato)borate for liquid electrolytes, and lithium sulfide as a solid electrolyte. | AD5: 27 | AE5: Pilot facility that mines spodumene, produces battery grade Li-hydroxide, Li-carbonate, and more
A6: 1005 | B6: Planned | C6: Upstream | D6: American Lithium | E6: No | F6: Tonopah Lithium Claims (TLC) Project | G6: Direct lithium extraction | H6: Lithium Sedimentary | I6: https://americanlithiumcorp.com/tlc-lithium-project/ | K6: Tonopah | L6: NV | M6: US | N6: 89049 | O6: 604-428-6126 | P6: 38.125 | Q6: -117.285 | S6: 38000 | T6: MT contained Li/yr | U6: American Lithium Corp | V6: https://americanlithiumcorp.com/ | W6: Vancouver | X6: BC | Y6: Canada | Z6: MK | AA6: 46064 | AB6: https://americanlithiumcorp.com/wp-content/uploads/2026/01/American-Lithium-Investor-Presentation-2026-01-05.pdf; https://americanlithiumcorp.com/tlc-lithium-project/ | AC6: American Lithium develops large-scale lithium projects in Nevada and Peru, utilizing sustainable mining and extraction methods to supply battery-grade lithium for the EV and energy storage sectors. | AD6: 27 | AE6: SOP 2028
A7: 1006 | B7: Pre-commercial/ startup | C7: Upstream | D7: Anson Resources | E7: No | F7: Paradox Lithium Project | G7: Direct lithium extraction | H7: Lithium Carbonate | I7: https://www.ansonresources.com/ | K7: Moab | L7: UT | M7: US | N7: 84532 | O7: 702 759 0182 | P7: 38.572695 | Q7: -109.54767 | R7: 5 | S7: 13000 | T7: MT contained Li/yr | U7: Anson Resources | V7: https://www.ansonresources.com/ | W7: West Perth | X7: Western Australia | Y7: Australia | Z7: MK | AA7: 45649 | AB7: https://www.ansonresources.com/paradox_lithium_project/; https://www.businessnewsasia.com/2024050152386375-anson-resources-signs-lithium-supply-agreement-with-lg-energy-solution/; https://mining.com.au/anson-resources-completes-dfs-at-paradox-lithium-project-us/ | AC7: Anson Resources is an ASX-listed mineral resources company developing the Paradox Lithium Project in Utah, aiming to become a significant supplier of lithium carbonate for the global EV battery market. | AD7: 30 | AE7: Anson Resources has signed a binding offtake agreement with LG Energy Solution to supply battery-grade lithium carbonate from the Paradox Project.
A8: 1007 | B8: Planned | C8: Upstream | D8: Anson Resources | E8: No | F8: Green River DLE Demonstration Plant | G8: Direct lithium extraction | H8: Lithium Brine | I8: https://www.ansonresources.com/ | J8: Green River Industrial Site | K8: Green River | L8: UT | M8: US | N8: 84525 | P8: 38.9955 | Q8: 110.1597 | R8: 80 | U8: Posco Holdings; Anson Resources | V8: http://www.posco-inc.com/poscoinc/v3/eng/index.jsp; https://www.ansonresources.com/ | W8: Seoul; West Perth | X8: NA; Western Australia | Y8: South Korea; Australia | Z8: MK | AA8: 46064 | AB8: https://investingnews.com/anson-resources-update-on-cooperation-between-anson-and-posco-holdings-for-dle-green-river-demonstration-plant/; https://www.accessnewswire.com/newsroom/en/metals-and-mining/anson-resources-update-on-cooperation-between-anson-and-posco-holdings-for-dle-gr-1118215 | AC8: POSCO Holdings is a global leader in steel and battery materials; it is advancing proprietary DLE technology and securing North American lithium resources to support a resilient EV supply chain. | AD8: 30
A9: 1008 | B9: Planned | C9: Upstream | D9: Arcadium Lithium | E9: No | F9: https://jamesbay.allkem.co/en/ | G9: Cathode raw materials | H9: Spodumene concentrates | I9: https://arcadiumlithium.com/ | J9: northern Québec, approximately 130 km east of James Bay and the Cree Nation of Eastmain community. | L9: QC | M9: Canada | P9: 53.536891 | Q9: -80.545652 | R9: 250 (Planned) | S9: 8100 | T9: MT contained Li/yr | U9: Arcadium Lithium | V9: https://arcadiumlithium.com/ | W9: Shannon | Y9: Ireland | Z9: VP | AA9: 44930 | AB9: https://www.mining-technology.com/news/canada-nod-galaxy-james-lithium/?cf-view; https://www.allkem.co/contact; https://iaac-aeic.gc.ca/050/evaluations/proj/80141 | AC9: Arcadium Lithium (2024 merger of Alkem and Livent) delivers sustainable lithium products globally, from resources in Argentina and Australia and conversion assets in the U.S., Asia, and the U.K. | AD9: 29 | AE9: Alkem and Livent merged in 2024
A10: 1009 | B10: Pre-commercial/ startup | C10: Upstream | D10: BHE Renewables | E10: No | F10: CalEnergy Operations | G10: Direct lithium extraction | H10: Lithium | I10: https://www.bherenewables.com/ | J10: 7030 Gentry Rd | K10: Calipatria | L10: CA | M10: US | N10: 92233 | P10: 33.335889 | Q10: -115.65919 | R10: 240 | S10: 90000 | T10: MT contained Li/yr | U10: BHE Renewables | V10: https://www.bherenewables.com/ | W10: Des Moines | X10: IA | Y10: US | Z10: MK | AA10: 45649 | AB10: https://www.linkedin.com/company/forcustomersforcommunities/about/; https://www.bherenewables.com/projects/geothermal; https://www.bherenewables.com/news/customers/occidental-and-bhe-renewables-form-joint-venture--to-commercialize-terralithium-extraction-technology | AC10: BHE Renewables owns and operates renewable energy projects, including geothermal facilities, and is collaborating with Occidental to develop lithium extraction technologies. | AD10: 21 | AF10: Dan Winters | AG10: dan.winters@bherenewables.com | AH10: 515-240-8395 | AI10: BHE Renewables, in partnership with Occidental and TerraLithium, is developing lithium extraction capabilities using patented Direct Lithium Extraction (DLE) technology at its Imperial Valley geothermal plants. This collaboration aims to produce high-purity lithium hydroxide and lithium carbonate to meet the rising demand for battery materials. TerraLithium's environmentally responsible approach processes brine extracted during geothermal energy production, supporting clean energy goals.
A11: 1010 | B11: Planned | C11: Upstream | D11: Canada Nickel Company | E11: No | F11: Crawford | G11: Cathode raw materials | H11: Nickel concentrates | I11: https://canadanickel.com/ | K11: Timmins | L11: ON | M11: Canada | P11: 48.476151 | Q11: -81.33084 | R11: 34 | S11: 48000 | T11: MT Ni/yr | U11: Canadian Nickel | V11: https://canadanickel.com/ | W11: Toronto | X11: ON | Y11: Canada | Z11: VP | AA11: 45463 | AB11: https://canadanickel.com/ https://northernontario.ctvnews.ca/study-shows-massive-nickel-deposit-in-northern-ont-even-more-profitable-than-expected-1.6600455; https://canadanickel.com/wp-content/uploads/2024/05/CNC_InvestorDeck_May2024_VF.pdf | AC11: Canada Nickel is advancing high-quality, high-potential nickel projects to deliver the metals to power the EV revolution and feed the stainless steel market. | AD11: 23 | AE11: Average annual production is expected to be438,000 tons of nickel over the 27-year peak production lifespan. The project will also produce significant amounts of cobalt, palladium, platinum, iron and chromite. Along with our flagship Crawford Nickel Project, Canada Nickel has acquired multiple properties in the region. Unlocking the potential for a Timmins Zero Carbon Nickel District with the consolidation of twenty plus nickel targets.
A12: 1011 | B12: Planned | C12: Upstream | D12: Canadian Royalties | E12: No | F12: Nunavik Nickel Project | G12: Cathode raw materials | H12: Nickel | I12: https://www.canadianroyalties.com/ | J12: Raglan Rd | K12: Donaldson | L12: QC | M12: Canada | N12: J0M 1K0 | P12: 61.561675 | Q12: -73.42748 | R12: 380 (Planned) | U12: Canadian Royalties | V12: https://www.canadianroyalties.com/ | W12: Montreal | X12: QC | Y12: Canada | Z12: MK | AA12: 45649 | AB12: https://www.canadianroyalties.com/articles/20230418200434/towards-phase-the-nunavik-nickel-project.html; https://www.mining-technology.com/marketdata/five-largest-nickel-mines-canada-2020/ | AC12: Canadian Royalties operates one of Canada’s largest nickel mining projects, supporting the growing demand for battery materials in the electric vehicle market. | AD12: 22
A13: 1012 | B13: Planned | C13: Upstream | D13: Century Lithium | E13: No | F13: Clayton Valley Lithium Project | G13: Cathode raw materials | H13: Lithium carbonate - crude | I13: https://www.centurylithium.com/ | K13: Clayton Valley | L13: NV | M13: US | N13: 89047 | P13: 37.752532 | Q13: -117.59062 | R13: 183 (Planned) | S13: 27400 | T13: MT/yr LCE | U13: Century Lithium Corp. | V13: https://www.centurylithium.com/ | W13: Vancouver | X13: BC | Y13: Canada | Z13: VP MK | AB13: Jay DB; www.centurylithium.com/_resources/technical-reports/cyp_pfs_amended_march_15th-2021.pdf?v=0.651?v=0.909?v=0.389; https://www.sudburyminingsolutions.com/top-stories/having-nickel-in-timmins-extremely-attractive-says-ceo-6601589; https://www.centurylithium.com/_resources/technical-reports/cyp_pfs_amended_march_15th-2021.pdf?v=0.483; consulting with Avicenne | AC13: Century Lithium is a Canadian-based advanced stage lithium exploration company advancing towards its goal of producing high-purity lithium carbonate for the electric vehicle and battery storage market. | AD13: 27 | AE13: SOP 203x
A14: 1013 | B14: Under Construction | C14: Upstream | D14: Chevron USA | E14: No | F14: East Texas Southwest Arkansas Lithium Project | G14: Lithium | H14: Direct Lithium Extraction (DLE) | I14: https://www.chevron.com | J14: ~125,000 net acres in the Smackover Formation | L14: TX & AK | M14: US | O14: 925-842-1000 | P14: 33.021943 | Q14: -94.060902 | U14: Chevron Corp | V14: https://www.chevron.com | W14: Houston | X14: TX | Y14: US | Z14: MK | AA14: 45867 | AB14: https://www.businesswire.com/news/home/20250617717350/en/Chevron-Enters-Domestic-Lithium-Sector-to-Support-U.S.-Energy-Security, https://www.ogj.com/energy-transition/article/55297744/chevron-enters-us-lithium-sector-with-leasehold-acquisitions | AC14: Chevron is a multinational energy corporation that has recently entered the domestic lithium sector to support U.S. energy security and expand its new energies business. | AD14: 25
A15: 1014 | B15: Pre-commercial/ startup | C15: Upstream | D15: Cobalt 27 Capital Corporation | E15: No | F15: Cobalt 27 Capital Corporation | G15: Cathode raw materials | H15: Cobalt ore | I15: https://nickel28.com/ | J15: 700 West Georgia Street | K15: Vancouver | L15: BC | M15: Canada | N15: BC V7Y 1B3 | O15: 414-560-9070 | P15: 49.282945 | Q15: -123.11916 | R15: 4 | U15: Nickel 28 | V15: https://nickel28.com/ | W15: Toronto | X15: ON | Y15: Canada | Z15: VP | AA15: 45463 | AB15: https://www.nickel28.com/investors/investors-overview/cobalt-27--change-of-auditors?turl=cobalt-27--change-of-auditors#:~:text=Cobalt%2027%20Capital%20Corp.%20is,portfolio%20of%206%20cobalt%20royalties. | AC15: Cobalt 27 Capital Corp. offers pure-play exposure to cobalt for the electric vehicle and battery energy storage markets, involving a diverse portfolio of streams, royalties, and direct investments. | AD15: 28 | AE15: Provider of mineral exploration services based in Toronto, Canada. The company specializes in offering exposure to metals integral to key technologies of the electric vehicle and battery energy storage markets. Has several assets in Canada, but none are operating yet.
A16: 1015 | B16: Commercial | C16: Upstream | D16: Compass Minerals | E16: No | F16: Salt, SOP and Magnesium Chloride Plants | G16: Direct lithium extraction | H16: Lithium | I16: https://www.compassminerals.com/ | J16: 765 N 10500 W | K16: Ogden | L16: UT | M16: US | N16: 84404 | O16: 801-731-3100 | P16: 41.283582 | Q16: -112.22673 | R16: 400 | S16: 11000 | T16: MT contained Li/yr | U16: Compass Minerals | V16: https://www.compassminerals.com/ | W16: Overland Park | X16: KA | Y16: US | Z16: MK | AA16: 45649 | AB16: https://investors.compassminerals.com/investors-relations/investor-news/press-release-details/2022/Compass-Minerals-Announces-Selection-of-Direct-Lithium-Extraction-DLE-Technology-Provider-Attractive-Economics-and-Positive-Sustainability-Profile-for-First-Phase-of-Lithium-Project/default.aspx; https://www.reuters.com/business/autos-transportation/compass-minerals-picks-lithium-extraction-technology-supply-ford-others-2022-09-14/; https://www.compassminerals.com/who-we-are/locations/ | AC16: Compass Minerals is a leading provider of essential minerals and is expanding its portfolio to include lithium extraction. | AD16: 18 | AE16: Compass Minerals is developing a lithium extraction facility to supply Ford and other automakers with lithium carbonate and hydroxide.
A17: 1016 | B17: Pre-commercial/ startup | C17: Upstream | D17: Controlled Thermal Resources | E17: No | F17: Hell's Kitchen Lithium and Power Project | G17: Cathode raw materials | H17: Lithium carbonate - crude | I17: https://www.cthermal.com/ | J17: 124 West 9th St | K17: Imperial | L17: CA | M17: US | N17: 92251 | P17: 32.848538 | Q17: -115.57109 | R17: 50 | S17: 5800 | T17: MT contained Li/yr | U17: Controlled Thermal Resources | V17: https://www.cthermal.com/ | W17: Brisbane | X17: Qld | Y17: Australia | Z17: VP | AA17: 44865 | AB17: https://www.prnewswire.com/news-releases/gm-to-source-us-based-lithium-for-next-generation-ev-batteries-through-closed-loop-process-with-low-carbon-emissions-301324868.html. https://www.crunchbase.com/organization/controlled-thermal-resources; Questionnaire | AC17: Controlled Thermal Resource Holdings, Inc. is an American company advancing the development of lithium and battery material products and renewable energy. | AD17: 21 | AE17: GM formed strategic investment and commercial collaboration to obtain lithium; Stage 1 is 20k Lithium hydroxide (5,800 MT contained Li); Facility is also listed in battery grade materials as it will make both battery grade lithium carbonate and hydroxide
A18: 1017 | B18: Planned | C18: Upstream | D18: Corporation Lithium Éléments Critiques | E18: No | F18: Rose Lithium-Tantalum project | G18: Cathode raw materials | H18: Lithium hydroxide - crude | I18: https://www.cecorp.ca/en/ | J18: 1080 Côte du Beaver Hall, Suite 2101 | K18: Montreal | L18: QC | M18: Canada | N18: H2Z 1S8 | O18: 514 904-1496 | P18: 45.502542 | Q18: -73.565493 | R18: 500 (Planned) | S18: 5727 | T18: MT contained Li/yr | U18: Corporation Lithium Éléments Critiques | V18: https://www.cecorp.ca/en/ | W18: Montreal | X18: QC | Y18: Canada | Z18: VP | AA18: 44417 | AB18: cecorp.ca/en; Propulsion Quebec | AC18: Critical Elements Lithium Corporation owns several lithium mining properties in Quebec. They seek to further their Rose Lithium-Tantalum project from advanced exploration to production. | AD18: 24 | AE18: Open pit mining of hard rock lithium (spodumene) and processing to technical(6% Li2O) and chemical (5% Li2O) grades of lithium concentrate; 186,327 MT of chem grade conc and 50,205 MT of tech grade conc.; Capacity was calculated from these values
A19: 1018 | B19: Commercial | C19: Upstream | D19: Eagle Graphite | E19: No | F19: Black Crystal Graphite Quarry | G19: Anode raw materials | H19: Natural graphite | I19: https://www.eaglegraphite.com/ | K19: Slocan Park | L19: BC | M19: Canada | N19: VOG 2E0 | P19: 49.529667 | Q19: -117.61321 | R19: 8 | S19: 2500 | T19: MT | U19: Eagle Graphite | V19: https://www.eaglegraphite.com/ | W19: Toronto | X19: ON | Y19: Canada | Z19: MK | AB19: https://miningdataonline.com/property/1630/Black-Crystal-Project.aspx; https://finance.yahoo.com/news/eagle-graphite-provides-corporate-215100199.html?guccounter=1&guce_referrer=aHR0cHM6Ly9jaGF0Z3B0LmNvbS8&guce_referrer_sig=AQAAAMcZQmCC4Dpp6gcDivA2gPalxFQTTZQQ62uqbqnymiUeViK8AdyvWGENtGmHxnfMplbeOKza1E7M8kPqraSUY9NH3EVO2Gxf1wJSJCoHZ2dMKxVgl617Qnkb3nZ4mBQFejIp-eiBQJG2ZkRvdnDoGABYfJULQ4oFZuvndJZuZ4kM | AC19: Eagle Graphite is a mining company producing battery-grade graphite from its Black Crystal Quarry in British Columbia, Canada. | AD19: 18 | AE19: The company is facing financial difficulties. Plan to expand to 7500 MT
A20: 1019 | B20: Pre-commercial/ startup | C20: Upstream | D20: Electric Metals (USA) Limited | E20: No | F20: Emily Manganese Project | G20: Mining & metals | H20: Manganese, iron | I20: https://electricmetals.com/ | K20: Crow Wing County | L20: MN | M20: US | O20: 303-656-9197 | P20: 46.7766 | Q20: -93.9566 | U20: Electric Metals (USA) Limited | V20: https://electricmetals.com/ | W20: Toronto | X20: ON | Y20: Canada | Z20: MK | AA20: 45872 | AB20: https://www.theassay.com/mining-company-profiles/electric-metals-usa-limited/ | AC20: Electric Metals (USA) Limited is a mineral development company focused on advancing North America's highest-grade manganese deposit to support the clean energy transition. | AD20: 23 | AE20: The Emily Manganese Project is the company's flagship asset. A Preliminary Economic Assessment (PEA) is underway.
A21: 1020 | B21: Under Construction | C21: Upstream | D21: Energy Source Minerals | E21: No | F21: Project ATLis | G21: Cathode raw materials | H21: Lithium | I21: https://www.esminerals.com/atlis | J21: Salton Sea | K21: Imperial County | L21: CA | M21: US | P21: 33.313056 | Q21: -115.83444 | R21: 62 (Planned) | S21: 20000 | T21: MT Li/yr | U21: Energy Source Minerals | V21: https://www.esminerals.com/ | W21: Carlsbad | X21: CA | Y21: US | Z21: VP | AA21: 45289 | AB21: https://www.esminerals.com/ https://www.prnewswire.com/news-releases/energysource-minerals-receives-approvals-on-project-atlis-salton-sea-based-geothermal-extraction-operation-301428234.html; https://www.prnewswire.com/news-releases/energysource-minerals-esm-announces-contract-with-ford-for-geothermal-lithium-301830259.html#:~:text=Project%20ATLiS%20in%20California's%20Salton,the%20auto%20industry%20per%20year. | AC21: EnergySource Minerals is a California-based company focused on its lithium project, Project ATLiS, with environmental targets to decrease land use, water depletion, and CO2 emissions. | AD21: 25
A22: 1021 | B22: Planned | C22: Upstream | D22: Exxon Mobil | E22: No | F22: Saltwerx | G22: Direct lithium extracion | H22: Lithium Brine | I22: https://corporate.exxonmobil.com/ | J22: Columbia and Lafayette Counties | K22: Magnolia | L22: AR | M22: US | N22: 71753 | P22: 33.2671 | Q22: -93.2407 | S22: 100000 | T22: MT/yr | U22: Exxon Mobile | V22: https://corporate.exxonmobil.com/ | W22: Spring | X22: TX | Y22: US | Z22: MK | AA22: 46064 | AB22: https://lowcarbon.exxonmobil.com/about-us/community/our-footprint-in-arkansas; https://corporate.exxonmobil.com/news/news-releases/2024/1120_exxonmobil-and-lg-chem-sign-mou-for-lithium-offtake; https://arkansasdeltainformer.com/u-s-oil-giants-billion-dollar-lithium-investment-set-to-transform-arkansass-smackover-formation/ | AC22: ExxonMobil is an international energy company developing a large-scale lithium business by leveraging subsurface expertise and Direct Lithium Extraction (DLE) to supply domestic battery-grade materials for electric vehicles. | AD22: 28 | AE22: 2027 SOP
A23: 1022 | B23: Planned | C23: Upstream | D23: Fortune Minerals Limited | E23: No | F23: NICO Project | G23: Cathode raw materials | H23: Cobalt ore | I23: https://www.fortuneminerals.com/ | K23: Fort Smith | L23: NT | M23: Canada | N23: X0E 1 A0 | O23: 519-858-8188 | P23: 63.548012 | Q23: -116.74057 | R23: 90 (Planned) | S23: 685 | T23: MT/yr Co | U23: Fortune Minerals Limited | V23: https://www.fortuneminerals.com/ | W23: London | X23: ON | Y23: Canada | Z23: VP | AA23: 45289 | AB23: https://www.fortuneminerals.com/; https://s1.q4cdn.com/337451660/files/doc_presentations/2023/231001-fortune-minerals-nico-project-presentation.pdf; https://www.miningweekly.com/print-version/nico-goldcobaltbismuthcopper-mine-project-canada-update-2023-12-15 | AC23: Fortune Minerals Limited is a North American development stage mining company that is focused on advancing the vertically integrated NICO cobalt-gold-bismuth-copper project, in the Northwest Territories. | AD23: 26 | AE23: Nico is a vertically integrated cobalt-gold-bismuth-copper project that is slated to include a mine in Northwest Territories and a hydrometallurgical refinery in Alberta. According to a 2020 development plan, an underground mine at Nico and an associated refinery to be built in Alberta would produce an average of 1,800 metric tons of battery-grade cobalt sulfate. Co back calculated from CoSO4
A24: 1023 | B24: Planned | C24: Upstream | D24: FPX Nickel | E24: No | F24: Baptiste Nickel Project | G24: Cathode raw materials | H24: Nickel concentrates | I24: https://www.fpxnickel.com/ | J24: Decar Ni District | K24: near Fort St. James | L24: BC | M24: Canada | O24: 604-681-8600 | P24: 54.446905 | Q24: -124.25567 | R24: 1100 (Planned) | S24: 59100 | T24: MT contained Ni/yr | U24: FPX Nickel Corp. | V24: https://www.fpxnickel.com/ | W24: Vancouver | X24: BC | Y24: Canada | Z24: VP | AA24: 45095 | AB24: Jay DB; https://fpxnickel.com/2022/09/fpx-nickel-to-prepare-updated-mineral-resource-estimate-for-baptiste-nickel-project-with-inclusion-of-total-nickel-cobalt-and-iron-grades/; https://fpxnickel.com/2023/05/fpx-nickel-achieves-successful-production-of-battery-grade-nickel-sulphate-from-optimized-refinery-flowsheet/; https://fpxnickel.com/wp-content/uploads/2023/04/FPX-Presentation-Q2-2023-v1-1.pdf | AC24: FPX Nickel is a nickel mining company that refines the ore by grinding it down and separating the metals. The nickel is used for nickel sulphate for EV battery cathodes. | AD24: 30 | AE24: Preliminary feasibility study (PFS) is looking at supplying the stainless steel market (base case) with an option of further upgrading the concentrate to produce battery grade nickel sulfate and cobalt-rich products for electric vehicles; PFS expected in September 2023; FPX was able to make battery grade nickel sulfate using an optimized flowsheet on the lab scale
A25: 1024 | B25: Planned | C25: Upstream | D25: Frontier Lithium | E25: No | F25: PAK Lithium Project | G25: Cathode raw materials | H25: Spodumene concentrates | I25: https://www.frontierlithium.com | J25: Red Lake | K25: Red Lake | L25: ON | M25: Canada | N25: P0V 2M0 | O25: 705-897-7622 | P25: 52.6 | Q25: -93.37 | R25: 132 (Planned) | S25: 160000 | T25: MT contained Li/yr | U25: Frontier Lithium | V25: https://www.frontierlithium.com/ | W25: Val Caron | X25: ON | Y25: Canada | Z25: VP MK | AB25: https://www.cruxinvestor.com/posts/frontier-lithium-north-americas-most-advanced-lithium-company#:~:text=The%20company%20is%20advancing%20its,top%20tier%20lithium%20asset%20globally. https://www.frontierlithium.com/news; https://www.nsenergybusiness.com/projects/pak-lithium-project/; | AC25: Frontier Lithium is an emerging lithium mineral and salts company focused on the development of its 100%-owned PAK Lithium Project in Ontario. | AD25: 28 | AE25: Start with spodumene concentrates and eventually lithium chemicals - Lithium Hydroxide 12,520 tons per year --Lithium carbonate 7,360 tons per year in a processing facility in the Great Lakes region of the U.S.; SOP 203x
A26: 1025 | B26: Commercial | C26: Upstream | D26: G6 Energy Corp | E26: No | F26: Kearney Mine | G26: Anode raw materials | H26: Natural graphite | I26: gsixenergy.com | K26: Kearney | L26: ON | M26: Canada | N26: P0A 0B1 | O26: 647-254-0870 | P26: 45.631667 | Q26: -79.115124 | R26: 20 | S26: 48000 | T26: MT contained graphite/yr | U26: G6 Energy Corp | V26: gsixenergy.com | W26: Toronto | X26: ON | Y26: Canada | Z26: MK | AA26: 45688 | AB26: Questionnaire | AC26: G6 Energy Corp. is a private company based in Toronto, Ontario that is developing a fully integrated natural graphite anode material producer. | AD26: 22 | AE26: G6 owns a fully permitted, past producing flake graphite mine located approximately 250 km north of Toronto, Ontario, Canada. G6 Energy has also established a joint venture and technology collaboration arrangement with a South Korean process technology provider for the exclusive right to exploit both its proven processing IP for the production of spheronized purified graphite (SPG), and its extensive process and configuration expertise for the production of coated SPG (CSPG). | AF26: Ian McCallum | AG26: info@gsixenergy.com | AH26: 647-254-0870
A27: 1026 | B27: Commercial | C27: Upstream | D27: GKN Hoeganaes Gallatin | E27: No | F27: GKN Hoeganaes Gallatin | G27: Cathode raw materials | H27: Iron powder | I27: https://www.gknpm.com/en/our-businesses/gkn-hoeganaes/ | J27: 1315 Airport Road | K27: Gallatin | L27: TN | M27: US | N27: 37066 | O27: 615-451-2000 | P27: 36.372206 | Q27: -86.422458 | R27: 220 | S27: 250000 | T27: MT/year | U27: GKN Hoeganaes owned by Dowlais | V27: https://www.gknpm.com/en/our-businesses/gkn-hoeganaes/ | W27: London | Y27: UK | Z27: SD | AA27: 45429 | AB27: Questionnaire | AC27: GKN Hoeganaes Gallatin specializes in water-atomized iron powder production and material manufacturing for a variety of industries. With seven manufacturing facilities, it provides localized supply and support to customers worldwide. | AD27: 30 | AF27: Kylan McQuaig | AG27: kylan.mcquaig@hoeganaes.com | AH27: 856-303-2729
A28: 1027 | B28: Commercial | C28: Upstream | D28: Glencore | E28: Yes | F28: Raglan Mine | G28: Cathode raw materials | H28: Nickel concentrates | I28: https://www.glencore.ca/en/raglan | J28: 120 Avenue De L'Aeroport | K28: Rouyn-Noranda | L28: QC | M28: Canada | N28: J9Y 0G1 | O28: 819-762-7800 | P28: 48.213817 | Q28: -78.828334 | R28: 640 | S28: 40000 | T28: MT contained Ni/yr | U28: Glencore | V28: https://www.glencore.com/ | W28: Baar | X28: Zug | Y28: Switzerland | Z28: VP | AA28: 44421 | AB28: glencore.ca; https://www.glencore.ca/en/raglan/who-we-are/at-a-glance | AC28: Glencore is one of the world’s largest global diversified natural resource companies and a major producer of more than 60 commodities, including nickel and cobalt for the lithium-ion supply chain. | AD28: 30
A29: 1028 | B29: Commercial | C29: Upstream | D29: Glencore | E29: Yes | F29: Raglan Mine | G29: Cathode raw materials | H29: Cobalt concentrates | I29: https://www.glencore.ca/en/raglan | J29: 120 Avenue De L'Aeroport | K29: Rouyn-Noranda | L29: QC | M29: Canada | N29: J9Y 0G1 | O29: 819-762-7800 | P29: 48.213817 | Q29: -78.828334 | R29: 640 | S29: 827 | T29: MT contained Co/yr | U29: Glencore | V29: https://www.glencore.com/ | W29: Baar | X29: Zug | Y29: Switzerland | Z29: VP | AA29: 44421 | AB29: glencore.ca; https://www.glencore.ca/en/raglan/who-we-are/at-a-glance; https://www.glencore.ca/en/raglan/what-we-do/our-mining-activity | AC29: Glencore is one of the world’s largest global diversified natural resource companies and a major producer of more than 60 commodities, including nickel and cobalt for the lithium-ion supply chain. | AD29: 30 | AE29: Production value is actual 2020 production
A30: 1029 | B30: Commercial | C30: Upstream | D30: Glencore | E30: Yes | F30: Glencore Sudbury INO | G30: Cathode raw materials | H30: Nickel matte | I30: https://www.glencore.ca/en/sudburyino | J30: 2 Longyear Dr | K30: Sudbury | L30: ON | M30: Canada | N30: P0M 1S0 | O30: 705-693-2761 | P30: 46.586931 | Q30: -80.769922 | R30: 600 | S30: 75695 | T30: MT contained metal/yr | U30: Glencore | V30: https://www.glencore.com/ | W30: Baar | X30: Zug | Y30: Switzerland | Z30: VP | AA30: 44421 | AB30: glencore.ca; https://www.yellowpages.ca/bus/Ontario/Falconbridge/Sudbury-Integrated-Nickel-Operations/100823081.html#:~:text=Sudbury%20Integrated%20Nickel%20Operations%20%2D%201%20Longyear%20Dr%2C%20Falconbridge%2C%20ON; | AC30: Glencore is one of the world’s largest global diversified natural resource companies and a major producer of more than 60 commodities, including nickel and cobalt for the lithium-ion supply chain. | AD30: 30 | AE30: Sudbury INO includes 2 underground mines, 1 mill and 1 smelter; smelter also recycles aerospace and other secondary metals as well as batteries, including LIBs. Smelter is a leader in recycling pre-treated (discharged and upgraded) Li-ion batteries in North America
A31: 1030 | B31: Commercial | C31: Upstream | D31: Glencore | E31: Yes | F31: Glencore Sudbury INO | G31: Cathode raw materials | H31: Cobalt | I31: https://www.glencore.ca/en/sudburyino | J31: 2 Longyear Dr | K31: Sudbury | L31: ON | M31: Canada | N31: P0M 1S0 | O31: 705-693-2761 | P31: 46.586931 | Q31: -80.769922 | R31: 600 | S31: 400 | T31: MT contained metal/yr | U31: Glencore | V31: https://www.glencore.com/ | W31: Baar | X31: Zug | Y31: Switzerland | Z31: MK | AA31: 46064 | AB31: https://www.glencore.com/media-and-insights/news/full-year-2025-production-report; https://www.glencore.ca/en/sudburyino/what-we-do | AC31: Glencore is one of the world’s largest global diversified natural resource companies and a major producer of more than 60 commodities, including nickel and cobalt for the lithium-ion supply chain. | AD31: 30
A32: 1031 | B32: Planned | C32: Upstream | D32: Graphite One | E32: No | F32: Graphite Creek | G32: Anode raw materials | H32: Graphite concentrates | I32: https://www.graphiteoneinc.com/ | K32: near Nome | L32: AK | M32: US | P32: 64.512432 | Q32: -165.42696 | R32: 200 (Planned) | S32: 57000 | T32: MT contained graphite/yr | U32: Graphite One | V32: https://www.graphiteoneinc.com/ | W32: Anchorage | X32: AK | Y32: US | Z32: VP | AA32: 45095 | AB32: Jay DB; PitchBook; graphiteoneinc.com; https://www.akbizmag.com/industry/alaska-native/bsnc-invests-2m-into-graphite-one/#:~:text=Capacity%20at%20the%20Graphite%20Creek,to%20200%20workers%20year%2Dround.&text=A%20proposed%20graphite%20mine%20near,the%20region's%20Alaska%20Native%20corporation. | AC32: Graphite One plans to mine, refine, and manufacture graphite for use in anodes electric car batteries. They are in the pre-feasibility stage. | AD32: 22 | AE32: Company is in pre-feasibility stage; Want to develop a CSG production facility likely in WA state, but no further details were available.
A33: 1032 | B33: Planned | C33: Upstream | D33: Green Technology Metals | E33: No | F33: Flagship Seymour Project | G33: Cathode raw materials | H33: Spodumene concentrates | I33: https://www.greentm.com.au/seymour-project | J33: near the township of Armstrong | K33: Armstrong | L33: ON | M33: Canada | P33: 48.382221 | Q33: -89.2461 | U33: Green Technology Metals | V33: https://www.greentm.com.au | W33: Subiaco | X33: WA | Y33: Australia | Z33: VP | AA33: 45305 | AB33: https:/https://news; lgensol.com/company-news/press-releases/1749//www.greentm.com.au/; https://news.lgensol.com/company-news/press-releases/1749/ https://www.greentm.com.au/seymour-project; | AC33: Green Technology Metals is a North American company focused on lithium exploration and development in Ontario. It owns 10 high-grade hard rock spodumene assets. | AD33: 24 | AE33: Project expected to move into development in 2024.
A34: 1033 | B34: Planned | C34: Upstream | D34: Hard Creek Nickel Corp | E34: No | F34: Turnagain Nickel Project - Phase 1 | G34: Cathode raw materials | H34: Nickel concentrates | I34: https://www.gigametals.com/ | K34: Stikine Region | L34: BC | M34: Canada | N34: V0C 2Z0 | P34: 58.474411 | Q34: -128.85263 | R34: 9 | S34: 33000 | T34: MT contained Ni/yr | U34: Giga Metals Mitsubishi Corporation | V34: https://www.gigametals.com mitsubishi.com/ | W34: Vancouver Tokyo | X34: BC Tokyo | Y34: Canada, Japan | Z34: VP | AA34: 45095 | AB34: Jay DB; gigametals.com/site/assets/files/4910/giga_metals_corporate_presentation_june_15-_2023.pdf | AC34: Hard Creek Nickel Corp is a mining and processing facility that utilizes froth floatation to separate cobalt and nickel from the raw ore. | AD34: 23 | AE34: JV between Giga Metals and Mitsubishi; Pre-feasibility study July 2023; targeting Class1 Ni; $1.4B for Phase 1; Phase II would double production and cost $0.5B
A35: 1034 | B35: Planned | C35: Upstream | D35: Hard Creek Nickel Corp | E35: No | F35: Turnagain Nickel Project - Phase 1 | G35: Cathode raw materials | H35: Cobalt concentrates | I35: https://www.gigametals.com/ | K35: Stikine Region | L35: BC | M35: Canada | N35: V0C 2Z0 | P35: 58.474411 | Q35: -128.85263 | R35: 9 | S35: 1800 | T35: MT contained Co/yr | U35: Giga Metals Mitsubishi Corporation | V35: https://www.gigametals.com mitsubishi.com/ | W35: Vancouver Tokyo | X35: BC Tokyo | Y35: Canada, Japan | Z35: VP | AA35: 45095 | AB35: Jay DB; gigametals.com/site/assets/files/4910/giga_metals_corporate_presentation_june_15-_2023.pdf | AC35: Hard Creek Nickel Corp is a mining and processing facility that utilizes froth floatation to separate cobalt and nickel from the raw ore. | AD35: 23 | AE35: JV between Giga Metals and Mitsubishi; Pre-feasibility study July 2023; targeting Class1 Ni; $1.4B for Phase 1; Phase II would double production and cost $0.5B
A36: 1035 | B36: Pre-commercial/ startup | C36: Upstream | D36: In-Medix, Inc | E36: No | F36: Nevada Lithium Project | G36: Lithium | H36: Lithium | I36: https://www.exideindustries.com/ | L36: NV | M36: US | U36: Exide Industries Ltd | V36: https://www.exideindustries.com/ | W36: Kolkata | X36: West Bengal | Y36: India | Z36: MK | AA36: 45872 | AB36: https://economictimes.indiatimes.com/industry/renewables/exide-outlines-growth-strategy-with-dual-focus-on-lead-acid-lithium-ion-batteries/articleshow/122922132.cms, https://www.google.com/search?q=https://www.bseindia.com/xml-data/corpfiling/AttachLive/4ce415e9-4977-4df3-883a-8fc4d18721c1.pdf | AC36: Exide Industries is India's largest manufacturer of storage batteries, with a strategy to expand into lithium-ion cell production and secure raw material supply chains. | AD36: 24 | AE36: Exide Industries of India has acquired a significant equity stake in In-Medix, Inc., giving them access to lithium mining assets in Nevada to secure raw materials for their li-ion business
A37: 1036 | B37: Planned | C37: Upstream | D37: Ioneer | E37: No | F37: Rhyolite Ridge Project | G37: Mining & metals | H37: Lithium Carbonate & Boric acid | I37: https://www.ioneer.com/rhyolite-ridge-project/ | J37: Coyote Hole | K37: Esmeralda County | L37: NV | M37: US | N37: 89010 | O37: 725-212-4060 | P37: 37.8647 | Q37: -117.8285 | R37: 600 | S37: 24500 | T37: MT contained Li/yr | U37: Ioneer | V37: https://www.ioneer.com/ | W37: North Sydney | X37: NSW | Y37: Australia | Z37: MK | AA37: 46093 | AB37: https://www.ioneer.com/wp-content/uploads/2025/12/Ioneer_Year_End_2025_Release_FINAL.pdf; https://www.industrialinfo.com/ | AC37: Ioneer Ltd is an Australian-headquartered critical minerals developer focused on supplying battery-grade lithium and boron to the EV supply chain. | AD37: 20
A38: 1037 | B38: Commercial | C38: Upstream | D38: Ionic Mineral Technologies | E38: Yes | F38: Provo Production Campus | G38: Anode raw materials | H38: Nano-silicon | I38: https://ionicmt.com/ | J38: 652 S Lakeview Parkway, Bldg B | K38: Provo | L38: UT | M38: US | N38: 84601 | O38: 385-241-2320 | P38: 40.22498 | Q38: -111.71384 | R38: 11 | S38: 2000 | T38: MT Nano-silicon Anode active material | U38: Ionic Mineral Technologies | V38: https://ionicmt.com/ | W38: Provo | X38: UT | Y38: US | Z38: VP | AA38: 45289 | AB38: Questionnaire; https://ionicmt.com/ | AC38: Ionic Mineral Technologies is a vertically-integrated company supplying naturally derived, drop-in anode materials using a patented technology. Ionic Mineral Technologies owns the highest purity deposit of nano-structured clay. | AD38: 28 | AE38: Expected to increase to 25,000 MT in 2027
A39: 1038 | B39: Under construction | C39: Upstream | D39: Jervois Mining | E39: No | F39: Idaho Cobalt Project | G39: Cathode raw materials | H39: Cobalt concentrates | I39: https://www.jervoisidahocobalt.com/ | K39: Lemhi County | L39: ID | M39: US | O39: 208-756-4578 | P39: 45.130677 | Q39: -114.36158 | R39: 38 | S39: 1915 | T39: MT contained Ni/yr | U39: Jervois Mining | V39: https://www.jervoisglobal.com/ | W39: Hawthorn | X39: VIC | Y39: Australia | Z39: VP | AA39: 45092 | AB39: jervoisidahocobalt.com; jervoisglobal.com; BNEF: US Supply Chain Security; https://jervoisglobal.com/wp-content/uploads/2021/06/190348_Idaho_Cobalt_13112020_NI_43_101_Technical_Report-FILED-r1.pdf; https://wcsecure.weblink.com.au/pdf/JRV/02549021.pdf | AC39: Jervois Mining is constructing a nickel and cobalt refinery and mining company. The cobalt is refined into cobalt oxide and cobalt sulfate for use as a cathode precursor. | AD39: 28 | AE39: Facility will produce cobalt concentrate with gold and copper concentrate; Final construction was suspended due to inflation and low Co prices
A40: 1039 | B40: Planned | C40: Upstream | D40: Jindalee Lithium | E40: No | F40: McDermitt Lithium Project | G40: Cathode raw materials | H40: Lithium | I40: https://www.jindaleelithium.com | J40: Malheur County | K40: McDermitt | L40: NV | M40: US | P40: 42.001389 | Q40: -117.99667 | R40: 5 | S40: 95602.294 | T40: MT contained Li/yr | U40: Jindalee Lithium | V40: https://www.jindaleelithium.com | W40: West Perth | X40: Western Australia | Y40: Australia | Z40: VP | AA40: 45289 | AB40: https://www.jindaleelithium.com https://www.miningweekly.com/article/mcdermitt-lithium-project-us-update-2023-10-20; https://s3.ap-southeast-2.amazonaws.com/assets.jindaleelithium.com/app/uploads/2023/10/23083152/2023-AGM-Presentationv2.pdf | AC40: Jindalee Lithium aims to develop the company’s flagship McDermitt Lithium Project, supplying a resource vital to the electrification of America’s automotive industry. | AD40: 22 | AE40: McDermitt is the biggest lithium deposit in the US by contained lithium, with 21.5-million tons of lithium carbonate equivalent in mineral resource. Assumed 43 year mine life to get annual production
A41: 1040 | B41: Planned | C41: Upstream | D41: Lilac Solutions, Inc. | E41: No | F41: Lilac Solutions, Inc. | G41: Cathode raw materials | H41: Lithium | I41: https://www.lilacsolutions.com/ | K41: Box Elder County | L41: UT | M41: US | N41: 94607 | O41: 401-714-7906 | P41: 41.558967 | Q41: -113.15636 | R41: 250 (Planned) | U41: Lilac Solutions, Inc. | V41: https://www.lilacsolutions.com/ | W41: Oakland | X41: CA | Y41: US | Z41: VP MK | AB41: https://www.energy.gov/mesc/bipartisan-infrastructure-law-battery-materials-processing-and-battery-manufacturing-recycling; https://lilacsolutions.com/2022/07/lilac-solutions-continues-to-advance-world-class-kachi-lithium-project-with-lake-resources/ | AC41: Lilac Solutions is a company that plans to extract lithium from brine for use in lithium-ion batteries. | AD41: 17 | AE41: Developer of lithium extraction technology designed to absorb lithium from brine resources. The company's technology is based on the ion-exchange theory that facilitates the production of lithium from brine resources with minimal cost and low environmental footprint, enabling lithium producers to accelerate project development, boost lithium recovery, streamline operations and unlock new resources. Recipient of $50M from DE-FOA-2678 to demonstrate their technology; 202x SOP; Signed binding offtake agreement with Traxys for 10 years
A42: 1041 | B42: Under construction | C42: Upstream | D42: Lithium Americas | E42: No | F42: Thacker Pass | G42: Cathode raw materials | H42: Lithium Sedimentary | I42: https://www.lithiumamericas.com/ | J42: Orovada (nearest town) | K42: Humboldt County | L42: NV | M42: US | O42: 778-656-5820 | P42: 41.569975 | Q42: -117.78581 | R42: 65 | S42: 5640 | T42: MT contained Li/yr | U42: Lithium Americas Corp. | V42: https://www.lithiumamericas.com; https://www.lithiumamericas.com/_resources/pdf/investors/technical-reports/thacker-pass/Technical-Report-Thacker-Pass.pdf/ | W42: Vancouver | X42: BC | Y42: Canada | Z42: VP MK | AB42: lithiumamericas.com; BNEF: US Supply Chain Security, https://www.macrotrends.net/stocks/charts/LAC/lithium-americas/number-of-employees;https://lithiumamericas.com/usa/thacker-pass/ | AC42: Lithium Americas plans to use block mining to extract lithium ore. The ore will be processed using leaching techniques to produce battery grade lithium carbonate for cathodes. | AD42: 27 | AE42: Q4 2026 SOP; making progress with construction
A43: 1042 | B43: Pre-commercial/ startup | C43: Upstream | D43: LithiumBank Resources | E43: No | F43: Boardwalk Lithium Brine Project | G43: Direct lithium extraction | H43: Lithium hydroxide monohydrate | I43: https://www.lithiumbank.ca/ | K43: Sturgeon Lake | L43: AB | M43: Canada | N43: T0H 3N0 | P43: 54.5 | Q43: -118.5 | R43: 4 | S43: 34005 | T43: MT contained Li/yr | U43: LithiumBank Resources | V43: https://www.lithiumbank.ca/ | W43: Calgary | X43: AB | Y43: Canada | Z43: MK | AA43: 45649 | AB43: https://www.lithiumbank.ca/news/lithiumbank-announces-updated-pea-significantly-increases-pre-tax-npv8-to-usd-3-7-billion-and-reduces-opex-to-usd-4-588-per-lce-t-at-flagship-boardwalk-lithium-brine-project-alberta-canada; https://www.lithiumbank.ca/projects/boardwalk | AC43: LithiumBank Resources Corp. is a publicly traded company focused on developing its flagship projects, Boardwalk and Park Place, in Western Canada. | AD43: 21 | AE43: The Boardwalk Project encompasses approximately 572,237 acres, covering 100% of the Leduc reef complex.
A44: 1043 | B44: Pre-commercial/ startup | C44: Upstream | D44: LithiumBank Resources | E44: No | F44: Park Place Lithium Brine Project | G44: Direct lithium extraction | H44: Lithium hydroxide monohydrate | I44: https://www.lithiumbank.ca/ | K44: Fox Creek | L44: AB | M44: Canada | N44: T0H 0A6 | P44: 54.41168 | Q44: -116.80777 | R44: 4 | U44: LithiumBank Resources | V44: https://www.lithiumbank.ca/ | W44: Calgary | X44: AB | Y44: Canada | Z44: MK | AA44: 45667 | AB44: https://www.lithiumbank.ca/news/lithiumbank-announces-updated-pea-significantly-increases-pre-tax-npv8-to-usd-3-7-billion-and-reduces-opex-to-usd-4-588-per-lce-t-at-flagship-boardwalk-lithium-brine-project-alberta-canada; https://www.lithiumbank.ca/projects/park-place | AC44: LithiumBank Resources Corp. is a publicly traded cused on developing its flagship projects, Boardwalk and Park Place, in Western Canada. | AD44: 20 | AE44: The Park Place project encompasses approximately 1,404,558 acres.
A45: 1044 | B45: Commercial | C45: Upstream | D45: Lundin Mining | E45: No | F45: Eagle Mine | G45: Cathode raw materials | H45: Nickel ore | I45: https://www.lundinmining.com/operations/eagle/ | K45: Michigamme Township | L45: MI | M45: US | O45: 906-339-7000 | P45: 46.750162 | Q45: -87.899989 | R45: 200 | S45: 19000 | T45: MT contained Ni/yr | U45: Lundin Mining | V45: https://www.lundinmining.com/ | W45: Toronto | X45: ON | Y45: Canada | Z45: VP | AA45: 44422 | AB45: BNEF: Interactive Datasets / Metals/ Mine Assets Map/ Nickel; lundinmining.com; https://www.lundinmining.com/site/assets/files/3640/2017-04-26-eagle-ni-43-101.pdf | AC45: Lundin Mining mines and processes copper and nickel ore. The nickel ore is ground down and separated to be used for cathodes. | AD45: 22 | AE45: Ni-Cu mine.
A46: 1045 | B46: Commercial | C46: Upstream | D46: Lundin Mining | E46: No | F46: Humboldt mill | G46: Cathode raw materials | H46: Nickel concentrates | I46: https://www.lundinmining.com/operations/eagle/ | J46: 4547 County Rd 601 | K46: Champion | L46: MI | M46: US | N46: 49814 | O46: 906-339-7000 | P46: 46.484071 | Q46: -87.898236 | R46: 200 | S46: 19000 | T46: MT contained Ni/yr | U46: Lundin Mining | V46: https://www.lundinmining.com/ | W46: Toronto | X46: ON | Y46: Canada | Z46: VP | AA46: 44422 | AB46: BNEF: Interactive Datasets / Metals/ Mine Assets Map/ Nickel; lundinmining.com; https://im-mining.com/2018/03/08/43017/; https://www.lundinmining.com/site/assets/files/3640/2017-04-26-eagle-ni-43-101.pdf | AC46: Lundin Mining mines and processes copper and nickel ore. The nickel ore is ground down and separated to be used for cathodes. | AD46: 22 | AE46: Re-purposed iron ore mill; Processes Cu and Ni ore from Eagle mine
A47: 1046 | B47: Pre-commercial/ startup | C47: Upstream | D47: Manganese X Energy Corp. | E47: No | F47: Battery Hill Project | G47: Cathode raw materials | H47: Manganese concentrates | I47: https://www.manganesexenergycorp.com/ | J47: Jacksonville (nearest town) | K47: Jacksonville | L47: NB | M47: Canada | O47: 514-802-1814 | P47: 46.200426 | Q47: -67.632821 | U47: Manganese X Energy Corp. | V47: https://www.manganesexenergycorp.com/ | W47: Saint-Laurent | X47: QC | Y47: Canada | Z47: VP | AA47: 44422 | AB47: manganesexenergycorp.com; Propulsion Quebec; https://www.manganesexenergycorp.com/wp-content/uploads/2020/09/Battery-Hill.pdf | AC47: Manganese X Energy is a manganese, iron, and carbon mine. Products include manganese sulphate as a cathode precursor and graphite for anodes. | AD47: 22 | AE47: Pilot plant and Preliminary Economic Assessment (PEA) in 2021; Demo plant and Feasibility Study in 2022; GPS is approximate center of claim and from Battery-Hill.pdf
A48: 1047 | B48: Pre-commercial/ startup | C48: Upstream | D48: Manganese X Energy Corp. | E48: No | F48: Lac Aux Bouleaux Graphite Property | G48: Anode raw materials | H48: Natural graphite | I48: https://www.manganesexenergycorp.com/ | J48: Mont-Laurier (nearest town) | K48: Mont-Laurier | L48: QC | M48: Canada | O48: 514-802-1814 | P48: 46.549238 | Q48: -75.504014 | U48: Manganese X Energy Corp. | V48: https://www.manganesexenergycorp.com/ | W48: Saint-Laurent | X48: QC | Y48: Canada | Z48: VP | AA48: 44422 | AB48: manganesexenergycorp.com; Propulsion Quebec | AC48: Manganese X Energy is a manganese, iron, and carbon mine. Products produced include manganese sulphate as a cathode precursor and graphite for anodes. | AD48: 23 | AE48: Mont-Laurier used for GPS; Very early project; No economic assessment or projection of development
A49: 1048 | B49: Pre-commercial/ startup | C49: Upstream | D49: Manganese X Energy Corp. | E49: No | F49: Woodstock MXE | G49: Cathode raw materials | H49: Manganese concentrates | I49: https://www.manganesexenergycorp.com/ | J49: Woodstock (nearest town) | K49: Woodstock | L49: NB | M49: Canada | O49: 514-802-1814 | P49: 46.200434 | Q49: -67.632746 | R49: 223 | S49: 2000 | T49: MT/yr electrolytic manganese metal | U49: Manganese X Energy Corp. | V49: https://www.manganesexenergycorp.com/ | W49: Saint-Laurent | X49: QC | Y49: Canada | Z49: VP | AA49: 45290 | AB49: manganesexenergycorp.com; Propulsion Quebec; https://www.manganesexenergycorp.com/wp-content/uploads/2020/09/WOODSTOCK.pdf; https://www.newswire.ca/news-releases/minco-announces-positive-economic-assessment-on-woodstock-manganese-project-514932301.html | AC49: Manganese X Energy is a manganese, iron, and carbon mine. Products include manganese sulphate as a cathode precursor and graphite for anodes. | AD49: 22 | AE49: GPS coordinates from Woodstock MXE technical report and refer to center of claim; Very early project; No economic assessment or projection of development
A50: 1049 | B50: Planned | C50: Upstream | D50: Mason Resources | E50: No | F50: Lac Gueret | G50: Anode raw materials | H50: Natural graphite | I50: https://masonresourcesinc.com/asset/lac-gueret-graphite-project/ | J50: La Gueret | K50: Manicouagan Regional County Municipality | L50: QC | M50: Canada | P50: 51.123248 | Q50: -69.064514 | R50: 100 | S50: 51900 | T50: MT graphite/yr | U50: Mason Resources | V50: https://masonresourcesinc.com/ | W50: Toronto | X50: ON | Y50: Canada | Z50: VP | AA50: 45290 | AB50: https://masonresourcesinc.com/about-us/; https://masonresourcesinc.com/asset/lac-gueret-graphite-project/ | AC50: Mason Resources focuses on identifying, evaluating, and pursuing business investment opportunities. Its strategy is to develop vertical and horizontal integration in the mining industry. | AD50: 24
A51: 1050 | B51: Commercial | C51: Upstream | D51: Minera y Metalúrgica del Boleo | E51: No | F51: El Boleo Mine | G51: Cathode raw materials | H51: Cobalt concentrates | I51: https://www.mmboleo.com/ | J51: Carretera Transpeninsular, 1 Km 5.5 | K51: Santa Rosalía | L51: Baja California Sur | M51: Mexico | N51: 23920 | O51: +52 (615) 155-2200 | P51: 27.3337 | Q51: 112.3309 | R51: 1200 | S51: 800 | T51: MT/yr | U51: Korea Mine Rehabilitation and Mineral Resources | V51: https://www.komir.or.kr/ | W51: Wonju | X51: Gangwon | Y51: South Korea | Z51: MK | AA51: 46064 | AB51: https://biz.chosun.com/; https://mexicobusiness.news/; Avicenne consulting | AC51: Minera y Metalúrgica del Boleo operates an industrial mining complex specializing in high-purity copper cathodes and metallic cobalt using advanced hydrometallurgical leaching and on-site power and desalination infrastructure. | AD51: 28 | AE51: As of early 2026, the majority owner, KOMIR, is actively seeking to divest its nearly 94% stake in the operating company (MMB); In 2025, MMB submitted an EIA to Mexican authorities to expand the mining area from 446 hectares to over 757 hectares. If approved, could significantly extend the mine life beyond the current 2040 projection
A52: 1051 | B52: Commercial | C52: Upstream | D52: Missouri Cobalt LLC | E52: No | F52: Madison mine | G52: Cathode raw materials | H52: Cobalt concentrates | I52: https://www.mocobalt.com/ | J52: 401 N Mine La Motte Ave | K52: Fredericktown | L52: MO | M52: US | N52: 63645 | P52: 37.565097 | Q52: -90.292589 | R52: 50 | S52: 300 | T52: MT/day Co concentrate | U52: US Strategic Metals LLC | V52: https://www.usstrategicmetals.com/ | W52: St. Louis | X52: MO | Y52: US | Z52: VP | AA52: 45094 | AB52: mocobalt.com; Pitchbook; https://dailyjournalonline.com/community/democrat-news/we-are-going-to-see-this-project-to-the-end/article_e4c14013-c103-5816-b2fc-a9f6b78afa0a.html | AC52: Missouri Cobalt mines and process cobalt, nickel, and copper ore. Ores are separated using froth floatation. | AD52: 16 | AE52: Currently cleaning up a superfund site and processing tailings for Co concentrate; 50 employees conduct the cleanup. Currently shutdown until cleanup is complete. Looking to operate a hydrometallurgical facility in Q4 2023 and employ 250 people.
A53: 1052 | B53: Commercial | C53: Upstream | D53: Moa JV | E53: No | F53: Moa Bay mine | G53: Cathode raw materials | H53: Cobalt concentrates | I53: https://www.sherritt.com/English/operations/metals/Moa/default.aspx | J53: Moa (nearest town) | K53: Moa | L53: Holguin | M53: Cuba | P53: 20.657727 | Q53: -74.944693 | S53: 3800 | T53: MT contained Co/yr | U53: Sherrit International and General Nickel Company SA of Cuba | V53: https://www.sherritt.com / | W53: Toronto | X53: ON | Y53: Canada | Z53: VP | AA53: 44422 | AB53: BNEF: Interactive Datasets / Metals/ Mine Assets Map/ Cobalt; https://miningdataonline.com/property/999/Moa-Mine.aspx | AC53: Moa Joint Venture (Sherritt International and General NIckel Company SA of Cuba) mines nickel and cobalt in Cuba. This raw ore is transported and purified using acid leaching. | AD53: 28 | AE53: Product is mixed Co-Ni sulfides; Open-pit mine followed by HPAL
A54: 1053 | B54: Commercial | C54: Upstream | D54: Moa JV | E54: No | F54: Moa Bay mine | G54: Cathode raw materials | H54: Nickel concentrates | I54: https://www.sherritt.com/English/operations/metals/Moa/default.aspx | J54: Moa (nearest town) | K54: Moa | L54: Holguin | M54: Cuba | P54: 20.657727 | Q54: -74.944693 | S54: 35000 | T54: MT contained Ni/yr | U54: Sherrit International and General Nickel Company SA of Cuba | V54: https://www.sherritt.com / | W54: Toronto | X54: ON | Y54: Canada | Z54: VP | AA54: 44422 | AB54: BNEF: Interactive Datasets / Metals/ Mine Assets Map/ Nickel; https://miningdataonline.com/property/999/Moa-Mine.aspx | AC54: Moa Joint Venture mines nickel and cobalt. This raw ore is transported and purified using acid leaching. | AD54: 17 | AE54: Product is mixed Co-Ni sulfides; Open-pit mine followed by HPAL
A55: 1054 | B55: Planned | C55: Upstream | D55: Nemaska Lithium | E55: No | F55: Whabouchi | G55: Cathode raw materials | H55: Spodumene concentrates | I55: https://www.nemaskalithium.com/ | J55: km 276, JOY3B0, Rte du Nord | K55: Baie-James | L55: QC | M55: Canada | O55: 877-704-6038 | P55: 51.689021 | Q55: -75.836362 | R55: 70 | S55: 5160 | T55: MT contained Li/yr | U55: Arcadium Lithium (50%) and Investissement Quebec (50%) | V55: https://arcadiumlithium.com/ | W55: Shannon Montreal | X55: QC | Y55: Ireland, Canada | Z55: VP MK | AB55: https://nemaskalithium.com/en/livent-increases-its-stake-in-nemaska-lithium/#:~:text=Indeed%2C%20Livent%20has%20announced%20the,in%20Nemaska%20%E2%80%8B%E2%80%8BLithium.; https://ir.arcadiumlithium.com/investors/news/news-details/2024/Arcadium-Lithium-Announces-Completion-of-Merger-of-Equals-between-Allkem-and-Livent/default.aspx | AC55: Nemaska Lithium is in the planning phase, intending to mine raw spodumene and convert it to lithium hydroxide, a cathode precursor. | AD55: 21 | AE55: Spodumene and/or concentrates to be processed in a facility in Becancour and converted to battery grade Lithium hydroxide; Rio Tinto invested $300 million in 2026 and now owns majority stake (53.9%); 2026 SOP
A56: 1055 | B56: Planned | C56: Upstream | D56: NeoLith Energy | E56: No | F56: NeoLith Energy | G56: Direct lithium extraction | H56: Lithium | I56: https://www.slb.com/ | K56: Silver Peak | L56: NV | M56: US | N56: 89047 | P56: 37.754617 | Q56: -117.63529 | U56: Schlumberger | V56: https://www.slb.com/ | W56: Houston | X56: TX | Y56: US | Z56: MK | AA56: 45649 | AB56: https://www.slb.com/news-and-insights/newsroom/press-release/2021/pr-2021-0318-sne-lithium-extraction-plant-nevada; https://insideclimatenews.org/news/08042024/nevada-great-basin-lithium-fight-over-water/ | AC56: NeoLith Energy, a division of Schlumberger, focuses on developing sustainable lithium extraction technologies to meet growing demand for battery materials. | AD56: 20 | AE56: NeoLith Energy is a lithium extraction company under Schlumberger, partnered with Pure Energy Minerals, using sustainable Direct Lithium Extraction (DLE) technology.
A57: 1056 | B57: Planned | C57: Upstream | D57: Net Zero Metals | E57: No | F57: Crawford Ni-Co Project | G57: Cathode raw materials | H57: Nickel concentrates | I57: https://www.canadanickel.com/ | K57: Timmins (near) | L57: ON | M57: Canada | P57: 48.479586 | Q57: -81.334262 | S57: 34000 | T57: MT contained Ni/yr | U57: Canada Nickel | V57: https://www.canadanickel.com/ | W57: Toronto | X57: ON | Y57: Canada | Z57: VP | AA57: 45095 | AB57: JayDB; canadanickel.com/wp-content/uploads/2023/06/CNC-Investor-Deck-June-2023.pdf; iaac-aeic.gc.ca/050/evaluations/proj/83857 | AC57: NetZero Metals is a subcompany of Canadian Nickel. Upon opening, it plans to mine and process cobalt and nickel. | AD57: 19 | AE57: $1.2B investment; primarily for stainless, but may move to EVs later; Conduct feasibility study in September 2023
A58: 1057 | B58: Planned | C58: Upstream | D58: Net Zero Metals | E58: No | F58: Crawford Ni-Co Project | G58: Cathode raw materials | H58: Cobalt concentrates | I58: https://www.canadanickel.com/ | K58: Timmins (near) | L58: ON | M58: Canada | P58: 48.479586 | Q58: -81.334262 | U58: Canada Nickel | V58: https://www.canadanickel.com/ | W58: Toronto | X58: ON | Y58: Canada | Z58: VP | AA58: 45095 | AB58: JayDB; canadanickel.com/wp-content/uploads/2023/06/CNC-Investor-Deck-June-2023.pdf; iaac-aeic.gc.ca/050/evaluations/proj/83857 | AC58: NetZero Metals is a subcompany of Canadian Nickel. Upon opening, it plans to mine and process cobalt and nickel. | AD58: 19 | AE58: $1.2B investment; primarily for stainless, but may move to EVs later; Conduct feasibility study in September 2023
A59: 1058 | B59: Under construction | C59: Upstream | D59: NewRange Copper Nickel JV | E59: No | F59: NewRange Copper Nickel Project | G59: Cathode raw materials | H59: Nickel concentrates | I59: https://www.newrangecoppernickel.com/ | J59: 6500 Co Rd 666 | K59: Hoyt Lakes | L59: MN | M59: US | N59: 55750 | O59: 218-471-2150 | P59: 47.587207 | Q59: -92.149961 | R59: 34 | U59: PolyMet Mining Inc. Teck Resources Ltd. | V59: https://www.polymetmining.com teck.com/ | W59: St. Paul Vancouver | X59: MN BC | Y59: US, Canada | Z59: VP | AA59: 45095 | AB59: newrangecoppernickel.com | AC59: New Range Copper Nickel is a mining company that is under construction. The battery resources provided will be nickel and cobalt. | AD59: 21
A60: 1059 | B60: Pre-commercial/ startup | C60: Upstream | D60: NION Nickel Inc | E60: No | F60: Dumont Project | G60: Cathode raw materials | H60: Lithium carbonate - crude | I60: https://www.nionnickel.com/ | J60: 42, rue Trudel | K60: Amos | L60: QC | M60: Canada | N60: J9T 4N1 | O60: 819-727-3777 | P60: 47.225568 | Q60: -77.786007 | R60: 22 | S60: 39304.611 | T60: MT contained Ni/yr | U60: Nion Nickel Inc. | V60: https://www.nionnickel.com/ | W60: Amos | X60: QC | Y60: Canada | Z60: VP | AA60: 45095 | AB60: Jay DB; nionnickel.com; dumontnickel.com; https://dumontnickel.com/wp-content/uploads/2021/02/Dumont-Ni-Project-43-101-dec-2019.pdf | AC60: Nion Nickel is a mining start up focused on mining nickel, with plans to process the ore into nickel sulphide. | AD60: 20 | AE60: Waterton Global is an investment advisor of the equity funds that own Nion. Nion owns the Dumont Project; It has a very large Ni deposit, but it does not appear that anyone is investing in the project for production. It would take about 2-3 years to get online - everything is permitted; will also produce Co. The plant was developed for stainless steel. Phase 2 of project would double production'
A61: 1060 | B61: Pre-commercial/ startup | C61: Upstream | D61: Noram Lithium Corp | E61: No | F61: Zeus Lithium Project | G61: Cathode raw materials | H61: Lithium carbonate - crude | I61: https://www.noramlithiumcorp.com/ | K61: Clayton Valley | L61: NV | M61: US | N61: 89047 | P61: 37.7435 | Q61: -117.5909 | R61: 300 | U61: Noram Lithium Corp | V61: https://www.noramlithiumcorp.com/ | W61: Vancouver | X61: BC | Y61: Canada | Z61: SD | AA61: 45412 | AB61: Jay DB; https://noramlithiumcorp.com/site/assets/files/4011/noram_corporate_update_june_2023.pdf | AC61: Noram Lithium Corp. is a startup lithium mine. It refines the ore into lithium carbonate for use as a cathode precursor. | AD61: 21 | AE61: Conducting pre-feasibility study in June 2023
A62: 1061 | B62: Planned | C62: Upstream | D62: North Arrow Mineral Inc | E62: No | F62: Bathust Inlet | G62: Mining & metals | H62: TBD | I62: https://www.northarrowminerals.com/ | K62: Bathurst Inlet | L62: NV | M62: Canada | N62: X0B 2A0 | P62: 66.835948 | Q62: -108.03087 | R62: 5 | U62: North Arrow Mineral Inc | V62: https://www.northarrowminerals.com/ | W62: Vancouver | X62: BC | Y62: Canada | Z62: MK | AA62: 45551 | AB62: https://www.northarrowminerals.com/projects/lithium/bathurst-inlet/ | AC62: North Arrow Minerals explores diamond opportunities in Canada, with a project near Bathurst Inlet featuring pegmatites and access to nearby mining infrastructure. | AD62: 22 | AE62: North Arrow Minerals owns seven claim blocks (5,728 ha) near Bathurst Inlet.
A63: 1062 | B63: Commercial | C63: Upstream | D63: Northern Graphite | E63: No | F63: Lac des Îles Graphite Mine | G63: Mining & metals | H63: Graphite concentrates | I63: https://www.northerngraphite.com/ldi/ | J63: 585 Chem. du Graphite O. | K63: Lac-des-Îles | L63: QC | M63: Canada | N63: J0W 1J0 | O63: 819-597-2400 | P63: 46.4674 | Q63: 75.309 | R63: 65 | S63: 15000 | T63: MT contained graphite/yr | U63: Northern Graphite Corporation | V63: https://www.northerngraphite.com/ | W63: Ottawa | X63: ON | Y63: Canada | Z63: MK | AA63: 46091 | AB63: https://www.northerngraphite.com/northern-graphite-provides-update-on-ldi-mine-development-plans/; https://secure.northernminer.com/news/projects-outside-china-face-long-road/1003888332/ | AC63: Northern Graphite is the only significant flake graphite producer in North America. The company is transitioning into a vertically integrated mine-to-market supplier. | AD63: 22
A64: 1063 | B64: Under construction | C64: Upstream | D64: Northern Graphite Corp. | E64: No | F64: Bissett Creek | G64: Anode raw materials | H64: Graphite concentrates | I64: https://www.northerngraphite.com/ | L64: ON | M64: Canada | N64: K0J 1E0 | P64: 46.22554 | Q64: -78.060393 | S64: 40000 | T64: MT/yr graphite concentrates | U64: Northern Graphite Corp | V64: https://www.northerngraphite.com/ | W64: Ottawa | X64: ON | Y64: Canada | Z64: VP | AA64: 45092 | AB64: northerngraphite.com; https://www.northerngraphite.com/_resources/presentations/corporate-presentation.pdf | AC64: Northern Graphite is a graphite mine and processing plant. It also has plans to incorporate a nickel/cobalt and mine in the future. | AD64: 22 | AE64: Will start at 40,000 MT/yr graphite concentrates, increasing to 80-100k in future
A65: 1064 | B65: Commercial | C65: Upstream | D65: Northern Graphite Corp. | E65: No | F65: Lac des Iles | G65: Anode raw materials | H65: Graphite concentrates | I65: https://www.northerngraphite.com/ | J65: 585 Chem. Du Graphite O | K65: Lac-des-Îles | L65: QC | M65: Canada | N65: J0W 1J0 | O65: 819-597-2911 | P65: 46.372128 | Q65: -75.52895 | S65: 15000 | T65: MT/yr graphite concentrates | U65: Northern Graphite Corp | V65: https://www.northerngraphite.com/ | W65: Ottawa | X65: ON | Y65: Canada | Z65: VP | AA65: 45092 | AB65: northerngraphite.com; https://www.northerngraphite.com/_resources/presentations/corporate-presentation.pdf | AC65: Northern Graphite is a graphite mine and processing plant. It also has plans to incorporate a nickel/cobalt and mine in the future. | AD65: 22 | AE65: Has only 2-3 years of life left; will process ore from other deposits, up to 25,000 MT graphite concentrates/yr with Mousseau West deposit
A66: 1065 | B66: Planned | C66: Upstream | D66: Northern Graphite Corp. | E66: No | F66: South Okak Ni/Cu/Co Project | G66: Cathode raw materials | H66: Cobalt ore Nickel ore | I66: https://www.northerngraphite.com/ | L66: NL | M66: Canada | P66: 56.352809 | Q66: -62.09372 | U66: Northern Graphite Corp | V66: https://www.northerngraphite.com/ | W66: Ottawa | X66: ON | Y66: Canada | Z66: PF | AA66: 45113 | AB66: https://www.northerngraphite.com/project/south-okak-ni-cu-co-project/ | AC66: Northern Graphite is a graphite mine and processing plant. It also has plans to incorporate a nickel/cobalt and mine in the future. | AD66: 22 | AE66: Entered an option agreement with Vale, begins with Northern earning money on the land for now, but may move to purchase the land. Might be worth emailing about those coordinates.
A67: 1066 | B67: Pre-commercial/ startup | C67: Upstream | D67: Nouveau Monde Graphite | E67: No | F67: Matawinie Graphite Mine | G67: Anode raw materials | H67: Graphite concentrates | I67: https://nmg.com/operations/#matawinie-graphite-property | J67: 481 Brassard Street | K67: Saint-Michel-des-Saints | L67: QC | M67: Canada | N67: J0K 3B0 | O67: 450-757-8905 | P67: 46.6775 | Q67: -73.9142 | R67: 50 | S67: 106000 | T67: MT contained graphite/yr | U67: Nouveau Monde Graphite | V67: https://www.nmg.com/ | W67: Saint-Michel-des-Saints | X67: QC | Y67: Canada | Z67: VP MK | AB67: nouveaumonde.group; Propulsion Quebec; Questionnaire; https://nmg.com/wp-content/uploads/2021/01/BFS.pdf; questionnaire | AC67: Nouveau Monde Graphite is a graphite mining and processing company. The flake graphite produced can be used in battery anodes. | AD67: 20 | AE67: Graphite purity - 97%; Construction started in 2021; Expected Spring 2023 commissioning; GPS is center of Tony Block and is from Tech. Feasibility Report | AF67: Frederic Collin | AG67: fcollin@nmg.com | AH67: 438-351-2126
A68: 1067 | B68: Planned | C68: Upstream | D68: Patriot Battery Metals | E68: No | F68: Corvette Property | G68: Cathode raw materials | H68: Spodumene concentrates | I68: https://patriotbatterymetals.com/ | J68: Eeyou Istchee Baie-James | K68: Jamesie | L68: QC | M68: Canada | O68: 604-279-8709 | P68: 53.5205 | Q68: -73.9393 | R68: 30 | U68: Patriot Battery Metals | V68: https://patriotbatterymetals.com | W68: Vancouver | X68: BC | Y68: Canada | Z68: VP | AA68: 45305 | AC68: Patriot Battery Metals Inc. is a hard-rock lithium exploration company. It is currently developing its Corvette Property in Quebec to produce spodumene. | AD68: 22
A69: 1068 | B69: Planned | C69: Upstream | D69: Piedmont Lithium | E69: No | F69: Piedmont Carolina Lithium Mine | G69: Cathode raw materials | H69: Spodumene concentrates | I69: https://www.piedmontlithium.com/ | J69: 5706 Dallas Cherryville Hwy 279 | K69: Cherryville | L69: NC | M69: US | N69: 28016 | O69: 704-461-8000 | P69: 35.3604 | Q69: -81.2965 | R69: 20 | S69: 240000 | T69: MT contained Li/yr | U69: Piedmont Lithium | V69: https://www.piedmontlithium.com/ | W69: Belmont | X69: NC | Y69: US | Z69: MK | AA69: 46064 | AB69: https://www.gastongov.com/1192/Piedmont-Lithium; consulting with Avicenne | AC69: Piedmont Lithium develops lithium projects in the U.S. and globally to supply battery-grade spodumene concentrate for EV and energy storage markets. | AD69: 21 | AE69: SOP 2027; new entry needed to differentiate between mine and refining plant producing lithium hydroxide
A70: 1069 | B70: Commercial | C70: Upstream | D70: Rio Tinto | E70: No | F70: U.S. Borax | G70: Cathode raw materials | H70: Lithium Carbonate | I70: https://www.borax.com/ | J70: 14486 Borax Rd | K70: Boron | L70: CA | M70: US | N70: 93516 | O70: 760-762-7000 | P70: 35.166479 | Q70: -117.6793 | R70: 1000 | S70: 10000 | T70: MT contained Li/yr | U70: Rio Tinto | V70: https://www.riotinto.com/en | W70: London | X70: Greater London | Y70: UK | Z70: MK | AA70: 45649 | AB70: https://www.mining.com/rio-tinto-kicks-off-lithium-production-in-the-us/ | AC70: Rio Tinto is a global mining company developing lithium production from waste rock at its Boron, California, operation. | AD70: 18
A71: 1070 | B71: Planned | C71: Upstream | D71: Sayona Mining Limited | E71: No | F71: Authier Project | G71: Cathode raw materials | H71: Spodumene | I71: https://sayonamining.com.au/authier-project/ | J71: LaMotte (nearest town) | K71: La Motte | L71: QC | M71: Canada | O71: 819-218-3423 | P71: 48.327012 | Q71: -78.135633 | R71: 176 (Planned) | S71: 3181 | T71: MT contained Li/yr | U71: Sayona Mining Ltd. | V71: https://www.sayonamining.com/ | W71: Paddington | X71: NSW | Y71: Australia | Z71: VP | AA71: 44422 | AB71: sayonamining.com; Propulsion Quebec; https://sayonamining.com.au/wp/wp-content/uploads/2019/11/SYA_ASX-Announ_20191111_Revised-Authier-DFS.pdf; https://sayonamining.com.au/authier-project/ | AC71: Sayona Mining primarily serves as a spodumene mining company, but is beginning to incorporate a graphite facility. Though based in Australia, it has several lithium projects in Canada. | AD71: 28 | AE71: Li content based on 114116 MT/yr spodumene at 6% Li2O
A72: 1071 | B72: Planned | C72: Upstream | D72: Sayona Quebec Inc. | E72: No | F72: Tansim Project | G72: Cathode raw materials | H72: Lithium carbonate - crude | I72: https://www.sayonaquebec.com/ | J72: Laforce (nearest town) | K72: Laforce | L72: QC | M72: Canada | O72: 819-218-3423 | P72: 47.685978 | Q72: -78.648665 | U72: Sayona Mining Ltd. | V72: https://www.sayonamining.com/ | W72: Paddington | X72: NSW | Y72: Australia | Z72: VP | AA72: 44422 | AB72: sayonamining.com; Propulsion Quebec; https://www.sayonaquebec.com/projet-tansim/ | AC72: Sayona works in Quebec to explore, extract, and produce lithium at five sites throughout the Abitibi-Temiscamingue and Eeyou Itschee James Bay regions. | AD72: 22 | AE72: GPS coordinates provided on website; Project is in exploration stage
A73: 1072 | B73: Commercial | C73: Upstream | D73: Sayona Quebec Inc. | E73: No | F73: North American Lithium Mining Complex | G73: Cathode raw materials | H73: Spodumene concentrates | I73: https://www.piedmontlithium.com/ | J73: Unnamed Road | K73: La Corne | L73: QC | M73: Canada | N73: J0Y 1R0 | O73: 819-734-5000 | P73: 48.59156 | Q73: -77.882121 | R73: 100 | S73: 140000 | T73: MT contained Li/yr | U73: Sayona Mining Ltd. | V73: https://www.sayonamining.com/ | W73: Paddington | X73: NSW | Y73: Australia | Z73: VP MK | AB73: https://www.sayona.ca/projet-north-american-lithium/; https://www.businesswire.com/news/home/20220628005277/en/Piedmont-Lithium-and-Sayona-Mining-Formalize-Restart-Plans-for-North-American-Lithium-in-Quebec#:~:text=The%20NAL%20restart%20will%20feature,on%20our%20jointly%20planned%20timeline.; https://piedmontlithium.com/piedmont-lithium-selects-tennessee-for-new-lithium-hydroxide-project/; https://www.sayona.ca/wp-content/uploads/2022/11/Communique-Redemarrage-LAN_Novembre-2022.pdf; https://www.nytimes.com/2022/09/20/business/electric-vehicles-lithium-quebec.html; https://sayonamining.com.au/projects/nal-project/; https://www.catl.com/en/ | AC73: Sayona works in Quebec to explore, extract, and produce lithium at five sites throughout the Abitibi-Temiscamingue and Eeyou Itschee James Bay regions. | AD73: 22 | AE73: SOP 2030; Facility will also process all spodumene from the Authier project. Was previously owned by CATL. Lithium content is based on 114,000 MT/yr of 6% Li2O; Plant is existing but not operational; 75% Sayona / 25% Piedmont
A74: 1073 | B74: Planned | C74: Upstream | D74: Sayona Quebec Inc. | E74: No | F74: Moblan Lithium Project | G74: Cathode raw materials | H74: Spodumene | I74: https://sayonamining.com.au/projects/moblan-project/# | J74: Nearest road is Rte du Nord | K74: Eeyou Istchee Baie-James | L74: QC | M74: Canada | O74: 819-734-5000 | P74: 50.424277 | Q74: -74.717904 | U74: Sayona Mining Ltd. | V74: https://www.sayonamining.com/ | W74: Paddington | X74: NSW | Y74: Australia | Z74: PF | AA74: 45114 | AB74: https://sayonamining.com.au/projects/moblan-project/# | AC74: Sayona works in Quebec to explore, extract, and produce lithium at five sites throughout the Abitibi-Temiscamingue and Eeyou Itschee James Bay regions. | AD74: 22 | AE74: Acquired Oct. 2021. A Mineral Resource Foreign Estimate of 12.03Mt @ 1.4% Li2O* has been identified at Moblan. Pre-feasibility study underway, set to finish September 2023.
A75: 1074 | B75: Planned | C75: Upstream | D75: Sayona Quebec Inc. | E75: No | F75: Lac Albert Lithium Project | G75: Cathode raw materials | H75: Spodumene | I75: https://sayonamining.com.au/projects/lac-albert-project/ | J75: Nearest road is Rte du Nord | K75: Eeyou Istchee Baie-James | L75: QC | M75: Canada | O75: 819-734-5000 | P75: 50.424277 | Q75: -74.717904 | U75: Sayona Mining Ltd. | V75: https://www.sayonamining.com/ | W75: Paddington | X75: NSW | Y75: Australia | Z75: PF | AA75: 45114 | AB75: https://sayonamining.com.au/projects/lac-albert-project/ | AC75: Sayona works in Quebec to explore, extract, and produce lithium at five sites throughout the Abitibi-Temiscamingue and Eeyou Itschee James Bay regions. | AD75: 22 | AE75: Very close to Moblan project (3.5 km West), but under different contract. Acquired Jan 2022.
A76: 1075 | B76: Pre-commercial/ startup | C76: Upstream | D76: Snow Lake Resources Ltd. | E76: No | F76: Thompson Brothers Lithium Project. | G76: Cathode raw materials | H76: Lithium | I76: https://www.snowlakelithium.com/ | J76: 201 Portage Avenue Suite 2200 Winnipeg | K76: Manitoba | L76: MB | M76: Canada | N76: R3B 3L3 | O76: 519-909-8745 | P76: 53.76 | Q76: -99 | R76: 10 | S76: 9600 | T76: MT contained Li/yr | U76: Snow Lake Resources Ltd. | V76: https://www.snowlakelithium.com/ | W76: Winnipeg | X76: MB | Y76: Canada | Z76: KK | AA76: 44774 | AB76: https://www.sec.gov/Archives/edgar/data/1769697/000121390021017941/ea138244-f1_snowlake.htm | AC76: Snow Lake Lithium mines raw spodumene with a focus on providing lithium for electric cars. | AD76: 15 | AE76: Snow Lake Resources Ltd is an exploration stage mining company engaged in lithium exploration in the province of Manitoba, Canada. Its primary focus is currently conducting exploration for lithium at Thompson Brothers Lithium Project. 160,000 MT/yr of 6% Li
A77: 1076 | B77: Pre-commercial/ startup | C77: Upstream | D77: Snow Lake Resources Ltd. | E77: No | F77: Grass River Project | G77: Cathode raw materials | H77: Spodumene | I77: https://snowlakelithium.com/projects/grass-river-project/ | J77: Snow Lake | K77: Manitoba | L77: MB | M77: Canada | O77: 519-909-8746 | P77: 53.76 | Q77: -99 | R77: 10 | U77: Snow Lake Resources Ltd. | V77: https://www.snowlakelithium.com/ | W77: Winnipeg | X77: MB | Y77: Canada | Z77: PF | AA77: 45114 | AB77: https://snowlakelithium.com/projects/grass-river-project/ | AC77: Snow Lake Lithium mines raw spodumene with a focus on providing lithium for electric cars. | AD77: 15 | AE77: Metallurgical test work from the grass river project demonstrates 83.5% lithium recovery producing a 6.39% li20 spodumene concentrate. Couldn't find exact coordinates for the facility, the coords are for Snow Lake.
A78: 1077 | B78: Pre-commercial/ startup | C78: Upstream | D78: Snow Lake Resources Ltd. | E78: No | F78: Snow Lake Lithium Project | G78: Cathode raw materials | H78: Spodumene | I78: https://snowlakelithium.com/projects/snow-lake-lithium-project/ | J78: Snow Lake | K78: Manitoba | L78: MB | M78: Canada | O78: 519-909-8747 | P78: 54.87201 | Q78: -90.149549 | R78: 10 | U78: Snow Lake Resources Ltd. | V78: https://www.snowlakelithium.com/ | W78: Winnipeg | X78: MB | Y78: Canada | Z78: PF | AA78: 45114 | AB78: https://snowlakelithium.com/projects/snow-lake-lithium-project/ | AC78: Snow Lake Lithium mines raw spodumene with a focus on providing lithium for electric cars. | AD78: 15 | AE78: Snow Lake sees the potential for an underground mining operation accessed via ramp at Thompson Brothers and potential open pit opportunities at Sheritt Gordon. Coords are for Lalor Mine, a nearby mine not operated by Snow Lake Lithium.
A79: 1078 | B79: Commercial | C79: Upstream | D79: South Star Battery Metals Corp | E79: Yes | F79: BamaStar Project (USA) | G79: Anode raw materials | H79: Flake crystalline graphite concentrate | I79: https://www.southstarbatterymetals.com | K79: Coosa County | L79: AL | M79: US | N79: 35151 | P79: 32.957258 | Q79: -86.173889 | R79: 50 | U79: South Star Battery Metals Corp | V79: https://www.southstarbatterymetals.com/ | W79: Vancouver | X79: British Columbia | Y79: Canada | Z79: SD; AP | AA79: 45475 | AB79: https://www.southstarbatterymetals.com/ceylon-graphite-project/ | AC79: South Star focuses on acquiring and developing near-term production projects, delivering value in the industrial and battery metals sector through strong financial and operational metrics. | AD79: 25 | AE79: The Project is located on the northeast end of the Alabama Graphite Belt and covers approximately 500 acres in Coosa County Alabama. The Project is a historic mine active during World Wars I & II. The Ceylon Graphite mine historically targeted friable outcropping graphite mineralization, averaging approximately 3-5% graphitic carbon. Mineralization is at surface, and the graphitic host rock was mined historically with shovels and excavators with no drilling and blasting required.
A80: 1079 | B80: Commercial | C80: Upstream | D80: South32 | E80: Yes | F80: South32 | G80: Mining & metals | H80: Zinc and manganese | I80: https://www.south32.net/what-we-do/our-locations/americas/hermosa/about-hermosa | J80: 1860 E River Road, Suite 200 | K80: Tucson | L80: AZ | M80: US | N80: 85718 | O80: 61 8 9324 9000 | P80: 32.28636 | Q80: -110.94451 | R80: 100 | U80: South32 | V80: https://www.south32.net/ | W80: Perth | Y80: Australia | Z80: BM AP | AA80: 45545 | AB80: https://www.south32.net/ | AC80: South32 is a global mining company producing essential commodities while diversifying by commodity and location. It strives to minimize impact and create lasting value for all stakeholders. | AD80: 27 | AI80: We are a global mining and metals company, creating value by producing commodities that are used in many aspects of modern life. Our operations, development options and exploration programs are diversified by commodity and geography. We work to minimize the impact of our activities and aim to create enduring value for all of our stakeholders, at each stage of the mining lifecycle.
A81: 1080 | B81: Planned | C81: Upstream | D81: Standard Lithium | E81: No | F81: SWA Lithium LLC | G81: Direct lithium extraction | H81: Lithium carbonate; Battery grade | I81: https://www.standardlithium.com/ | K81: Smackover | L81: AR | M81: US | P81: 33.3602 | Q81: -93.5774 | R81: 90 (Planned) | U81: Standard Lithium | V81: https://www.standardlithium.com/ | Z81: BM AP MK | AB81: https://stocktwits.com/news-articles/markets/equity/standard-lithium-gets-major-us-government-backing-in-race-with-exxon-to-mine-lithium-in-arkansas/cLPQgHKRE4K | AC81: SWA Lithium aims to be one of the first commercial-scale, direct lithium extraction companies in the Smackover Formation, producing up to 45,000 tonne per year of battery-quality lithium carbonate. | AD81: 29 | AE81: 2028 SOP; awarded $225 million grant from DOE
A82: 1081 | B82: Pre-commercial/ startup | C82: Upstream | D82: Summit Nanotech | E82: No | F82: Summit Nanotech Colorado | G82: Cathode raw materials | H82: Lithium extraction services | I82: https://www.summitnanotech.com/ | J82: 1355 Horizon Blvd | K82: Lafayette | L82: CO | M82: US | N82: 80026 | O82: 860-595-7221 | P82: 39.980104 | Q82: -105.06823 | R82: 100 | U82: Summit Nanotech | V82: https://www.summitnanotech.com/ | W82: Calgary | X82: AB | Y82: US | Z82: MK | AA82: 45584 | AB82: Questionnaire | AC82: Summit Nanotech is a cleantech firm specializing in direct lithium extraction technology to enhance lithium access and support the global energy transition sustainably. | AD82: 23 | AF82: Zachary Marcoux | AG82: zachary.marcoux@summitnanotech.com | AH82: 860-595-7221 | AI82: Summit Nanotech Corporation is a cleantech organization transforming how the world accesses lithium for the global energy transition. Through their proprietary and sustainable direct lithium extraction (DLE) technology, Summit Nanotech is conserving natural resources and optimizing operations for lithium producers.
A83: 1082 | B83: Pre-commercial/ startup | C83: Upstream | D83: Surge Battery Metals | E83: No | F83: Nevada North Lithium Project | G83: Cathode raw materials | H83: Lithium Carbonate | I83: https://surgebatterymetals.com/ | K83: Elko | L83: NV | M83: US | N83: 89801 | O83: 604-662-8184 | P83: 40.832562 | Q83: -115.76183 | R83: 15 | U83: Surge Battery Metals | V83: https://surgebatterymetals.com/ | W83: West Vancouver | X83: BC | Y83: Canada | Z83: MK | AA83: 45689 | AB83: Questionnaire | AC83: Surge Battery Metals focuses on exploring clean, high-grade lithium energy metals in Nevada, United States. | AD83: 15 | AF83: Michael Harris | AG83: michael@surgebatterymetals.com | AH83: 778-951-4869
A84: 1083 | B84: Planned | C84: Upstream | D84: Talon Metals | E84: No | F84: Mercer County Processing Facility | G84: Cathode raw materials | H84: Nickel concentrates | I84: https://www.talonmetals.com/ | K84: Mercer County | L84: ND | M84: US | P84: 47.393915 | Q84: -101.78775 | R84: 45 | S84: 75000 | T84: MT contained Nil/yr | U84: Talon Metals Tesla | V84: https://www.talonmetals.com/ | W84: Road Town | X84: Tortola | Y84: British VI | Z84: VP | AA84: 44899 | AB84: talonmetals.com; https://talonmetals.com/wp-content/uploads/2021/07/TLO_Presentation_July-2021-1.pdf; https://talonmetals.com/talon-metals-announces-improved-economics-under-its-updated-pea-and-a-106-increase-in-overall-tonnage-included-in-the-mine-plan-along-with-an-increased-mine-life/; https://www.energy.gov/sites/default/files/2022-11/DOE%20BIL%20Battery%20FOA-2678%20Selectee%20Fact%20Sheets.pdf | AC84: Talon Metals Corp is a proposed nickel mine that will focus primarily on finding nickel, but is set to account for cobalt and iron found in the process. | AD84: 28 | AE84: Recipient of $114.8M under DE-FOA-2678 and has supply agreement for 75,000 MT/yr in Ni in concentrate in Mercer County ND; Center of county was used for address; 12-Month Extension Provided for Key Environmental Review Milestone Expected in H1 2026
A85: 1084 | B85: Planned | C85: Upstream | D85: TerraVolta Resources | E85: No | F85: TerraVolta Resources | G85: Direct lithium extraction | H85: Lithium carbonate; Battery grade | I85: https://www.terravolta.com/ | K85: Texarkana | L85: TX | M85: US | P85: 33.4251 | Q85: -94.0477 | R85: 8 | V85: https://www.terravolta.com/ | Z85: BM AP | AA85: 45560 | AC85: TerraVolta Resources plans to design, build, and operate a commercial-scale lithium extraction and refining facility to produce battery-grade lithium from domestic brine resources. | AD85: 23
A86: 1085 | B86: Planned | C86: Upstream | D86: The Metals Company | E86: Yes | F86: NORI-D | G86: Cathode raw materials | H86: Cobalt ore | I86: https://www.metals.co/ | J86: Clarion-Clipperton Zone - NORI-D | K86: N/A | L86: N/A | M86: N/A | N86: N/A | P86: 10.48 | Q86: -116.95 | R86: 160 (Planned) | S86: 10025 | T86: MT contained Co/yr | U86: The Metals Company | V86: https://www.metals.co/ | W86: Vancouver | X86: BC | Y86: Canada | Z86: VP | AA86: 44780 | AB86: Questionnaire; metals.co | AC86: The Metals Company plans to comb the sea floor for small rocks rich in metals, including lithium, cobalt, nickel, manganese, and copper. There are also plans for a recycling facility. | AD86: 30 | AE86: Facility is expected to be online in 2024 through 2046; values are averages calculated based on questionnaire; Workforce should be 120-200 in 2024 rising to 500-800 in 2030 - 500 was selected as representative for the facility
A87: 1086 | B87: Planned | C87: Upstream | D87: The Metals Company | E87: Yes | F87: NORI-D | G87: Cathode raw materials | H87: Nickel ore | I87: https://www.metals.co/ | J87: Clarion-Clipperton Zone - NORI-D | K87: N/A | L87: N/A | M87: N/A | N87: N/A | P87: 10.48 | Q87: -116.95 | R87: 160 (Planned) | S87: 99500 | T87: MT contained Ni/yr | U87: The Metals Company | V87: https://www.metals.co/ | W87: Vancouver | X87: BC | Y87: Canada | Z87: VP | AA87: 44780 | AB87: Questionnaire; metals.co | AC87: The Metals Company plans to comb the sea floor for small rocks rich in metals, including lithium, cobalt, nickel, manganese, and copper. There are also plans for a recycling facility. | AD87: 30 | AE87: Facility is expected to be online in 2024 through 2046; values are averages calculated based on questionnaire; Workforce should be 120-200 in 2024 rising to 500-800 in 2030 - 500 was selected as representative for the facility
A88: 1087 | B88: Planned | C88: Upstream | D88: The Metals Company | E88: Yes | F88: NORI-D | G88: Cathode raw materials | H88: Manganese ore | I88: https://www.metals.co/ | J88: Clarion-Clipperton Zone - NORI-D | K88: N/A | L88: N/A | M88: N/A | N88: N/A | P88: 10.48 | Q88: -116.95 | R88: 180 (Planned) | S88: 2222000 | T88: MT contained Mn/yr | U88: The Metals Company | V88: https://www.metals.co/ | W88: Vancouver | X88: BC | Y88: Canada | Z88: VP | AA88: 44780 | AB88: Questionnaire; metals.co | AC88: The Metals Company plans to comb the sea floor for small rocks rich in metals, including lithium, cobalt, nickel, manganese, and copper. There are also plans for a recycling facility. | AD88: 30 | AE88: Facility is expected to be online in 2024 through 2046; values are averages calculated based on questionnaire; Workforce should be 120-200 in 2024 rising to 500-800 in 2030 - 500 was selected as representative for the facility
A89: 1088 | B89: Planned | C89: Upstream | D89: The Metals Company | E89: Yes | F89: TOML-F | G89: Cathode raw materials | H89: Cobalt ore | I89: https://www.metals.co/ | J89: Clarion-Clipperton Zone - TOML-F | K89: N/A | L89: N/A | M89: N/A | N89: N/A | P89: 10.489 | Q89: -118.367 | R89: 153 (Planned) | S89: 6800 | T89: MT contained Co/yr | U89: The Metals Company | V89: https://www.metals.co/ | W89: Vancouver | X89: BC | Y89: Canada | Z89: VP | AA89: 44780 | AB89: Questionnaire; metals.co | AC89: The Metals Company plans to comb the sea floor for small rocks rich in metals, including lithium, cobalt, nickel, manganese, and copper. There are also plans for a recycling facility. | AD89: 30 | AE89: Facility is expected to be online in 2026 and has ~72% of the resource as NORI
A90: 1089 | B90: Planned | C90: Upstream | D90: The Metals Company | E90: Yes | F90: TOML-F | G90: Cathode raw materials | H90: Nickel ore | I90: https://www.metals.co/ | J90: Clarion-Clipperton Zone - TOML-F | K90: N/A | L90: N/A | M90: N/A | N90: N/A | P90: 10.489 | Q90: -118.367 | R90: 152 (Planned) | S90: 67900 | T90: MT contained Ni/yr | U90: The Metals Company | V90: https://www.metals.co/ | W90: Vancouver | X90: BC | Y90: Canada | Z90: VP | AA90: 44780 | AB90: Questionnaire; metals.co | AC90: The Metals Company plans to comb the sea floor for small rocks rich in metals, including lithium, cobalt, nickel, manganese, and copper. There are also plans for a recycling facility. | AD90: 30 | AE90: Facility is expected to be online in 2026 and has ~72% of the resource as NORI
A91: 1090 | B91: Planned | C91: Upstream | D91: The Metals Company | E91: Yes | F91: TOML-F | G91: Cathode raw materials | H91: Manganese ore | I91: https://www.metals.co/ | J91: Clarion-Clipperton Zone - TOML-F | K91: N/A | L91: N/A | M91: N/A | N91: N/A | P91: 10.489 | Q91: -118.367 | R91: 152 (Planned) | S91: 1515600 | T91: MT contained Mn/yr | U91: The Metals Company | V91: https://www.metals.co/ | W91: Vancouver | X91: BC | Y91: Canada | Z91: VP | AA91: 44780 | AB91: Questionnaire; metals.co | AC91: The Metals Company plans to comb the sea floor for small rocks rich in metals, including lithium, cobalt, nickel, manganese, and copper. There are also plans for a recycling facility. | AD91: 30 | AE91: Facility is expected to be online in 2026 and has ~72% of the resource as NORI
A92: 1091 | B92: Commercial | C92: Upstream | D92: Titan Lithium | E92: No | F92: Titan Lithium | G92: Lithium | H92: Lithium | I92: https://titanlithiuminc.com/titan-lithium | J92: 4005 West Reno Ave Suite F | K92: Las Vegas | L92: NV | M92: US | N92: 89118 | O92: 702-595-2247 | P92: 36.097388 | Q92: -115.19283 | R92: 200 | U92: CDSG Lithium (China Dongsheng International Inc.) | V92: https://titanlithiuminc.com/ | Y92: China | Z92: SD | AA92: 45699 | AB92: Ahmad's email on 2.11.25 | AC92: Titan Lithium is a project of China Dongsheng International Lithium, a Nevada-based lithium explorer and developer advancing its lithium project in Nye County, Nevada. | AD92: 24
A93: 1092 | B93: Under Construction | C93: Upstream | D93: Titan Mining Corp. | E93: No | F93: Empire State Mines, Kilbourne Graphite Project | G93: Graphite | H93: Natural graphite | I93: https://www.titanminingcorp.com | J93: 408 Sylvia Lake Road | K93: Gouverneur | L93: NY | M93: US | N93: 13642 | O93: 315-535-3200 | P93: 44.318869 | Q93: -75.352556 | R93: 140 | S93: 1200 | T93: MT contained graphite/yr | U93: Titan Mining Corp | V93: https://www.titanminingcorp.com | W93: Vancouver | X93: BC | Y93: US | Z93: MK | AA93: 45867 | AB93: https://www.titanminingcorp.com/news/news-releases/titan-mining-on-track-to-become-the-only-fully-integrated-us-graphite-producer-by-q4-2025, https://chargedevs.com/newswire/titan-builds-graphite-processing-facility-in-new-york, https://www.mining.com/titan-mining-targets-q4-2025-to-become-only-integrated-us-graphite-producer/ | AC93: Titan Mining produces zinc at its New York mine and is developing a project to become the USA's first fully integrated, end-to-end producer of natural flake graphite. | AD93: 27 | AE93: Production capacity target: 40,000
A94: 1093 | B94: Planned | C94: Upstream | D94: Trilogy Metals | E94: No | F94: Arctic Project Mine | G94: Mining & metals | H94: Nickel, copper, zinc | I94: https://trilogymetals.com/ | J94: NW Arctic Borough | K94: North of Arctic Circle | L94: AK | M94: US | P94: 67.1744 | Q94: -156.3881 | U94: Trilogy Metals | V94: https://trilogymetals.com/ | W94: Vancouver | X94: BC | Y94: Canada | Z94: MK | AA94: 46093 | AB94: https://trilogymetals.com/news-and-media/news/trilogy-metals-announces-dec-17-2025/; https://finance.yahoo.com/news/trilogy-metals-tsx-tmq-19-081412344.html | AC94: Trilogy Metals is a base metals exploration company focused on the Upper Kobuk Mineral Projects (UKMP) in the Ambler Mining District. It is backed by a direct federal investment. | AD94: 29
A95: 1094 | B95: Planned | C95: Upstream | D95: Twin Metals Minnesota | E95: No | F95: Twin Metals | G95: Mining & metals | H95: Nickel concentrates | I95: https://www.twin-metals.com/ | J95: 400 Miners Drive East | K95: Ely | L95: MN | M95: US | N95: 55731 | P95: 47.901717 | Q95: -91.852517 | R95: 750 (Planned) | U95: Antofagasta PLC | V95: https://www.antofagasta.co.uk/ | W95: London Philadelphia Montreal | X95: London | Y95: UK | Z95: VP AP | AA95: 45524 | AB95: Jay DB; twin-metals.com; PitchBook.com; https://www.mining.com/web/us-blocks-mining-in-parts-of-minnesota-dealing-latest-blow-to-antofagastas-copper-project/ | AC95: Twin Metals Minnesota is a mining startup focused on mining nickel and copper. The nickel is useful for cathodes. | AD95: 19 | AE95: U.S. Interior Dept. has blocked mining in this part of MN for 20 years, but it is changing.
A96: 1095 | B96: Commercial | C96: Upstream | D96: Vale Canada Ltd. | E96: No | F96: Sudbury Basin - Copper Cliff Complex | G96: Cathode raw materials | H96: Cobalt concentrates | I96: https://www.vale.com/ | J96: 18 Rink St | K96: Copper Cliff | L96: ON | M96: Canada | N96: P0M 1N0 | O96: 705-682-4211 | P96: 46.477489 | Q96: -81.064097 | R96: 1200 | S96: 1000 | T96: MT contained Co/yr | U96: Vale | V96: https://www.vale.com/ | W96: Rio de Janeiro | X96: Rio de Janeiro | Y96: Brazil | Z96: VP | AA96: 44425 | AB96: BNEF: Interactive Datasets / Metals/ Mine Assets Map/ Cobalt; vale.com; https://republicofmining.com/category/sudbury-basin/ | AC96: Vale is an international mining company. Within North America, it mines nickel and cobalt. It also handles the purification and shipment of many of its products. | AD96: 26
A97: 1096 | B97: Commercial | C97: Upstream | D97: Vale Canada Ltd. | E97: No | F97: Thompson | G97: Cathode raw materials | H97: Cobalt concentrates | I97: https://www.vale.com/canada | J97: 1 Vale Road | K97: Thompson | L97: MB | M97: Canada | N97: R8N 1P3 | O97: 204-778-2211 | P97: 55.712888 | Q97: -97.85071 | R97: 450 | S97: 800 | T97: MT contained Co/yr | U97: Vale | V97: https://www.vale.com/ | W97: Rio de Janeiro | X97: Rio de Janeiro | Y97: Brazil | Z97: VP | AA97: 44425 | AB97: BNEF: Interactive Datasets / Metals/ Mine Assets Map/ Cobalt; vale.com; http://www.vale.com/canada/en/business/mining/nickel/vale-canada/thompson/pages/default.aspx; http://www.vale.com/canada/en/aboutvale/communities/thompson/csr%20documents/manitoba-csr-2020/index.html | AC97: Vale is an international mining company. Within North America, it mines nickel and cobalt. It also handles the purification and shipment of many of its products. | AD97: 26 | AE97: Vale Canada Ltd also produces Cobalt Rounds in Port Colborne (~800tpy) and Long Harbour (~1500tpy). Some of these volumes are already allocated via streaming deals.
A98: 1097 | B98: Commercial | C98: Upstream | D98: Vale Canada Ltd. | E98: No | F98: Voisey Bay | G98: Cathode raw materials | H98: Cobalt concentrates | I98: https://www.vale.com/canada | J98: P.O. Box 7001 Stn C | K98: Happy Valley - Goose Bay | L98: NL | M98: Canada | N98: A0P 1C0 | O98: 709-228-3600 | P98: 56.494382 | Q98: -62.06951 | R98: 450 | S98: 2000 | T98: MT contained Co/yr | U98: Vale | V98: https://www.vale.com/ | W98: Rio de Janeiro | X98: Rio de Janeiro | Y98: Brazil | Z98: VP | AA98: 44425 | AB98: BNEF: Interactive Datasets / Metals/ Mine Assets Map/ Cobalt; vale.com | AC98: Vale is an international mining company. Within North America, it mines nickel and cobalt. It also handles the purification and shipment of many of its products. | AD98: 26 | AE98: 500 people currently, but 400 will be added for the underground mine; need to check when it will be done. Concentrate is a mixed NI-Co and is processed at the Long Harbour hydrometallurgical refinery
A99: 1098 | B99: Commercial | C99: Upstream | D99: Vale Canada Ltd. | E99: No | F99: Sudbury Basin - Copper Cliff Complex | G99: Cathode raw materials | H99: Nickel concentrates | I99: https://www.vale.com/ | J99: 18 Rink St | K99: Copper Cliff | L99: ON | M99: Canada | N99: P0M 1N0 | O99: 705-682-4211 | P99: 46.477489 | Q99: -81.064097 | R99: 1200 | S99: 66000 | T99: MT contained Ni/yr | U99: Vale | V99: https://www.vale.com/ | W99: Rio de Janeiro | X99: Rio de Janeiro | Y99: Brazil | Z99: VP | AA99: 44425 | AB99: BNEF: Interactive Datasets / Metals/ Mine Assets Map/ Nickel; vale.com; https://republicofmining.com/category/sudbury-basin/ | AC99: Vale is an international mining company. Within North America, it mines nickel and cobalt. It also handles the purification and shipment of many of its products. | AD99: 26 | AE99: Concentrates are sent to Copper Cliff refinery
A100: 1099 | B100: Commercial | C100: Upstream | D100: Vale Canada Ltd. | E100: No | F100: Thompson | G100: Cathode raw materials | H100: Nickel concentrates | I100: https://www.vale.com/canada | J100: 1 Vale Road | K100: Thompson | L100: MB | M100: Canada | N100: R8N 1P3 | O100: 204-778-2211 | P100: 55.712888 | Q100: -97.85071 | R100: 450 | S100: 14800 | T100: MT contained Ni/yr | U100: Vale | V100: https://www.vale.com/ | W100: Rio de Janeiro | X100: Rio de Janeiro | Y100: Brazil | Z100: VP | AA100: 44425 | AB100: BNEF: Interactive Datasets / Metals/ Mine Assets Map/Nickel; vale.com; http://www.vale.com/canada/en/business/mining/nickel/vale-canada/thompson/pages/default.aspx; http://www.vale.com/canada/en/aboutvale/communities/thompson/csr%20documents/manitoba-csr-2020/index.html | AC100: Vale is an international mining company. Within North America, it mines nickel and cobalt. It also handles the purification and shipment of many of their products. | AD100: 26 | AE100: Canada Growth Fund announces up to US$85 million investment in critical minerals with key strategic partners for acquisition of Manitoba's Thompson Mine Nickel Complex
...

Sheet Map Instructions for Excel

Sheet Raw Materials
A1: ID | B1: Status | C1: Supply Chain Segment | D1: Company | E1: NAATBatt Member | F1: Facility Name | G1: Product/Facility Type | H1: Product | I1: Company Website | J1: Facility Address | K1: Facility City | L1: Facility State or Province | M1: Facility Country | N1: Facility Zip | O1: Facility Phone | P1: Latitude | Q1: Longitude | R1: Facility Workforce | S1: Production Capacity | T1: Production Units | U1: HQ Company | V1: HQ Company Website | W1: HQ City | X1: HQ State or Province | Y1: HQ Country | Z1: QC | AA1: QC Date | AB1: Sources | AC1: Brief Company Profile | AD1: Summary Word Count | AE1: Notes | AF1: Contact | AG1: Contact email | AH1: Contact Phone | AI1: Long Description
A2: 1001 | B2: Pre-commercial/ startup | C2: Upstream | D2: Aether | E2: Yes | F2: Aether | G2: Cathode raw materials | H2: Lithium | I2: https://www.aetherbio.com/ | J2: 1455 Adams Dr | K2: Menlo Park | L2: CA | M2: US | N2: 94025 | O2: 415-316-3591 | P2: 37.478008 | Q2: -122.14252 | R2: 40 | U2: Aether | V2: https://www.aetherbio.com/ | W2: Aether | X2: CA | Y2: US | Z2: VP | AA2: 45339 | AC2: Aether engineers enzymes to make novel products. It recently developed a cheaper, faster and more sustainable direct lithium extraction technology using robotics, machine learning, and synthetic biology. | AD2: =IF(LEN(TRIM(AC2))=0,0,LEN(TRIM(AC2))-LEN(SUBSTITUTE(AC2," ",""))+1) -> 27
A3: 1002 | B3: Pre-commercial/ startup | C3: Upstream | D3: Alaska Energy Metals Corp | E3: No | F3: Nikolai Project | G3: Mining & metals | H3: Nickel, copper, cobalt, chromium, iron, platinum, palladium, gold | I3: https://alaskaenergymetals.com/ | K3: Delta Junction | L3: AK | M3: US | O3: 907-677-7479 | P3: 63.5236 | Q3: -145.8222 | U3: Alaska Energy Metals Corp | V3: https://alaskaenergymetals.com/ | W3: Vancouver | X3: BC | Y3: US | Z3: MK | AA3: 45872 | AB3: https://www.morningstar.com/news/accesswire/1052272msn/alaska-energy-metals-enters-memorandum-of-understanding-with-american-electric-vehicle-manufacturer-lucid-and-other-mining-and-processing-companies | AC3: Alaska Energy Metals is a mineral exploration company focused on developing its large-scale Nikolai Project in Alaska to become a domestic source of strategic and critical metals for North America. | AD3: =IF(LEN(TRIM(AC3))=0,0,LEN(TRIM(AC3))-LEN(SUBSTITUTE(AC3," ",""))+1) -> 30 | AE3: The company is actively exploring the site to define the resources they will focus on. They also have an office in Anchorage, AK.
A4: 1003 | B4: Commercial | C4: Upstream | D4: Albemarle Corporation | E4: Yes | F4: Albemarle Corporation, Silver Peak NV | G4: Cathode raw materials | H4: Lithium carbonate - crude | I4: https://www.albemarle.com/ | J4: HWY 265 | K4: Silver Peak | L4: NV | M4: US | N4: 89047 | O4: 775-937-2222 | P4: 37.740208 | Q4: -117.79232 | R4: 75 | S4: 5000 | T4: MT contained Li/yr | U4: Albermarle | V4: https://www.albermarle.com/ | W4: Charlotte | X4: NC | Y4: US | Z4: VP MK | AA4: 8/9/2021 3/12/2026 | AB4: Capacity from BNEF: Interactive Datasets / Metals/ Mine Assets Map/ Lithium; albermarle.com; Questionnaire; https://www.leg.state.nv.us/App/InterimCommittee/REL/Document/16038#:~:text=We%20have%2065%20employees%20and,is%20about%20%2494%2C000%20a%20year.&text=We%20thank%20you%20for%20the%20opportunity%20to%20speak%20to%20you%20today.&text=Global%20specialty%20chemicals%20company%20with,lithium%2C%20bromine%20and%20refining%20catalysts; https://www.mining.com/albemarle-to-double-lithium-production-in-nevada/ | AC4: Albemarle is a chemical company that provides lithium carbonate and lithium hydroxide as cathode precursors, lithium bis-(oxalato)borate for liquid electrolytes, and lithium sulfide as a solid electrolyte. | AD4: =IF(LEN(TRIM(AC4))=0,0,LEN(TRIM(AC4))-LEN(SUBSTITUTE(AC4," ",""))+1) -> 27 | AE4: Expects to double production; Expansion possible after completing federal permitting in Feb 2026
A5: 1004 | B5: Commercial | C5: Upstream | D5: Albemarle Corporation | E5: Yes | F5: Albemarle - Kings Mountain, NC | G5: Cathode raw materials | H5: Lithium hydroxide - crude | I5: https://www.albemarle.com/ | J5: 348 Holiday Inn Drive | K5: Kings Mountain | L5: NC | M5: US | N5: 28086 | O5: 704-739-2501 | P5: 35.220466 | Q5: -81.341653 | R5: 170 | S5: 5500 | T5: MT contained Li/yr | U5: Albermarle | V5: https://www.albemarle.com/ | W5: Charlotte | X5: NC | Y5: US | Z5: VP | AA5: 44417 | AB5: albermarle.com; BNEF: US Supply Chain Security; Questionnaire; https://www.shelbystar.com/story/news/2022/03/25/kings-mountain-corporation-restart-lithium-mining/7130284001/ | AC5: Albemarle is a chemical company that provides lithium carbonate and lithium hydroxide as cathode precursors, lithium bis-(oxalato)borate for liquid electrolytes, and lithium sulfide as a solid electrolyte. | AD5: =IF(LEN(TRIM(AC5))=0,0,LEN(TRIM(AC5))-LEN(SUBSTITUTE(AC5," ",""))+1) -> 27 | AE5: Pilot facility that mines spodumene, produces battery grade Li-hydroxide, Li-carbonate, and more
A6: 1005 | B6: Planned | C6: Upstream | D6: American Lithium | E6: No | F6: Tonopah Lithium Claims (TLC) Project | G6: Direct lithium extraction | H6: Lithium Sedimentary | I6: https://americanlithiumcorp.com/tlc-lithium-project/ | K6: Tonopah | L6: NV | M6: US | N6: 89049 | O6: 604-428-6126 | P6: 38.125 | Q6: -117.285 | S6: 38000 | T6: MT contained Li/yr | U6: American Lithium Corp | V6: https://americanlithiumcorp.com/ | W6: Vancouver | X6: BC | Y6: Canada | Z6: MK | AA6: 46064 | AB6: https://americanlithiumcorp.com/wp-content/uploads/2026/01/American-Lithium-Investor-Presentation-2026-01-05.pdf; https://americanlithiumcorp.com/tlc-lithium-project/ | AC6: American Lithium develops large-scale lithium projects in Nevada and Peru, utilizing sustainable mining and extraction methods to supply battery-grade lithium for the EV and energy storage sectors. | AD6: =IF(LEN(TRIM(AC6))=0,0,LEN(TRIM(AC6))-LEN(SUBSTITUTE(AC6," ",""))+1) -> 27 | AE6: SOP 2028
A7: 1006 | B7: Pre-commercial/ startup | C7: Upstream | D7: Anson Resources | E7: No | F7: Paradox Lithium Project | G7: Direct lithium extraction | H7: Lithium Carbonate | I7: https://www.ansonresources.com/ | K7: Moab | L7: UT | M7: US | N7: 84532 | O7: 702 759 0182 | P7: 38.572695 | Q7: -109.54767 | R7: 5 | S7: 13000 | T7: MT contained Li/yr | U7: Anson Resources | V7: https://www.ansonresources.com/ | W7: West Perth | X7: Western Australia | Y7: Australia | Z7: MK | AA7: 45649 | AB7: https://www.ansonresources.com/paradox_lithium_project/; https://www.businessnewsasia.com/2024050152386375-anson-resources-signs-lithium-supply-agreement-with-lg-energy-solution/; https://mining.com.au/anson-resources-completes-dfs-at-paradox-lithium-project-us/ | AC7: Anson Resources is an ASX-listed mineral resources company developing the Paradox Lithium Project in Utah, aiming to become a significant supplier of lithium carbonate for the global EV battery market. | AD7: =IF(LEN(TRIM(AC7))=0,0,LEN(TRIM(AC7))-LEN(SUBSTITUTE(AC7," ",""))+1) -> 30 | AE7: Anson Resources has signed a binding offtake agreement with LG Energy Solution to supply battery-grade lithium carbonate from the Paradox Project.
A8: 1007 | B8: Planned | C8: Upstream | D8: Anson Resources | E8: No | F8: Green River DLE Demonstration Plant | G8: Direct lithium extraction | H8: Lithium Brine | I8: https://www.ansonresources.com/ | J8: Green River Industrial Site | K8: Green River | L8: UT | M8: US | N8: 84525 | P8: 38.9955 | Q8: 110.1597 | R8: 80 | U8: Posco Holdings; Anson Resources | V8: http://www.posco-inc.com/poscoinc/v3/eng/index.jsp; https://www.ansonresources.com/ | W8: Seoul; West Perth | X8: NA; Western Australia | Y8: South Korea; Australia | Z8: MK | AA8: 46064 | AB8: https://investingnews.com/anson-resources-update-on-cooperation-between-anson-and-posco-holdings-for-dle-green-river-demonstration-plant/; https://www.accessnewswire.com/newsroom/en/metals-and-mining/anson-resources-update-on-cooperation-between-anson-and-posco-holdings-for-dle-gr-1118215 | AC8: POSCO Holdings is a global leader in steel and battery materials; it is advancing proprietary DLE technology and securing North American lithium resources to support a resilient EV supply chain. | AD8: =IF(LEN(TRIM(AC8))=0,0,LEN(TRIM(AC8))-LEN(SUBSTITUTE(AC8," ",""))+1) -> 30
A9: 1008 | B9: Planned | C9: Upstream | D9: Arcadium Lithium | E9: No | F9: https://jamesbay.allkem.co/en/ | G9: Cathode raw materials | H9: Spodumene concentrates | I9: https://arcadiumlithium.com/ | J9: northern Québec, approximately 130 km east of James Bay and the Cree Nation of Eastmain community. | L9: QC | M9: Canada | P9: 53.536891 | Q9: -80.545652 | R9: 250 (Planned) | S9: 8100 | T9: MT contained Li/yr | U9: Arcadium Lithium | V9: https://arcadiumlithium.com/ | W9: Shannon | Y9: Ireland | Z9: VP | AA9: 44930 | AB9: https://www.mining-technology.com/news/canada-nod-galaxy-james-lithium/?cf-view; https://www.allkem.co/contact; https://iaac-aeic.gc.ca/050/evaluations/proj/80141 | AC9: Arcadium Lithium (2024 merger of Alkem and Livent) delivers sustainable lithium products globally, from resources in Argentina and Australia and conversion assets in the U.S., Asia, and the U.K. | AD9: =IF(LEN(TRIM(AC9))=0,0,LEN(TRIM(AC9))-LEN(SUBSTITUTE(AC9," ",""))+1) -> 29 | AE9: Alkem and Livent merged in 2024
A10: 1009 | B10: Pre-commercial/ startup | C10: Upstream | D10: BHE Renewables | E10: No | F10: CalEnergy Operations | G10: Direct lithium extraction | H10: Lithium | I10: https://www.bherenewables.com/ | J10: 7030 Gentry Rd | K10: Calipatria | L10: CA | M10: US | N10: 92233 | P10: 33.335889 | Q10: -115.65919 | R10: 240 | S10: 90000 | T10: MT contained Li/yr | U10: BHE Renewables | V10: https://www.bherenewables.com/ | W10: Des Moines | X10: IA | Y10: US | Z10: MK | AA10: 45649 | AB10: https://www.linkedin.com/company/forcustomersforcommunities/about/; https://www.bherenewables.com/projects/geothermal; https://www.bherenewables.com/news/customers/occidental-and-bhe-renewables-form-joint-venture--to-commercialize-terralithium-extraction-technology | AC10: BHE Renewables owns and operates renewable energy projects, including geothermal facilities, and is collaborating with Occidental to develop lithium extraction technologies. | AD10: =IF(LEN(TRIM(AC10))=0,0,LEN(TRIM(AC10))-LEN(SUBSTITUTE(AC10," ",""))+1) -> 21 | AF10: Dan Winters | AG10: dan.winters@bherenewables.com | AH10: 515-240-8395 | AI10: BHE Renewables, in partnership with Occidental and TerraLithium, is developing lithium extraction capabilities using patented Direct Lithium Extraction (DLE) technology at its Imperial Valley geothermal plants. This collaboration aims to produce high-purity lithium hydroxide and lithium carbonate to meet the rising demand for battery materials. TerraLithium's environmentally responsible approach processes brine extracted during geothermal energy production, supporting clean energy goals.
A11: 1010 | B11: Planned | C11: Upstream | D11: Canada Nickel Company | E11: No | F11: Crawford | G11: Cathode raw materials | H11: Nickel concentrates | I11: https://canadanickel.com/ | K11: Timmins | L11: ON | M11: Canada | P11: 48.476151 | Q11: -81.33084 | R11: 34 | S11: 48000 | T11: MT Ni/yr | U11: Canadian Nickel | V11: https://canadanickel.com/ | W11: Toronto | X11: ON | Y11: Canada | Z11: VP | AA11: 45463 | AB11: https://canadanickel.com/ https://northernontario.ctvnews.ca/study-shows-massive-nickel-deposit-in-northern-ont-even-more-profitable-than-expected-1.6600455; https://canadanickel.com/wp-content/uploads/2024/05/CNC_InvestorDeck_May2024_VF.pdf | AC11: Canada Nickel is advancing high-quality, high-potential nickel projects to deliver the metals to power the EV revolution and feed the stainless steel market. | AD11: =IF(LEN(TRIM(AC11))=0,0,LEN(TRIM(AC11))-LEN(SUBSTITUTE(AC11," ",""))+1) -> 23 | AE11: Average annual production is expected to be438,000 tons of nickel over the 27-year peak production lifespan. The project will also produce significant amounts of cobalt, palladium, platinum, iron and chromite. Along with our flagship Crawford Nickel Project, Canada Nickel has acquired multiple properties in the region. Unlocking the potential for a Timmins Zero Carbon Nickel District with the consolidation of twenty plus nickel targets.
A12: 1011 | B12: Planned | C12: Upstream | D12: Canadian Royalties | E12: No | F12: Nunavik Nickel Project | G12: Cathode raw materials | H12: Nickel | I12: https://www.canadianroyalties.com/ | J12: Raglan Rd | K12: Donaldson | L12: QC | M12: Canada | N12: J0M 1K0 | P12: 61.561675 | Q12: -73.42748 | R12: 380 (Planned) | U12: Canadian Royalties | V12: https://www.canadianroyalties.com/ | W12: Montreal | X12: QC | Y12: Canada | Z12: MK | AA12: 45649 | AB12: https://www.canadianroyalties.com/articles/20230418200434/towards-phase-the-nunavik-nickel-project.html; https://www.mining-technology.com/marketdata/five-largest-nickel-mines-canada-2020/ | AC12: Canadian Royalties operates one of Canada’s largest nickel mining projects, supporting the growing demand for battery materials in the electric vehicle market. | AD12: =IF(LEN(TRIM(AC12))=0,0,LEN(TRIM(AC12))-LEN(SUBSTITUTE(AC12," ",""))+1) -> 22
A13: 1012 | B13: Planned | C13: Upstream | D13: Century Lithium | E13: No | F13: Clayton Valley Lithium Project | G13: Cathode raw materials | H13: Lithium carbonate - crude | I13: https://www.centurylithium.com/ | K13: Clayton Valley | L13: NV | M13: US | N13: 89047 | P13: 37.752532 | Q13: -117.59062 | R13: 183 (Planned) | S13: 27400 | T13: MT/yr LCE | U13: Century Lithium Corp. | V13: https://www.centurylithium.com/ | W13: Vancouver | X13: BC | Y13: Canada | Z13: VP MK | AA13: 1/8/2024 2/11/2026 | AB13: Jay DB; www.centurylithium.com/_resources/technical-reports/cyp_pfs_amended_march_15th-2021.pdf?v=0.651?v=0.909?v=0.389; https://www.sudburyminingsolutions.com/top-stories/having-nickel-in-timmins-extremely-attractive-says-ceo-6601589; https://www.centurylithium.com/_resources/technical-reports/cyp_pfs_amended_march_15th-2021.pdf?v=0.483; consulting with Avicenne | AC13: Century Lithium is a Canadian-based advanced stage lithium exploration company advancing towards its goal of producing high-purity lithium carbonate for the electric vehicle and battery storage market. | AD13: =IF(LEN(TRIM(AC13))=0,0,LEN(TRIM(AC13))-LEN(SUBSTITUTE(AC13," ",""))+1) -> 27 | AE13: SOP 203x
A14: 1013 | B14: Under Construction | C14: Upstream | D14: Chevron USA | E14: No | F14: East Texas Southwest Arkansas Lithium Project | G14: Lithium | H14: Direct Lithium Extraction (DLE) | I14: https://www.chevron.com | J14: ~125,000 net acres in the Smackover Formation | L14: TX | M14: US | O14: 925-842-1000 | P14: 33.021943 | Q14: -94.060902 | U14: Chevron Corp | V14: https://www.chevron.com | W14: Houston | X14: TX | Y14: US | Z14: MK | AA14: 45867 | AB14: https://www.businesswire.com/news/home/20250617717350/en/Chevron-Enters-Domestic-Lithium-Sector-to-Support-U.S.-Energy-Security, https://www.ogj.com/energy-transition/article/55297744/chevron-enters-us-lithium-sector-with-leasehold-acquisitions | AC14: Chevron is a multinational energy corporation that has recently entered the domestic lithium sector to support U.S. energy security and expand its new energies business. | AD14: =IF(LEN(TRIM(AC14))=0,0,LEN(TRIM(AC14))-LEN(SUBSTITUTE(AC14," ",""))+1) -> 25
A15: 1014 | B15: Pre-commercial/ startup | C15: Upstream | D15: Cobalt 27 Capital Corporation | E15: No | F15: Cobalt 27 Capital Corporation | G15: Cathode raw materials | H15: Cobalt ore | I15: https://nickel28.com/ | J15: 700 West Georgia Street | K15: Vancouver | L15: BC | M15: Canada | N15: BC V7Y 1B3 | O15: 414-560-9070 | P15: 49.282945 | Q15: -123.11916 | R15: 4 | U15: Nickel 28 | V15: https://nickel28.com/ | W15: Toronto | X15: ON | Y15: Canada | Z15: VP | AA15: 45463 | AB15: https://www.nickel28.com/investors/investors-overview/cobalt-27--change-of-auditors?turl=cobalt-27--change-of-auditors#:~:text=Cobalt%2027%20Capital%20Corp.%20is,portfolio%20of%206%20cobalt%20royalties. | AC15: Cobalt 27 Capital Corp. offers pure-play exposure to cobalt for the electric vehicle and battery energy storage markets, involving a diverse portfolio of streams, royalties, and direct investments. | AD15: =IF(LEN(TRIM(AC15))=0,0,LEN(TRIM(AC15))-LEN(SUBSTITUTE(AC15," ",""))+1) -> 28 | AE15: Provider of mineral exploration services based in Toronto, Canada. The company specializes in offering exposure to metals integral to key technologies of the electric vehicle and battery energy storage markets. Has several assets in Canada, but none are operating yet.
A16: 1015 | B16: Commercial | C16: Upstream | D16: Compass Minerals | E16: No | F16: Salt, SOP and Magnesium Chloride Plants | G16: Direct lithium extraction | H16: Lithium | I16: https://www.compassminerals.com/ | J16: 765 N 10500 W | K16: Ogden | L16: UT | M16: US | N16: 84404 | O16: 801-731-3100 | P16: 41.283582 | Q16: -112.22673 | R16: 400 | S16: 11000 | T16: MT contained Li/yr | U16: Compass Minerals | V16: https://www.compassminerals.com/ | W16: Overland Park | X16: KA | Y16: US | Z16: MK | AA16: 45649 | AB16: https://investors.compassminerals.com/investors-relations/investor-news/press-release-details/2022/Compass-Minerals-Announces-Selection-of-Direct-Lithium-Extraction-DLE-Technology-Provider-Attractive-Economics-and-Positive-Sustainability-Profile-for-First-Phase-of-Lithium-Project/default.aspx; https://www.reuters.com/business/autos-transportation/compass-minerals-picks-lithium-extraction-technology-supply-ford-others-2022-09-14/; https://www.compassminerals.com/who-we-are/locations/ | AC16: Compass Minerals is a leading provider of essential minerals and is expanding its portfolio to include lithium extraction. | AD16: =IF(LEN(TRIM(AC16))=0,0,LEN(TRIM(AC16))-LEN(SUBSTITUTE(AC16," ",""))+1) -> 18 | AE16: Compass Minerals is developing a lithium extraction facility to supply Ford and other automakers with lithium carbonate and hydroxide.
A17: 1016 | B17: Pre-commercial/ startup | C17: Upstream | D17: Controlled Thermal Resources | E17: No | F17: Hell's Kitchen Lithium and Power Project | G17: Cathode raw materials | H17: Lithium carbonate - crude | I17: https://www.cthermal.com/ | J17: 124 West 9th St | K17: Imperial | L17: CA | M17: US | N17: 92251 | P17: 32.848538 | Q17: -115.57109 | R17: 50 | S17: 5800 | T17: MT contained Li/yr | U17: Controlled Thermal Resources | V17: https://www.cthermal.com/ | W17: Brisbane | X17: Qld | Y17: Australia | Z17: VP | AA17: 44865 | AB17: https://www.prnewswire.com/news-releases/gm-to-source-us-based-lithium-for-next-generation-ev-batteries-through-closed-loop-process-with-low-carbon-emissions-301324868.html. https://www.crunchbase.com/organization/controlled-thermal-resources; Questionnaire | AC17: Controlled Thermal Resource Holdings, Inc. is an American company advancing the development of lithium and battery material products and renewable energy. | AD17: =IF(LEN(TRIM(AC17))=0,0,LEN(TRIM(AC17))-LEN(SUBSTITUTE(AC17," ",""))+1) -> 21 | AE17: GM formed strategic investment and commercial collaboration to obtain lithium; Stage 1 is 20k Lithium hydroxide (5,800 MT contained Li); Facility is also listed in battery grade materials as it will make both battery grade lithium carbonate and hydroxide
A18: 1017 | B18: Planned | C18: Upstream | D18: Corporation Lithium Éléments Critiques | E18: No | F18: Rose Lithium-Tantalum project | G18: Cathode raw materials | H18: Lithium hydroxide - crude | I18: https://www.cecorp.ca/en/ | J18: 1080 Côte du Beaver Hall, Suite 2101 | K18: Montreal | L18: QC | M18: Canada | N18: H2Z 1S8 | O18: 514 904-1496 | P18: 45.502542 | Q18: -73.565493 | R18: 500 (Planned) | S18: 5727 | T18: MT contained Li/yr | U18: Corporation Lithium Éléments Critiques | V18: https://www.cecorp.ca/en/ | W18: Montreal | X18: QC | Y18: Canada | Z18: VP | AA18: 44417 | AB18: cecorp.ca/en; Propulsion Quebec | AC18: Critical Elements Lithium Corporation owns several lithium mining properties in Quebec. They seek to further their Rose Lithium-Tantalum project from advanced exploration to production. | AD18: =IF(LEN(TRIM(AC18))=0,0,LEN(TRIM(AC18))-LEN(SUBSTITUTE(AC18," ",""))+1) -> 24 | AE18: Open pit mining of hard rock lithium (spodumene) and processing to technical(6% Li2O) and chemical (5% Li2O) grades of lithium concentrate; 186,327 MT of chem grade conc and 50,205 MT of tech grade conc.; Capacity was calculated from these values
A19: 1018 | B19: Commercial | C19: Upstream | D19: Eagle Graphite | E19: No | F19: Black Crystal Graphite Quarry | G19: Anode raw materials | H19: Natural graphite | I19: https://www.eaglegraphite.com/ | K19: Slocan Park | L19: BC | M19: Canada | N19: VOG 2E0 | P19: 49.529667 | Q19: -117.61321 | R19: 8 | S19: 2500 | T19: MT | U19: Eagle Graphite | V19: https://www.eaglegraphite.com/ | W19: Toronto | X19: ON | Y19: Canada | Z19: MK | AA19: 12/23/2024 1/28/2026 | AB19: https://miningdataonline.com/property/1630/Black-Crystal-Project.aspx; https://finance.yahoo.com/news/eagle-graphite-provides-corporate-215100199.html?guccounter=1&guce_referrer=aHR0cHM6Ly9jaGF0Z3B0LmNvbS8&guce_referrer_sig=AQAAAMcZQmCC4Dpp6gcDivA2gPalxFQTTZQQ62uqbqnymiUeViK8AdyvWGENtGmHxnfMplbeOKza1E7M8kPqraSUY9NH3EVO2Gxf1wJSJCoHZ2dMKxVgl617Qnkb3nZ4mBQFejIp-eiBQJG2ZkRvdnDoGABYfJULQ4oFZuvndJZuZ4kM | AC19: Eagle Graphite is a mining company producing battery-grade graphite from its Black Crystal Quarry in British Columbia, Canada. | AD19: =IF(LEN(TRIM(AC19))=0,0,LEN(TRIM(AC19))-LEN(SUBSTITUTE(AC19," ",""))+1) -> 18 | AE19: The company is facing financial difficulties. Plan to expand to 7500 MT
A20: 1019 | B20: Pre-commercial/ startup | C20: Upstream | D20: Electric Metals (USA) Limited | E20: No | F20: Emily Manganese Project | G20: Mining & metals | H20: Manganese, iron | I20: https://electricmetals.com/ | K20: Crow Wing County | L20: MN | M20: US | O20: 303-656-9197 | P20: 46.7766 | Q20: -93.9566 | U20: Electric Metals (USA) Limited | V20: https://electricmetals.com/ | W20: Toronto | X20: ON | Y20: Canada | Z20: MK | AA20: 45872 | AB20: https://www.theassay.com/mining-company-profiles/electric-metals-usa-limited/ | AC20: Electric Metals (USA) Limited is a mineral development company focused on advancing North America's highest-grade manganese deposit to support the clean energy transition. | AD20: =IF(LEN(TRIM(AC20))=0,0,LEN(TRIM(AC20))-LEN(SUBSTITUTE(AC20," ",""))+1) -> 23 | AE20: The Emily Manganese Project is the company's flagship asset. A Preliminary Economic Assessment (PEA) is underway.
A21: 1020 | B21: Under Construction | C21: Upstream | D21: Energy Source Minerals | E21: No | F21: Project ATLis | G21: Cathode raw materials | H21: Lithium | I21: https://www.esminerals.com/atlis | J21: Salton Sea | K21: Imperial County | L21: CA | M21: US | P21: 33.313056 | Q21: -115.83444 | R21: 62 (Planned) | S21: 20000 | T21: MT Li/yr | U21: Energy Source Minerals | V21: https://www.esminerals.com/ | W21: Carlsbad | X21: CA | Y21: US | Z21: VP | AA21: 45289 | AB21: https://www.esminerals.com/ https://www.prnewswire.com/news-releases/energysource-minerals-receives-approvals-on-project-atlis-salton-sea-based-geothermal-extraction-operation-301428234.html; https://www.prnewswire.com/news-releases/energysource-minerals-esm-announces-contract-with-ford-for-geothermal-lithium-301830259.html#:~:text=Project%20ATLiS%20in%20California's%20Salton,the%20auto%20industry%20per%20year. | AC21: EnergySource Minerals is a California-based company focused on its lithium project, Project ATLiS, with environmental targets to decrease land use, water depletion, and CO2 emissions. | AD21: =IF(LEN(TRIM(AC21))=0,0,LEN(TRIM(AC21))-LEN(SUBSTITUTE(AC21," ",""))+1) -> 25
A22: 1021 | B22: Planned | C22: Upstream | D22: Exxon Mobil | E22: No | F22: Saltwerx | G22: Direct lithium extraction | H22: Lithium Brine | I22: https://corporate.exxonmobil.com/ | J22: Columbia and Lafayette Counties | K22: Magnolia | L22: AR | M22: US | N22: 71753 | P22: 33.2671 | Q22: -93.2407 | S22: 100000 | T22: MT/yr | U22: Exxon Mobile | V22: https://corporate.exxonmobil.com/ | W22: Spring | X22: TX | Y22: US | Z22: MK | AA22: 46064 | AB22: https://lowcarbon.exxonmobil.com/about-us/community/our-footprint-in-arkansas; https://corporate.exxonmobil.com/news/news-releases/2024/1120_exxonmobil-and-lg-chem-sign-mou-for-lithium-offtake; https://arkansasdeltainformer.com/u-s-oil-giants-billion-dollar-lithium-investment-set-to-transform-arkansass-smackover-formation/ | AC22: ExxonMobil is an international energy company developing a large-scale lithium business by leveraging subsurface expertise and Direct Lithium Extraction (DLE) to supply domestic battery-grade materials for electric vehicles. | AD22: =IF(LEN(TRIM(AC22))=0,0,LEN(TRIM(AC22))-LEN(SUBSTITUTE(AC22," ",""))+1) -> 28 | AE22: 2027 SOP
A23: 1022 | B23: Planned | C23: Upstream | D23: Fortune Minerals Limited | E23: No | F23: NICO Project | G23: Cathode raw materials | H23: Cobalt ore | I23: https://www.fortuneminerals.com/ | K23: Fort Smith | L23: NT | M23: Canada | N23: X0E 1 A0 | O23: 519-858-8188 | P23: 63.548012 | Q23: -116.74057 | R23: 90 (Planned) | S23: 685 | T23: MT/yr Co | U23: Fortune Minerals Limited | V23: https://www.fortuneminerals.com/ | W23: London | X23: ON | Y23: Canada | Z23: VP | AA23: 45289 | AB23: https://www.fortuneminerals.com/; https://s1.q4cdn.com/337451660/files/doc_presentations/2023/231001-fortune-minerals-nico-project-presentation.pdf; https://www.miningweekly.com/print-version/nico-goldcobaltbismuthcopper-mine-project-canada-update-2023-12-15 | AC23: Fortune Minerals Limited is a North American development stage mining company that is focused on advancing the vertically integrated NICO cobalt-gold-bismuth-copper project, in the Northwest Territories. | AD23: =IF(LEN(TRIM(AC23))=0,0,LEN(TRIM(AC23))-LEN(SUBSTITUTE(AC23," ",""))+1) -> 26 | AE23: Nico is a vertically integrated cobalt-gold-bismuth-copper project that is slated to include a mine in Northwest Territories and a hydrometallurgical refinery in Alberta. According to a 2020 development plan, an underground mine at Nico and an associated refinery to be built in Alberta would produce an average of 1,800 metric tons of battery-grade cobalt sulfate. Co back calculated from CoSO4
A24: 1023 | B24: Planned | C24: Upstream | D24: FPX Nickel | E24: No | F24: Baptiste Nickel Project | G24: Cathode raw materials | H24: Nickel concentrates | I24: https://www.fpxnickel.com/ | J24: Decar Ni District | K24: near Fort St. James | L24: BC | M24: Canada | O24: 604-681-8600 | P24: 54.446905 | Q24: -124.25567 | R24: 1100 (Planned) | S24: 59100 | T24: MT contained Ni/yr | U24: FPX Nickel Corp. | V24: https://www.fpxnickel.com/ | W24: Vancouver | X24: BC | Y24: Canada | Z24: VP | AA24: 45095 | AB24: Jay DB; https://fpxnickel.com/2022/09/fpx-nickel-to-prepare-updated-mineral-resource-estimate-for-baptiste-nickel-project-with-inclusion-of-total-nickel-cobalt-and-iron-grades/; https://fpxnickel.com/2023/05/fpx-nickel-achieves-successful-production-of-battery-grade-nickel-sulphate-from-optimized-refinery-flowsheet/; https://fpxnickel.com/wp-content/uploads/2023/04/FPX-Presentation-Q2-2023-v1-1.pdf | AC24: FPX Nickel is a nickel mining company that refines the ore by grinding it down and separating the metals. The nickel is used for nickel sulphate for EV battery cathodes. | AD24: =IF(LEN(TRIM(AC24))=0,0,LEN(TRIM(AC24))-LEN(SUBSTITUTE(AC24," ",""))+1) -> 30 | AE24: Preliminary feasibility study (PFS) is looking at supplying the stainless steel market (base case) with an option of further upgrading the concentrate to produce battery grade nickel sulfate and cobalt-rich products for electric vehicles; PFS expected in September 2023; FPX was able to make battery grade nickel sulfate using an optimized flowsheet on the lab scale
A25: 1024 | B25: Planned | C25: Upstream | D25: Frontier Lithium | E25: No | F25: PAK Lithium Project | G25: Cathode raw materials | H25: Spodumene concentrates | I25: https://www.frontierlithium.com | J25: Red Lake | K25: Red Lake | L25: ON | M25: Canada | N25: P0V 2M0 | O25: 705-897-7622 | P25: 52.6 | Q25: -93.37 | R25: 132 (Planned) | S25: 160000 | T25: MT contained Li/yr | U25: Frontier Lithium | V25: https://www.frontierlithium.com/ | W25: Val Caron | X25: ON | Y25: Canada | Z25: VP MK | AA25: 12/31/2023 2/11/2026 | AB25: https://www.cruxinvestor.com/posts/frontier-lithium-north-americas-most-advanced-lithium-company#:~:text=The%20company%20is%20advancing%20its,top%20tier%20lithium%20asset%20globally. https://www.frontierlithium.com/news; https://www.nsenergybusiness.com/projects/pak-lithium-project/; | AC25: Frontier Lithium is an emerging lithium mineral and salts company focused on the development of its 100%-owned PAK Lithium Project in Ontario. | AD25: =IF(LEN(TRIM(AC15))=0,0,LEN(TRIM(AC15))-LEN(SUBSTITUTE(AC15," ",""))+1) -> 28 | AE25: Start with spodumene concentrates and eventually lithium chemicals - Lithium Hydroxide 12,520 tons per year --Lithium carbonate 7,360 tons per year in a processing facility in the Great Lakes region of the U.S.; SOP 203x
A26: 1025 | B26: Commercial | C26: Upstream | D26: G6 Energy Corp | E26: No | F26: Kearney Mine | G26: Anode raw materials | H26: Natural graphite | I26: gsixenergy.com | K26: Kearney | L26: ON | M26: Canada | N26: P0A 0B1 | O26: 647-254-0870 | P26: 45.631667 | Q26: -79.115124 | R26: 20 | S26: 48000 | T26: MT contained graphite/yr | U26: G6 Energy Corp | V26: gsixenergy.com | W26: Toronto | X26: ON | Y26: Canada | Z26: MK | AA26: 45688 | AB26: Questionnaire | AC26: G6 Energy Corp. is a private company based in Toronto, Ontario that is developing a fully integrated natural graphite anode material producer. | AD26: =IF(LEN(TRIM(AC26))=0,0,LEN(TRIM(AC26))-LEN(SUBSTITUTE(AC26," ",""))+1) -> 22 | AE26: G6 owns a fully permitted, past producing flake graphite mine located approximately 250 km north of Toronto, Ontario, Canada. G6 Energy has also established a joint venture and technology collaboration arrangement with a South Korean process technology provider for the exclusive right to exploit both its proven processing IP for the production of spheronized purified graphite (SPG), and its extensive process and configuration expertise for the production of coated SPG (CSPG). | AF26: Ian McCallum | AG26: info@gsixenergy.com | AH26: 647-254-0870
A27: 1026 | B27: Commercial | C27: Upstream | D27: GKN Hoeganaes Gallatin | E27: No | F27: GKN Hoeganaes Gallatin | G27: Cathode raw materials | H27: Iron powder | I27: https://www.gknpm.com/en/our-businesses/gkn-hoeganaes/ | J27: 1315 Airport Road | K27: Gallatin | L27: TN | M27: US | N27: 37066 | O27: 615-451-2000 | P27: 36.372206 | Q27: -86.422458 | R27: 220 | S27: 250000 | T27: MT/year | U27: GKN Hoeganaes owned by Dowlais | V27: https://www.gknpm.com/en/our-businesses/gkn-hoeganaes/ | W27: London | Y27: UK | Z27: SD | AA27: 45429 | AB27: Questionnaire | AC27: GKN Hoeganaes Gallatin specializes in water-atomized iron powder production and material manufacturing for a variety of industries. With seven manufacturing facilities, it provides localized supply and support to customers worldwide. | AD27: =IF(LEN(TRIM(AC27))=0,0,LEN(TRIM(AC27))-LEN(SUBSTITUTE(AC27," ",""))+1) -> 30 | AF27: Kylan McQuaig | AG27: kylan.mcquaig@hoeganaes.com | AH27: 856-303-2729
A28: 1027 | B28: Commercial | C28: Upstream | D28: Glencore | E28: Yes | F28: Raglan Mine | G28: Cathode raw materials | H28: Nickel concentrates | I28: https://www.glencore.ca/en/raglan | J28: 120 Avenue De L'Aeroport | K28: Rouyn-Noranda | L28: QC | M28: Canada | N28: J9Y 0G1 | O28: 819-762-7800 | P28: 48.213817 | Q28: -78.828334 | R28: 640 | S28: 40000 | T28: MT contained Ni/yr | U28: Glencore | V28: https://www.glencore.com/ | W28: Baar | X28: Zug | Y28: Switzerland | Z28: VP | AA28: 44421 | AB28: glencore.ca; https://www.glencore.ca/en/raglan/who-we-are/at-a-glance | AC28: Glencore is one of the world’s largest global diversified natural resource companies and a major producer of more than 60 commodities, including nickel and cobalt for the lithium-ion supply chain. | AD28: =IF(LEN(TRIM(AC28))=0,0,LEN(TRIM(AC28))-LEN(SUBSTITUTE(AC28," ",""))+1) -> 30
A29: 1028 | B29: Commercial | C29: Upstream | D29: Glencore | E29: Yes | F29: Raglan Mine | G29: Cathode raw materials | H29: Cobalt concentrates | I29: https://www.glencore.ca/en/raglan | J29: 120 Avenue De L'Aeroport | K29: Rouyn-Noranda | L29: QC | M29: Canada | N29: J9Y 0G1 | O29: 819-762-7800 | P29: 48.213817 | Q29: -78.828334 | R29: 640 | S29: 827 | T29: MT contained Co/yr | U29: Glencore | V29: https://www.glencore.com/ | W29: Baar | X29: Zug | Y29: Switzerland | Z29: VP | AA29: 44421 | AB29: glencore.ca; https://www.glencore.ca/en/raglan/who-we-are/at-a-glance; https://www.glencore.ca/en/raglan/what-we-do/our-mining-activity | AC29: Glencore is one of the world’s largest global diversified natural resource companies and a major producer of more than 60 commodities, including nickel and cobalt for the lithium-ion supply chain. | AD29: =IF(LEN(TRIM(AC29))=0,0,LEN(TRIM(AC29))-LEN(SUBSTITUTE(AC29," ",""))+1) -> 30 | AE29: Production value is actual 2020 production
A30: 1029 | B30: Commercial | C30: Upstream | D30: Glencore | E30: Yes | F30: Glencore Sudbury INO | G30: Cathode raw materials | H30: Nickel matte | I30: https://www.glencore.ca/en/sudburyino | J30: 2 Longyear Dr | K30: Sudbury | L30: ON | M30: Canada | N30: P0M 1S0 | O30: 705-693-2761 | P30: 46.586931 | Q30: -80.769922 | R30: 600 | S30: 75695 | T30: MT contained metal/yr | U30: Glencore | V30: https://www.glencore.com/ | W30: Baar | X30: Zug | Y30: Switzerland | Z30: VP | AA30: 44421 | AB30: glencore.ca; https://www.yellowpages.ca/bus/Ontario/Falconbridge/Sudbury-Integrated-Nickel-Operations/100823081.html#:~:text=Sudbury%20Integrated%20Nickel%20Operations%20%2D%201%20Longyear%20Dr%2C%20Falconbridge%2C%20ON; | AC30: Glencore is one of the world’s largest global diversified natural resource companies and a major producer of more than 60 commodities, including nickel and cobalt for the lithium-ion supply chain. | AD30: =IF(LEN(TRIM(AC30))=0,0,LEN(TRIM(AC30))-LEN(SUBSTITUTE(AC30," ",""))+1) -> 30 | AE30: Sudbury INO includes 2 underground mines, 1 mill and 1 smelter; smelter also recycles aerospace and other secondary metals as well as batteries, including LIBs. Smelter is a leader in recycling pre-treated (discharged and upgraded) Li-ion batteries in North America
A31: 1030 | B31: Commercial | C31: Upstream | D31: Glencore | E31: Yes | F31: Glencore Sudbury INO | G31: Cathode raw materials | H31: Cobalt | I31: https://www.glencore.ca/en/sudburyino | J31: 2 Longyear Dr | K31: Sudbury | L31: ON | M31: Canada | N31: P0M 1S0 | O31: 705-693-2761 | P31: 46.586931 | Q31: -80.769922 | R31: 600 | S31: 400 | T31: MT contained metal/yr | U31: Glencore | V31: https://www.glencore.com/ | W31: Baar | X31: Zug | Y31: Switzerland | Z31: MK | AA31: 46064 | AB31: https://www.glencore.com/media-and-insights/news/full-year-2025-production-report; https://www.glencore.ca/en/sudburyino/what-we-do | AC31: Glencore is one of the world’s largest global diversified natural resource companies and a major producer of more than 60 commodities, including nickel and cobalt for the lithium-ion supply chain. | AD31: =IF(LEN(TRIM(AC31))=0,0,LEN(TRIM(AC31))-LEN(SUBSTITUTE(AC31," ",""))+1) -> 30
A32: 1031 | B32: Planned | C32: Upstream | D32: Graphite One | E32: No | F32: Graphite Creek | G32: Anode raw materials | H32: Graphite concentrates | I32: https://www.graphiteoneinc.com/ | K32: near Nome | L32: AK | M32: US | P32: 64.512432 | Q32: -165.42696 | R32: 200 (Planned) | S32: =60000*0.95 -> 57000 | T32: MT contained graphite/yr | U32: Graphite One | V32: https://www.graphiteoneinc.com/ | W32: Anchorage | X32: AK | Y32: US | Z32: VP | AA32: 45095 | AB32: Jay DB; PitchBook; graphiteoneinc.com; https://www.akbizmag.com/industry/alaska-native/bsnc-invests-2m-into-graphite-one/#:~:text=Capacity%20at%20the%20Graphite%20Creek,to%20200%20workers%20year%2Dround.&text=A%20proposed%20graphite%20mine%20near,the%20region's%20Alaska%20Native%20corporation. | AC32: Graphite One plans to mine, refine, and manufacture graphite for use in anodes electric car batteries. They are in the pre-feasibility stage. | AD32: =IF(LEN(TRIM(AC32))=0,0,LEN(TRIM(AC32))-LEN(SUBSTITUTE(AC32," ",""))+1) -> 22 | AE32: Company is in pre-feasibility stage; Want to develop a CSG production facility likely in WA state, but no further details were available.
A33: 1032 | B33: Planned | C33: Upstream | D33: Green Technology Metals | E33: No | F33: Flagship Seymour Project | G33: Cathode raw materials | H33: Spodumene concentrates | I33: https://www.greentm.com.au/seymour-project | J33: near the township of Armstrong | K33: Armstrong | L33: ON | M33: Canada | P33: 48.382221 | Q33: -89.2461 | U33: Green Technology Metals | V33: https://www.greentm.com.au | W33: Subiaco | X33: WA | Y33: Australia | Z33: VP | AA33: 45305 | AB33: https:/https://news; lgensol.com/company-news/press-releases/1749//www.greentm.com.au/; https://news.lgensol.com/company-news/press-releases/1749/ https://www.greentm.com.au/seymour-project; | AC33: Green Technology Metals is a North American company focused on lithium exploration and development in Ontario. It owns 10 high-grade hard rock spodumene assets. | AD33: =IF(LEN(TRIM(AC33))=0,0,LEN(TRIM(AC33))-LEN(SUBSTITUTE(AC33," ",""))+1) -> 24 | AE33: Project expected to move into development in 2024.
A34: 1033 | B34: Planned | C34: Upstream | D34: Hard Creek Nickel Corp | E34: No | F34: Turnagain Nickel Project - Phase 1 | G34: Cathode raw materials | H34: Nickel concentrates | I34: https://www.gigametals.com/ | K34: Stikine Region | L34: BC | M34: Canada | N34: V0C 2Z0 | P34: 58.474411 | Q34: -128.85263 | R34: 9 | S34: 33000 | T34: MT contained Ni/yr | U34: Giga Metals Mitsubishi Corporation | V34: https://www.gigametals.com mitsubishi.com/ | W34: Vancouver Tokyo | X34: BC Tokyo | Y34: Canada, Japan | Z34: VP | AA34: 45095 | AB34: Jay DB; gigametals.com/site/assets/files/4910/giga_metals_corporate_presentation_june_15-_2023.pdf | AC34: Hard Creek Nickel Corp is a mining and processing facility that utilizes froth floatation to separate cobalt and nickel from the raw ore. | AD34: =IF(LEN(TRIM(AC34))=0,0,LEN(TRIM(AC34))-LEN(SUBSTITUTE(AC34," ",""))+1) -> 23 | AE34: JV between Giga Metals and Mitsubishi; Pre-feasibility study July 2023; targeting Class1 Ni; $1.4B for Phase 1; Phase II would double production and cost $0.5B
A35: 1034 | B35: Planned | C35: Upstream | D35: Hard Creek Nickel Corp | E35: No | F35: Turnagain Nickel Project - Phase 1 | G35: Cathode raw materials | H35: Cobalt concentrates | I35: https://www.gigametals.com/ | K35: Stikine Region | L35: BC | M35: Canada | N35: V0C 2Z0 | P35: 58.474411 | Q35: -128.85263 | R35: 9 | S35: 1800 | T35: MT contained Co/yr | U35: Giga Metals Mitsubishi Corporation | V35: https://www.gigametals.com mitsubishi.com/ | W35: Vancouver Tokyo | X35: BC Tokyo | Y35: Canada, Japan | Z35: VP | AA35: 45095 | AB35: Jay DB; gigametals.com/site/assets/files/4910/giga_metals_corporate_presentation_june_15-_2023.pdf | AC35: Hard Creek Nickel Corp is a mining and processing facility that utilizes froth floatation to separate cobalt and nickel from the raw ore. | AD35: =IF(LEN(TRIM(AC35))=0,0,LEN(TRIM(AC35))-LEN(SUBSTITUTE(AC35," ",""))+1) -> 23 | AE35: JV between Giga Metals and Mitsubishi; Pre-feasibility study July 2023; targeting Class1 Ni; $1.4B for Phase 1; Phase II would double production and cost $0.5B
A36: 1035 | B36: Pre-commercial/ startup | C36: Upstream | D36: In-Medix, Inc | E36: No | F36: Nevada Lithium Project | G36: Lithium | H36: Lithium | I36: https://www.exideindustries.com/ | L36: NV | M36: US | U36: Exide Industries Ltd | V36: https://www.exideindustries.com/ | W36: Kolkata | X36: West Bengal | Y36: India | Z36: MK | AA36: 45872 | AB36: https://economictimes.indiatimes.com/industry/renewables/exide-outlines-growth-strategy-with-dual-focus-on-lead-acid-lithium-ion-batteries/articleshow/122922132.cms, https://www.google.com/search?q=https://www.bseindia.com/xml-data/corpfiling/AttachLive/4ce415e9-4977-4df3-883a-8fc4d18721c1.pdf | AC36: Exide Industries is India's largest manufacturer of storage batteries, with a strategy to expand into lithium-ion cell production and secure raw material supply chains. | AD36: =IF(LEN(TRIM(AC36))=0,0,LEN(TRIM(AC36))-LEN(SUBSTITUTE(AC36," ",""))+1) -> 24 | AE36: Exide Industries of India has acquired a significant equity stake in In-Medix, Inc., giving them access to lithium mining assets in Nevada to secure raw materials for their li-ion business
A37: 1036 | B37: Planned | C37: Upstream | D37: Ioneer | E37: No | F37: Rhyolite Ridge Project | G37: Mining & metals | H37: Lithium Carbonate & Boric acid | I37: https://www.ioneer.com/rhyolite-ridge-project/ | J37: Coyote Hole | K37: Esmeralda County | L37: NV | M37: US | N37: 89010 | O37: 725-212-4060 | P37: 37.8647 | Q37: -117.8285 | R37: 600 | S37: 24500 | T37: MT contained Li/yr | U37: Ioneer | V37: https://www.ioneer.com/ | W37: North Sydney | X37: NSW | Y37: Australia | Z37: MK | AA37: 46093 | AB37: https://www.ioneer.com/wp-content/uploads/2025/12/Ioneer_Year_End_2025_Release_FINAL.pdf; https://www.industrialinfo.com/ | AC37: Ioneer Ltd is an Australian-headquartered critical minerals developer focused on supplying battery-grade lithium and boron to the EV supply chain. | AD37: =IF(LEN(TRIM(AC37))=0,0,LEN(TRIM(AC37))-LEN(SUBSTITUTE(AC37," ",""))+1) -> 20
A38: 1037 | B38: Commercial | C38: Upstream | D38: Ionic Mineral Technologies | E38: Yes | F38: Provo Production Campus | G38: Anode raw materials | H38: Nano-silicon | I38: https://ionicmt.com/ | J38: 652 S Lakeview Parkway, Bldg B | K38: Provo | L38: UT | M38: US | N38: 84601 | O38: 385-241-2320 | P38: 40.22498 | Q38: -111.71384 | R38: 11 | S38: 2000 | T38: MT Nano-silicon Anode active material | U38: Ionic Mineral Technologies | V38: https://ionicmt.com/ | W38: Provo | X38: UT | Y38: US | Z38: VP | AA38: 45289 | AB38: Questionnaire; https://ionicmt.com/ | AC38: Ionic Mineral Technologies is a vertically-integrated company supplying naturally derived, drop-in anode materials using a patented technology. Ionic Mineral Technologies owns the highest purity deposit of nano-structured clay. | AD38: =IF(LEN(TRIM(AC38))=0,0,LEN(TRIM(AC38))-LEN(SUBSTITUTE(AC38," ",""))+1) -> 28 | AE38: Expected to increase to 25,000 MT in 2027
A39: 1038 | B39: Under construction | C39: Upstream | D39: Jervois Mining | E39: No | F39: Idaho Cobalt Project | G39: Cathode raw materials | H39: Cobalt concentrates | I39: https://www.jervoisidahocobalt.com/ | K39: Lemhi County | L39: ID | M39: US | O39: 208-756-4578 | P39: 45.130677 | Q39: -114.36158 | R39: 38 | S39: 1915 | T39: MT contained Ni/yr | U39: Jervois Mining | V39: https://www.jervoisglobal.com/ | W39: Hawthorn | X39: VIC | Y39: Australia | Z39: VP | AA39: 45092 | AB39: jervoisidahocobalt.com; jervoisglobal.com; BNEF: US Supply Chain Security; https://jervoisglobal.com/wp-content/uploads/2021/06/190348_Idaho_Cobalt_13112020_NI_43_101_Technical_Report-FILED-r1.pdf; https://wcsecure.weblink.com.au/pdf/JRV/02549021.pdf | AC39: Jervois Mining is constructing a nickel and cobalt refinery and mining company. The cobalt is refined into cobalt oxide and cobalt sulfate for use as a cathode precursor. | AD39: =IF(LEN(TRIM(AC39))=0,0,LEN(TRIM(AC39))-LEN(SUBSTITUTE(AC39," ",""))+1) -> 28 | AE39: Facility will produce cobalt concentrate with gold and copper concentrate; Final construction was suspended due to inflation and low Co prices
A40: 1039 | B40: Planned | C40: Upstream | D40: Jindalee Lithium | E40: No | F40: McDermitt Lithium Project | G40: Cathode raw materials | H40: Lithium | I40: https://www.jindaleelithium.com | J40: Malheur County | K40: McDermitt | L40: NV | M40: US | P40: 42.001389 | Q40: -117.99667 | R40: 5 | S40: =21500000/43/5.23 -> 95602.294 | T40: MT contained Li/yr | U40: Jindalee Lithium | V40: https://www.jindaleelithium.com | W40: West Perth | X40: Western Australia | Y40: Australia | Z40: VP | AA40: 45289 | AB40: https://www.jindaleelithium.com https://www.miningweekly.com/article/mcdermitt-lithium-project-us-update-2023-10-20; https://s3.ap-southeast-2.amazonaws.com/assets.jindaleelithium.com/app/uploads/2023/10/23083152/2023-AGM-Presentationv2.pdf | AC40: Jindalee Lithium aims to develop the company’s flagship McDermitt Lithium Project, supplying a resource vital to the electrification of America’s automotive industry. | AD40: =IF(LEN(TRIM(AC40))=0,0,LEN(TRIM(AC40))-LEN(SUBSTITUTE(AC40," ",""))+1) -> 22 | AE40: McDermitt is the biggest lithium deposit in the US by contained lithium, with 21.5-million tons of lithium carbonate equivalent in mineral resource. Assumed 43 year mine life to get annual production
A41: 1040 | B41: Planned | C41: Upstream | D41: Lilac Solutions, Inc. | E41: No | F41: Lilac Solutions, Inc. | G41: Cathode raw materials | H41: Lithium | I41: https://www.lilacsolutions.com/ | K41: Box Elder County | L41: UT | M41: US | N41: 94607 | O41: 401-714-7906 | P41: 41.558967 | Q41: -113.15636 | R41: 250 (Planned) | U41: Lilac Solutions, Inc. | V41: https://www.lilacsolutions.com/ | W41: Oakland | X41: CA | Y41: US | Z41: VP MK | AA41: 12/4/2022 3/12/2026 | AB41: https://www.energy.gov/mesc/bipartisan-infrastructure-law-battery-materials-processing-and-battery-manufacturing-recycling; https://lilacsolutions.com/2022/07/lilac-solutions-continues-to-advance-world-class-kachi-lithium-project-with-lake-resources/ | AC41: Lilac Solutions is a company that plans to extract lithium from brine for use in lithium-ion batteries. | AD41: =IF(LEN(TRIM(AC41))=0,0,LEN(TRIM(AC41))-LEN(SUBSTITUTE(AC41," ",""))+1) -> 17 | AE41: Developer of lithium extraction technology designed to absorb lithium from brine resources. The company's technology is based on the ion-exchange theory that facilitates the production of lithium from brine resources with minimal cost and low environmental footprint, enabling lithium producers to accelerate project development, boost lithium recovery, streamline operations and unlock new resources. Recipient of $50M from DE-FOA-2678 to demonstrate their technology; 202x SOP; Signed binding offtake agreement with Traxys for 10 years
A42: 1041 | B42: Under construction | C42: Upstream | D42: Lithium Americas | E42: No | F42: Thacker Pass | G42: Cathode raw materials | H42: Lithium Sedimentary | I42: https://www.lithiumamericas.com/ | J42: Orovada (nearest town) | K42: Humboldt County | L42: NV | M42: US | O42: 778-656-5820 | P42: 41.569975 | Q42: -117.78581 | R42: 65 | S42: 5640 | T42: MT contained Li/yr | U42: Lithium Americas Corp. | V42: https://www.lithiumamericas.com; https://www.lithiumamericas.com/_resources/pdf/investors/technical-reports/thacker-pass/Technical-Report-Thacker-Pass.pdf/ | W42: Vancouver | X42: BC | Y42: Canada | Z42: VP MK | AA42: 6/15/2023 3/12/2026 | AB42: lithiumamericas.com; BNEF: US Supply Chain Security, https://www.macrotrends.net/stocks/charts/LAC/lithium-americas/number-of-employees;https://lithiumamericas.com/usa/thacker-pass/ | AC42: Lithium Americas plans to use block mining to extract lithium ore. The ore will be processed using leaching techniques to produce battery grade lithium carbonate for cathodes. | AD42: =IF(LEN(TRIM(AC42))=0,0,LEN(TRIM(AC42))-LEN(SUBSTITUTE(AC42," ",""))+1) -> 27 | AE42: Q4 2026 SOP; making progress with construction
A43: 1042 | B43: Pre-commercial/ startup | C43: Upstream | D43: LithiumBank Resources | E43: No | F43: Boardwalk Lithium Brine Project | G43: Direct lithium extraction | H43: Lithium hydroxide monohydrate | I43: https://www.lithiumbank.ca/ | K43: Sturgeon Lake | L43: AB | M43: Canada | N43: T0H 3N0 | P43: 54.5 | Q43: -118.5 | R43: 4 | S43: 34005 | T43: MT contained Li/yr | U43: LithiumBank Resources | V43: https://www.lithiumbank.ca/ | W43: Calgary | X43: AB | Y43: Canada | Z43: MK | AA43: 45649 | AB43: https://www.lithiumbank.ca/news/lithiumbank-announces-updated-pea-significantly-increases-pre-tax-npv8-to-usd-3-7-billion-and-reduces-opex-to-usd-4-588-per-lce-t-at-flagship-boardwalk-lithium-brine-project-alberta-canada; https://www.lithiumbank.ca/projects/boardwalk | AC43: LithiumBank Resources Corp. is a publicly traded company focused on developing its flagship projects, Boardwalk and Park Place, in Western Canada. | AD43: =IF(LEN(TRIM(AC43))=0,0,LEN(TRIM(AC43))-LEN(SUBSTITUTE(AC43," ",""))+1) -> 21 | AE43: The Boardwalk Project encompasses approximately 572,237 acres, covering 100% of the Leduc reef complex.
A44: 1043 | B44: Pre-commercial/ startup | C44: Upstream | D44: LithiumBank Resources | E44: No | F44: Park Place Lithium Brine Project | G44: Direct lithium extraction | H44: Lithium hydroxide monohydrate | I44: https://www.lithiumbank.ca/ | K44: Fox Creek | L44: AB | M44: Canada | N44: T0H 0A6 | P44: 54.41168 | Q44: -116.80777 | R44: 4 | U44: LithiumBank Resources | V44: https://www.lithiumbank.ca/ | W44: Calgary | X44: AB | Y44: Canada | Z44: MK | AA44: 45667 | AB44: https://www.lithiumbank.ca/news/lithiumbank-announces-updated-pea-significantly-increases-pre-tax-npv8-to-usd-3-7-billion-and-reduces-opex-to-usd-4-588-per-lce-t-at-flagship-boardwalk-lithium-brine-project-alberta-canada; https://www.lithiumbank.ca/projects/park-place | AC44: LithiumBank Resources Corp. is a publicly traded cused on developing its flagship projects, Boardwalk and Park Place, in Western Canada. | AD44: =IF(LEN(TRIM(AC44))=0,0,LEN(TRIM(AC44))-LEN(SUBSTITUTE(AC44," ",""))+1) -> 20 | AE44: The Park Place project encompasses approximately 1,404,558 acres.
A45: 1044 | B45: Commercial | C45: Upstream | D45: Lundin Mining | E45: No | F45: Eagle Mine | G45: Cathode raw materials | H45: Nickel ore | I45: https://www.lundinmining.com/operations/eagle/ | K45: Michigamme Township | L45: MI | M45: US | O45: 906-339-7000 | P45: 46.750162 | Q45: -87.899989 | R45: 200 | S45: 19000 | T45: MT contained Ni/yr | U45: Lundin Mining | V45: https://www.lundinmining.com/ | W45: Toronto | X45: ON | Y45: Canada | Z45: VP | AA45: 44422 | AB45: BNEF: Interactive Datasets / Metals/ Mine Assets Map/ Nickel; lundinmining.com; https://www.lundinmining.com/site/assets/files/3640/2017-04-26-eagle-ni-43-101.pdf | AC45: Lundin Mining mines and processes copper and nickel ore. The nickel ore is ground down and separated to be used for cathodes. | AD45: =IF(LEN(TRIM(AC45))=0,0,LEN(TRIM(AC45))-LEN(SUBSTITUTE(AC45," ",""))+1) -> 22 | AE45: Ni-Cu mine.
A46: 1045 | B46: Commercial | C46: Upstream | D46: Lundin Mining | E46: No | F46: Humboldt mill | G46: Cathode raw materials | H46: Nickel concentrates | I46: https://www.lundinmining.com/operations/eagle/ | J46: 4547 County Rd 601 | K46: Champion | L46: MI | M46: US | N46: 49814 | O46: 906-339-7000 | P46: 46.484071 | Q46: -87.898236 | R46: 200 | S46: 19000 | T46: MT contained Ni/yr | U46: Lundin Mining | V46: https://www.lundinmining.com/ | W46: Toronto | X46: ON | Y46: Canada | Z46: VP | AA46: 44422 | AB46: BNEF: Interactive Datasets / Metals/ Mine Assets Map/ Nickel; lundinmining.com; https://im-mining.com/2018/03/08/43017/; https://www.lundinmining.com/site/assets/files/3640/2017-04-26-eagle-ni-43-101.pdf | AC46: Lundin Mining mines and processes copper and nickel ore. The nickel ore is ground down and separated to be used for cathodes. | AD46: =IF(LEN(TRIM(AC46))=0,0,LEN(TRIM(AC46))-LEN(SUBSTITUTE(AC46," ",""))+1) -> 22 | AE46: Re-purposed iron ore mill; Processes Cu and Ni ore from Eagle mine
A47: 1046 | B47: Pre-commercial/ startup | C47: Upstream | D47: Manganese X Energy Corp. | E47: No | F47: Battery Hill Project | G47: Cathode raw materials | H47: Manganese concentrates | I47: https://www.manganesexenergycorp.com/ | J47: Jacksonville (nearest town) | K47: Jacksonville | L47: NB | M47: Canada | O47: 514-802-1814 | P47: 46.200426 | Q47: -67.632821 | U47: Manganese X Energy Corp. | V47: https://www.manganesexenergycorp.com/ | W47: Saint-Laurent | X47: QC | Y47: Canada | Z47: VP | AA47: 44422 | AB47: manganesexenergycorp.com; Propulsion Quebec; https://www.manganesexenergycorp.com/wp-content/uploads/2020/09/Battery-Hill.pdf | AC47: Manganese X Energy is a manganese, iron, and carbon mine. Products include manganese sulphate as a cathode precursor and graphite for anodes. | AD47: =IF(LEN(TRIM(AC47))=0,0,LEN(TRIM(AC47))-LEN(SUBSTITUTE(AC47," ",""))+1) -> 22 | AE47: Pilot plant and Preliminary Economic Assessment (PEA) in 2021; Demo plant and Feasibility Study in 2022; GPS is approximate center of claim and from Battery-Hill.pdf
A48: 1047 | B48: Pre-commercial/ startup | C48: Upstream | D48: Manganese X Energy Corp. | E48: No | F48: Lac Aux Bouleaux Graphite Property | G48: Anode raw materials | H48: Natural graphite | I48: https://www.manganesexenergycorp.com/ | J48: Mont-Laurier (nearest town) | K48: Mont-Laurier | L48: QC | M48: Canada | O48: 514-802-1814 | P48: 46.549238 | Q48: -75.504014 | U48: Manganese X Energy Corp. | V48: https://www.manganesexenergycorp.com/ | W48: Saint-Laurent | X48: QC | Y48: Canada | Z48: VP | AA48: 44422 | AB48: manganesexenergycorp.com; Propulsion Quebec | AC48: Manganese X Energy is a manganese, iron, and carbon mine. Products produced include manganese sulphate as a cathode precursor and graphite for anodes. | AD48: =IF(LEN(TRIM(AC48))=0,0,LEN(TRIM(AC48))-LEN(SUBSTITUTE(AC48," ",""))+1) -> 23 | AE48: Mont-Laurier used for GPS; Very early project; No economic assessment or projection of development
A49: 1048 | B49: Pre-commercial/ startup | C49: Upstream | D49: Manganese X Energy Corp. | E49: No | F49: Woodstock MXE | G49: Cathode raw materials | H49: Manganese concentrates | I49: https://www.manganesexenergycorp.com/ | J49: Woodstock (nearest town) | K49: Woodstock | L49: NB | M49: Canada | O49: 514-802-1814 | P49: 46.200434 | Q49: -67.632746 | R49: 223 | S49: 2000 | T49: MT/yr electrolytic manganese metal | U49: Manganese X Energy Corp. | V49: https://www.manganesexenergycorp.com/ | W49: Saint-Laurent | X49: QC | Y49: Canada | Z49: VP | AA49: 45290 | AB49: manganesexenergycorp.com; Propulsion Quebec; https://www.manganesexenergycorp.com/wp-content/uploads/2020/09/WOODSTOCK.pdf; https://www.newswire.ca/news-releases/minco-announces-positive-economic-assessment-on-woodstock-manganese-project-514932301.html | AC49: Manganese X Energy is a manganese, iron, and carbon mine. Products include manganese sulphate as a cathode precursor and graphite for anodes. | AD49: =IF(LEN(TRIM(AC49))=0,0,LEN(TRIM(AC49))-LEN(SUBSTITUTE(AC49," ",""))+1) -> 22 | AE49: GPS coordinates from Woodstock MXE technical report and refer to center of claim; Very early project; No economic assessment or projection of development
A50: 1049 | B50: Planned | C50: Upstream | D50: Mason Resources | E50: No | F50: Lac Gueret | G50: Anode raw materials | H50: Natural graphite | I50: https://masonresourcesinc.com/asset/lac-gueret-graphite-project/ | J50: La Gueret | K50: Manicouagan Regional County Municipality | L50: QC | M50: Canada | P50: 51.123248 | Q50: -69.064514 | R50: 100 | S50: 51900 | T50: MT graphite/yr | U50: Mason Resources | V50: https://masonresourcesinc.com/ | W50: Toronto | X50: ON | Y50: Canada | Z50: VP | AA50: 45290 | AB50: https://masonresourcesinc.com/about-us/; https://masonresourcesinc.com/asset/lac-gueret-graphite-project/ | AC50: Mason Resources focuses on identifying, evaluating, and pursuing business investment opportunities. Its strategy is to develop vertical and horizontal integration in the mining industry. | AD50: =IF(LEN(TRIM(AC50))=0,0,LEN(TRIM(AC50))-LEN(SUBSTITUTE(AC50," ",""))+1) -> 24
A51: 1050 | B51: Commercial | C51: Upstream | D51: Minera y Metalúrgica del Boleo | E51: No | F51: El Boleo Mine | G51: Cathode raw materials | H51: Cobalt concentrates | I51: https://www.mmboleo.com/ | J51: Carretera Transpeninsular, 1 Km 5.5 | K51: Santa Rosalía | L51: Baja California Sur | M51: Mexico | N51: 23920 | O51: +52 (615) 155-2200 | P51: 27.3337 | Q51: 112.3309 | R51: 1200 | S51: 800 | T51: MT/yr | U51: Korea Mine Rehabilitation and Mineral Resources | V51: https://www.komir.or.kr/ | W51: Wonju | X51: Gangwon | Y51: South Korea | Z51: MK | AA51: 46064 | AB51: https://biz.chosun.com/; https://mexicobusiness.news/; Avicenne consulting | AC51: Minera y Metalúrgica del Boleo operates an industrial mining complex specializing in high-purity copper cathodes and metallic cobalt using advanced hydrometallurgical leaching and on-site power and desalination infrastructure. | AD51: =IF(LEN(TRIM(AC51))=0,0,LEN(TRIM(AC51))-LEN(SUBSTITUTE(AC51," ",""))+1) -> 28 | AE51: As of early 2026, the majority owner, KOMIR, is actively seeking to divest its nearly 94% stake in the operating company (MMB); In 2025, MMB submitted an EIA to Mexican authorities to expand the mining area from 446 hectares to over 757 hectares. If approved, could significantly extend the mine life beyond the current 2040 projection
A52: 1051 | B52: Commercial | C52: Upstream | D52: Missouri Cobalt LLC | E52: No | F52: Madison mine | G52: Cathode raw materials | H52: Cobalt concentrates | I52: https://www.mocobalt.com/ | J52: 401 N Mine La Motte Ave | K52: Fredericktown | L52: MO | M52: US | N52: 63645 | P52: 37.565097 | Q52: -90.292589 | R52: 50 | S52: 300 | T52: MT/day Co concentrate | U52: US Strategic Metals LLC | V52: https://www.usstrategicmetals.com/ | W52: St. Louis | X52: MO | Y52: US | Z52: VP | AA52: 45094 | AB52: mocobalt.com; Pitchbook; https://dailyjournalonline.com/community/democrat-news/we-are-going-to-see-this-project-to-the-end/article_e4c14013-c103-5816-b2fc-a9f6b78afa0a.html | AC52: Missouri Cobalt mines and process cobalt, nickel, and copper ore. Ores are separated using froth floatation. | AD52: =IF(LEN(TRIM(AC52))=0,0,LEN(TRIM(AC52))-LEN(SUBSTITUTE(AC52," ",""))+1) -> 16 | AE52: Currently cleaning up a superfund site and processing tailings for Co concentrate; 50 employees conduct the cleanup. Currently shutdown until cleanup is complete. Looking to operate a hydrometallurgical facility in Q4 2023 and employ 250 people.
